Workbook
Name AssetName: 'Control Panel'!$B$6
Name RunDate: 'Control Panel'!$B$7
Name AcquisitionDate: 'Control Panel'!$B$8
Name DispositionDate: 'Control Panel'!$B$9
Name HoldMonths: 'Control Panel'!$B$10
Name HoldYears: 'Control Panel'!$B$11
Name BusinessPlanMode: 'Control Panel'!$B$14
Name PriceMode: 'Control Panel'!$B$15
Name TargetReturnBasis: 'Control Panel'!$B$16
Name TargetReturnValue: 'Control Panel'!$B$17
Name RefiOn: 'Control Panel'!$B$18
Name DebtStructure: 'Control Panel'!$B$19
Name Use_LTV: 'Control Panel'!$B$20
Name Use_LTC: 'Control Panel'!$B$21
Name Use_DSCR: 'Control Panel'!$B$22
Name Use_DY: 'Control Panel'!$B$23
Name LoanRateType: 'Control Panel'!$B$24
Name RetailLeaseStructure: 'Control Panel'!$B$25
Name RecoveryMethod: 'Control Panel'!$B$26
Name AdminFeeOn: 'Control Panel'!$B$27
Name GrossUpOn: 'Control Panel'!$B$28
Name ExitValMethod: 'Control Panel'!$B$29
Name ExitNOIBasis: 'Control Panel'!$B$30
Name TaxMethod: 'Control Panel'!$B$31
Name AcqFeeOn: 'Control Panel'!$B$32
Name AMFeeOn: 'Control Panel'!$B$33
Name AMFeeBasis: 'Control Panel'!$B$34
Name DispFeeOn: 'Control Panel'!$B$35
Name GPCatchUpOn: 'Control Panel'!$B$36
Name LP_Present: 'Control Panel'!$B$37
Name Fund_Repairs: 'Control Panel'!$B$40
Name Fund_Reno: 'Control Panel'!$B$41
Name Fund_TILC: 'Control Panel'!$B$42
Name Fund_Contingency: 'Control Panel'!$B$43
Name ModelStatus: 'Control Panel'!$B$46
Name InputPrice: Assumptions!$B$6
Name SolvedPrice: Assumptions!$B$7
Name PurchasePrice: Assumptions!$B$8
Name ClosingCostPct: Assumptions!$B$9
Name DispCostPct: Assumptions!$B$10
Name ExitCapBlended: Assumptions!$B$13
Name ExitCapMF: Assumptions!$B$14
Name ExitCapRetail: Assumptions!$B$15
Name MF_Vacancy: Assumptions!$B$18
Name MF_Concessions: Assumptions!$B$19
Name MF_BadDebt: Assumptions!$B$20
Name LTL_Months: Assumptions!$B$21
Name RenoPremium: Assumptions!$B$24
Name RenoPace: Assumptions!$B$25
Name RenoCostUnit: Assumptions!$B$26
Name RenoDowntime: Assumptions!$B$27
Name LeaseUpStartOcc: Assumptions!$B$28
Name StabilizedOcc: Assumptions!$B$29
Name LeaseUpAbsorption: Assumptions!$B$30
Name RetailGenVacancy: Assumptions!$B$33
Name RetailCreditLoss: Assumptions!$B$34
Name RetailRenewalProb: Assumptions!$B$35
Name RetailDowntime: Assumptions!$B$36
Name RenewalRentFactor: Assumptions!$B$37
Name NewLeaseTI: Assumptions!$B$38

Sheet Control Panel
A1: CONTROL PANEL — Master Toggles
A2: Asset: | B2: =AssetName | D2: Run date: | E2: =RunDate | G2: Business plan: | H2: =BusinessPlanMode | J2: Hold (mo): | K2: =HoldMonths
A3: Model status: | B3: =ModelStatus
A5: Header / identity
A6: Asset Name | B6: Maplewood Commons
A7: Run Date | B7: 46189
A8: Acquisition Date | B8: 46204
A9: Disposition Date | B9: 48030
A10: Hold (months) | B10: =(YEAR(DispositionDate)-YEAR(AcquisitionDate))*12+MONTH(DispositionDate)-MONTH(AcquisitionDate)
A11: Hold (years) | B11: =HoldMonths/12
A13: Master toggles (referenced by name everywhere)
A14: 1. Business Plan Mode | B14: Value-Add | C14: Stabilized | Value-Add | Core-Plus Lease-Up
A15: 3. Price Mode | B15: Input Price | C15: Input Price | Solve for Target Return
A16: 4. Target Return Basis | B16: Levered IRR | C16: Levered IRR | Unlevered IRR | Untrended YoC
A17: 4b. Target Return Value | B17: 0.15 | C17: target metric value (e.g. 0.15 = 15% IRR)
A18: 5. Refi | B18: Off | C18: On | Off
A19: 6. Debt Structure | B19: Single Blended Loan | C19: Single Blended Loan | Separate MF + Retail Loans
A20: 7a. Sizing: LTV constraint | B20: On | C20: On | Off
A21: 7b. Sizing: LTC constraint | B21: On | C21: On | Off
A22: 7c. Sizing: DSCR constraint | B22: On | C22: On | Off
A23: 7d. Sizing: Debt Yield constraint | B23: On | C23: On | Off
A24: 8. Loan Rate Type | B24: Fixed | C24: Fixed | Floating (SOFR + spread)
A25: 9. Retail Lease Structure (global) | B25: NNN | C25: NNN | Gross | Modified Gross
A26: 10. Recovery Method | B26: Pro-rata | C26: Pro-rata
A27: 10a. Admin Fee | B27: On | C27: On | Off
A28: 10b. Gross-Up | B28: On | C28: On | Off
A29: 11. Exit Valuation Method | B29: Blended Cap on Total NOI | C29: Blended Cap on Total NOI | Component Caps
... A37: 17. LP Present | B37: Yes | C37: Yes | No
A39: Capital budget funding (per bucket): Equity | Financed
A40: 14a. Immediate/Deferred Repairs funding | B40: Financed | C40: Equity | Financed
A41: 14b. Value-Add Unit Renovation funding | B41: Financed | C41: Equity | Financed
A42: 14c. Retail TI/LC reserve funding | B42: Financed | C42: Equity | Financed
A43: 14d. Contingency funding | B43: Equity | C43: Equity | Financed
A45: Model status (red on any failed check)
A46: Model Status | B46: =IF(Summary!$B$3=TRUE,"OK","CHECK FAILED")

Sheet Summary
A1: SUMMARY / RETURNS
A2: Asset: | B2: =AssetName | D2: Run date: | E2: =RunDate | G2: Business plan: | H2: =BusinessPlanMode | J2: Hold (mo): | K2: =HoldMonths
A3: All-checks-pass flag | B3: =AND(ABS(SourcesTotal-UsesTotal)<1,ABS(WF_Check-TotalLeveredCF)<MAX(1,ABS(TotalLeveredCF))*0.001,LoanAmount>=0)
A5: Deal snapshot
A6: Purchase price ($) | B6: =PurchasePrice
A7: $/unit | B7: =PurchasePrice/MF_UnitCount
A8: $/SF (total) | B8: =PurchasePrice/(MF_TotalSF+Retail_GLA)
A9: MF units | B9: =MF_UnitCount
A10: Retail GLA (SF) | B10: =Retail_GLA
A11: Going-in cap (%) | B11: =GoingInCap
A12: Stabilized cap (%) | B12: =StabCap
A13: Business plan | B13: =BusinessPlanMode
A15: Sources & Uses
A16: USES
A17: Purchase price | B17: =PurchasePrice
A18: Closing / transaction costs | B18: =PurchasePrice*ClosingCostPct
A19: Capital budget | B19: =TotalCapBudget
A20: Financing costs | B20: =FinancingCosts
A21: Total uses | B21: =SUM(B17:B20)
A23: SOURCES
A24: Loan proceeds | B24: =LoanAmount
A25: Equity | B25: =InitialEquity
A26: Total sources | B26: =SUM(B24:B25)
A28: Returns
A29: Unlevered IRR (%) | B29: =XIRR('Monthly CF'!E$25:DT$25,'Monthly CF'!E$6:DT$6)
A30: Levered IRR (%) | B30: =LeveredIRR
A31: Equity multiple (x) | B31: =EquityMultiple
A32: Yield-on-cost (%) | B32: =YieldOnCost
A33: Exit cap (blended) (%) | B33: =ExitCapBlended
A34: Development spread (bps) | B34: =DevSpread
A35: Loan amount ($) | B35: =LoanAmount
A36: Binding constraint | B36: =BindingConstraint
A37: Initial equity ($) | B37: =InitialEquity
A39: Partner returns (waterfall)
A40: LP IRR (%) | B40: =LP_IRR
A41: GP IRR (%) | B41: =GP_IRR
A42: LP equity multiple (x) | B42: =LP_EM
A43: GP promote ($) | B43: =GPPromote
A44: LP distributions ($) | B44: =LPDist
A45: GP distributions ($) | B45: =GPDist
A47: Acceptance checks
A48: Sources = Uses? | B48: =ABS(SourcesTotal-UsesTotal)<1
A49: Waterfall ties to levered CF? | B49: =ABS(WF_Check-TotalLeveredCF)<MAX(1,ABS(TotalLeveredCF))*0.001
A50: Loan non-negative? | B50: =LoanAmount>=0

Sheet Assumptions
A1: ASSUMPTIONS — Global Drivers & Growth Block
A2: Asset: | B2: =AssetName | D2: Run date: | E2: =RunDate | G2: Business plan: | H2: =BusinessPlanMode | J2: Hold (mo): | K2: =HoldMonths
A3: Model status: | B3: =ModelStatus
A5: Pricing & cost
A6: Input Purchase Price ($) | B6: 48000000
A7: Solved Max-Bid Price ($) [Python binary search] | B7: 48000000
A8: Active Purchase Price ($) | B8: =IF(PriceMode="Solve for Target Return",SolvedPrice,InputPrice)
A9: Closing / transaction cost (% of price) | B9: 0.018
A10: Disposition cost (% of sale) | B10: 0.015
A12: Exit assumptions
A13: Exit cap — blended (%) | B13: 0.055
A14: Exit cap — MF component (%) | B14: 0.0525
A15: Exit cap — Retail component (%) | B15: 0.0675
A17: MF operating assumptions
A18: Economic vacancy (% of GPR) | B18: 0.05
A19: Concessions (% of GPR) | B19: 0.01
A20: Bad debt (% of GPR) | B20: 0.005
A21: Loss-to-lease burn-off (months to market) | B21: 12
A23: Value-Add / Core-Plus ramps
A24: Renovation premium ($/unit/mo) | B24: 250
A25: Renovation pace (units/month) | B25: 4
A26: Renovation cost ($/unit) | B26: 18000
A27: Renovation downtime (months/unit) | B27: 1
A28: Lease-up: start occupancy (%) | B28: 0.7
A29: Lease-up: stabilized occupancy (%) | B29: 0.95
A30: Lease-up: absorption (units/month) | B30: 6
A32: Retail assumptions
A33: Retail general vacancy (% of retail income) | B33: 0.05
A34: Retail credit loss / bad debt (%) | B34: 0.01
A35: Retail renewal probability (%) | B35: 0.7
A36: Retail re-let downtime (months) | B36: 6
A37: Renewal rent factor (% of market) | B37: 1
A38: New-lease TI ($/SF) | B38: 50
A39: Renewal TI ($/SF) | B39: 15
A40: Leasing commission (% of lease value) | B40: 0.05
A41: Admin fee (% of recoveries) | B41: 0.15
A43: OpEx
A44: Management fee (% of EGI) | B44: 0.03
A45: Replacement reserves ($/unit/yr) | B45: 300
A47: Taxes
A48: Mill rate (tax per $ assessed) | B48: 0.0185
A49: Assessment ratio (% of value) | B49: 0.9
A50: Tax flat growth (%/yr) | B50: 0.03
A51: Base annual tax ($) [year 1] | B51: 720000
A52: PILOT annual tax ($) [flat schedule proxy] | B52: 350000
A54: GROWTH BLOCK — annual vectors (year-over-year)
A55: Vector \ Year | E55: Y1 | F55: Y2 | G55: Y3 | H55: Y4 | I55: Y5 | J55: Y6 | K55: Y7 | L55: Y8 | M55: Y9 | N55: Y10 | O55: Y11
A56: MF market rent growth | E56: 0.04 | F56: 0.04 | G56: 0.035 | H56: 0.03 | I56: 0.03 | J56: 0.03 | K56: 0.03 | L56: 0.03 | M56: 0.03 | N56: 0.03 | O56: 0.03
A57: Retail market rent growth | E57: 0.025 | F57: 0.0275 | G57: 0.03 | H57: 0.03 | I57: 0.03 | J57: 0.03 | K57: 0.03 | L57: 0.03 | M57: 0.03 | N57: 0.03 | O57: 0.03
A58: OpEx / general inflation | E58: 0.03 | F58: 0.03 | G58: 0.03 | H58: 0.03 | I58: 0.03 | J58: 0.03 | K58: 0.03 | L58: 0.03 | M58: 0.03 | N58: 0.03 | O58: 0.03
A59: TI/LC growth | E59: 0.03 | F59: 0.03 | G59: 0.03 | H59: 0.03 | I59: 0.03 | J59: 0.03 | K59: 0.03 | L59: 0.03 | M59: 0.03 | N59: 0.03 | O59: 0.03
A60: Other income growth | E60: 0.03 | F60: 0.03 | G60: 0.03 | H60: 0.03 | I60: 0.03 | J60: 0.03 | K60: 0.03 | L60: 0.03 | M60: 0.03 | N60: 0.03 | O60: 0.03
A62: Cumulative growth factors (year 0=1.0; applied at anniversary)
A63: Factor \ Year | D63: Y0 | E63: Y1 | F63: Y2 | G63: Y3 | H63: Y4 | I63: Y5 | J63: Y6 | K63: Y7 | L63: Y8 | M63: Y9 | N63: Y10 | O63: Y11
A64: MF rent cum factor | D64: 1 | E64: =D64*(1+E$56) | F64: =E64*(1+F$56) | G64: =F64*(1+G$56) | H64: =G64*(1+H$56) | I64: =H64*(1+I$56) | J64: =I64*(1+J$56) | K64: =J64*(1+K$56) | L64: =K64*(1+L$56) | ... O64: =N64*(1+O$56)
A65: Retail rent cum factor | D65: 1 | E65: =D65*(1+E$57) | F65: =E65*(1+F$57) | G65: =F65*(1+G$57) | H65: =G65*(1+H$57) | I65: =H65*(1+I$57) | J65: =I65*(1+J$57) | K65: =J65*(1+K$57) | L65: =K65*(1+L$57) | ... O65: =N65*(1+O$57)
A66: OpEx cum factor | D66: 1 | E66: =D66*(1+E$58) | F66: =E66*(1+F$58) | G66: =F66*(1+G$58) | H66: =G66*(1+H$58) | I66: =H66*(1+I$58) | J66: =I66*(1+J$58) | K66: =J66*(1+K$58) | L66: =K66*(1+L$58) | ... O66: =N66*(1+O$58)
A67: TI/LC cum factor | D67: 1 | E67: =D67*(1+E$59) | F67: =E67*(1+F$59) | G67: =F67*(1+G$59) | H67: =G67*(1+H$59) | I67: =H67*(1+I$59) | J67: =I67*(1+J$59) | K67: =J67*(1+K$59) | L67: =K67*(1+L$59) | ... O67: =N67*(1+O$59)
A68: Other income cum factor | D68: 1 | E68: =D68*(1+E$60) | F68: =E68*(1+F$60) | G68: =F68*(1+G$60) | H68: =G68*(1+H$60) | I68: =H68*(1+I$60) | J68: =I68*(1+J$60) | K68: =J68*(1+K$60) | L68: =K68*(1+L$60) | ... O68: =N68*(1+O$60)
A71: MONTHLY PERIOD HEADER (dynamic; every schedule references these rows)
A72: Month index (0 = acquisition) | E72: 0 | F72: 1 | G72: 2 | H72: 3 | I72: 4 | J72: 5 | K72: 6 | L72: 7 | M72: 8 | N72: 9 | O72: 10 | P72: 11 | Q72: 12 | R72: 13 | S72: 14 | T72: 15 | U72: 16 | V72: 17 | W72: 18 | X72: 19 | Y72: 20 | Z72: 21 | AA72: 22 | AB72: 23 | AC72: 24 | AD72: 25 | AE72: 26 | AF72: 27 | AG72: 28 | AH72: 29 | AI72: 30 | AJ72: 31 | AK72: 32 | AL72: 33 | AM72: 34 | AN72: 35 | AO72: 36 | AP72: 37 | AQ72: 38 | AR72: 39 | AS72: 40 | AT72: 41 | AU72: 42 | AV72: 43 | AW72: 44 | AX72: 45 | AY72: 46 | AZ72: 47 | BA72: 48 | BB72: 49 | BC72: 50 | BD72: 51 | BE72: 52 | BF72: 53 | BG72: 54 | BH72: 55 | BI72: 56 | BJ72: 57 | BK72: 58 | BL72: 59 | BM72: 60 | BN72: 61 | BO72: 62 | BP72: 63 | BQ72: 64 | BR72: 65 | BS72: 66 | BT72: 67 | BU72: 68 | BV72: 69 | BW72: 70 | BX72: 71 | BY72: 72 | BZ72: 73 | CA72: 74 | CB72: 75 | CC72: 76 | CD72: 77 | CE72: 78 | CF72: 79 | CG72: 80 | CH72: 81 | CI72: 82 | CJ72: 83 | CK72: 84 | CL72: 85 | CM72: 86 | CN72: 87 | CO72: 88 | CP72: 89 | CQ72: 90 | CR72: 91 | CS72: 92 | CT72: 93 | CU72: 94 | CV72: 95 | CW72: 96 | CX72: 97 | CY72: 98 | CZ72: 99 | DA72: 100 | DB72: 101 | DC72: 102 | DD72: 103 | DE72: 104 | DF72: 105 | DG72: 106 | DH72: 107 | DI72: 108 | DJ72: 109 | DK72: 110 | DL72: 111 | DM72: 112 | DN72: 113 | DO72: 114 | DP72: 115 | DQ72: 116 | DR72: 117 | DS72: 118 | DT72: 119
A73: Period date | E73: =AcquisitionDate | F73: =EDATE(AcquisitionDate,1) | G73: =EDATE(AcquisitionDate,2) | H73: =EDATE(AcquisitionDate,3) | I73: =EDATE(AcquisitionDate,4) | J73: =EDATE(AcquisitionDate,5) | K73: =EDATE(AcquisitionDate,6) | L73: =EDATE(AcquisitionDate,7) | M73: =EDATE(AcquisitionDate,8) | N73: =EDATE(AcquisitionDate,9) | O73: =EDATE(AcquisitionDate,10) | P73: =EDATE(AcquisitionDate,11) | Q73: =EDATE(AcquisitionDate,12) | R73: =EDATE(AcquisitionDate,13) | S73: =EDATE(AcquisitionDate,14) | T73: =EDATE(AcquisitionDate,15) | U73: =EDATE(AcquisitionDate,16) | V73: =EDATE(AcquisitionDate,17) | W73: =EDATE(AcquisitionDate,18) | X73: =EDATE(AcquisitionDate,19) | Y73: =EDATE(AcquisitionDate,20) | Z73: =EDATE(AcquisitionDate,21) | AA73: =EDATE(AcquisitionDate,22) | AB73: =EDATE(AcquisitionDate,23) | AC73: =EDATE(AcquisitionDate,24) | AD73: =EDATE(AcquisitionDate,25) | AE73: =EDATE(AcquisitionDate,26) | AF73: =EDATE(AcquisitionDate,27) | AG73: =EDATE(AcquisitionDate,28) | AH73: =EDATE(AcquisitionDate,29) | AI73: =EDATE(AcquisitionDate,30) | AJ73: =EDATE(AcquisitionDate,31) | AK73: =EDATE(AcquisitionDate,32) | AL73: =EDATE(AcquisitionDate,33) | AM73: =EDATE(AcquisitionDate,34) | AN73: =EDATE(AcquisitionDate,35) | AO73: =EDATE(AcquisitionDate,36) | AP73: =EDATE(AcquisitionDate,37) | AQ73: =EDATE(AcquisitionDate,38) | AR73: =EDATE(AcquisitionDate,39) | AS73: =EDATE(AcquisitionDate,40) | AT73: =EDATE(AcquisitionDate,41) | AU73: =EDATE(AcquisitionDate,42) | AV73: =EDATE(AcquisitionDate,43) | AW73: =EDATE(AcquisitionDate,44) | AX73: =EDATE(AcquisitionDate,45) | AY73: =EDATE(AcquisitionDate,46) | AZ73: =EDATE(AcquisitionDate,47) | BA73: =EDATE(AcquisitionDate,48) | BB73: =EDATE(AcquisitionDate,49) | BC73: =EDATE(AcquisitionDate,50) | BD73: =EDATE(AcquisitionDate,51) | BE73: =EDATE(AcquisitionDate,52) | BF73: =EDATE(AcquisitionDate,53) | BG73: =EDATE(AcquisitionDate,54) | BH73: =EDATE(AcquisitionDate,55) | BI73: =EDATE(AcquisitionDate,56) | BJ73: =EDATE(AcquisitionDate,57) | BK73: =EDATE(AcquisitionDate,58) | BL73: =EDATE(AcquisitionDate,59) | BM73: =EDATE(AcquisitionDate,60) | BN73: =EDATE(AcquisitionDate,61) | BO73: =EDATE(AcquisitionDate,62) | BP73: =EDATE(AcquisitionDate,63) | BQ73: =EDATE(AcquisitionDate,64) | BR73: =EDATE(AcquisitionDate,65) | BS73: =EDATE(AcquisitionDate,66) | BT73: =EDATE(AcquisitionDate,67) | BU73: =EDATE(AcquisitionDate,68) | BV73: =EDATE(AcquisitionDate,69) | BW73: =EDATE(AcquisitionDate,70) | BX73: =EDATE(AcquisitionDate,71) | BY73: =EDATE(AcquisitionDate,72) | BZ73: =EDATE(AcquisitionDate,73) | CA73: =EDATE(AcquisitionDate,74) | CB73: =EDATE(AcquisitionDate,75) | CC73: =EDATE(AcquisitionDate,76) | CD73: =EDATE(AcquisitionDate,77) | CE73: =EDATE(AcquisitionDate,78) | CF73: =EDATE(AcquisitionDate,79) | CG73: =EDATE(AcquisitionDate,80) | CH73: =EDATE(AcquisitionDate,81) | CI73: =EDATE(AcquisitionDate,82) | CJ73: =EDATE(AcquisitionDate,83) | CK73: =EDATE(AcquisitionDate,84) | CL73: =EDATE(AcquisitionDate,85) | CM73: =EDATE(AcquisitionDate,86) | CN73: =EDATE(AcquisitionDate,87) | CO73: =EDATE(AcquisitionDate,88) | CP73: =EDATE(AcquisitionDate,89) | CQ73: =EDATE(AcquisitionDate,90) | CR73: =EDATE(AcquisitionDate,91) | CS73: =EDATE(AcquisitionDate,92) | CT73: =EDATE(AcquisitionDate,93) | CU73: =EDATE(AcquisitionDate,94) | CV73: =EDATE(AcquisitionDate,95) | CW73: =EDATE(AcquisitionDate,96) | CX73: =EDATE(AcquisitionDate,97) | CY73: =EDATE(AcquisitionDate,98) | CZ73: =EDATE(AcquisitionDate,99) | DA73: =EDATE(AcquisitionDate,100) | DB73: =EDATE(AcquisitionDate,101) | DC73: =EDATE(AcquisitionDate,102) | DD73: =EDATE(AcquisitionDate,103) | DE73: =EDATE(AcquisitionDate,104) | DF73: =EDATE(AcquisitionDate,105) | DG73: =EDATE(AcquisitionDate,106) | DH73: =EDATE(AcquisitionDate,107) | DI73: =EDATE(AcquisitionDate,108) | DJ73: =EDATE(AcquisitionDate,109) | DK73: =EDATE(AcquisitionDate,110) | DL73: =EDATE(AcquisitionDate,111) | DM73: =EDATE(AcquisitionDate,112) | DN73: =EDATE(AcquisitionDate,113) | DO73: =EDATE(AcquisitionDate,114) | DP73: =EDATE(AcquisitionDate,115) | DQ73: =EDATE(AcquisitionDate,116) | DR73: =EDATE(AcquisitionDate,117) | DS73: =EDATE(AcquisitionDate,118) | DT73: =EDATE(AcquisitionDate,119)
A74: Operating-month flag (1 if active) | E74: 0 | F74: =IF(F$73<=DispositionDate,1,0) | G74: =IF(G$73<=DispositionDate,1,0) | H74: =IF(H$73<=DispositionDate,1,0) | I74: =IF(I$73<=DispositionDate,1,0) | J74: =IF(J$73<=DispositionDate,1,0) | K74: =IF(K$73<=DispositionDate,1,0) | L74: =IF(L$73<=DispositionDate,1,0) | M74: =IF(M$73<=DispositionDate,1,0) | ... DT74: =IF(DT$73<=DispositionDate,1,0)
A75: Hold-year number (1-based) | E75: =IF(E$74=1,INT((E$72-1)/12)+1,0) | F75: =IF(F$74=1,INT((F$72-1)/12)+1,0) | G75: =IF(G$74=1,INT((G$72-1)/12)+1,0) | H75: =IF(H$74=1,INT((H$72-1)/12)+1,0) | I75: =IF(I$74=1,INT((I$72-1)/12)+1,0) | J75: =IF(J$74=1,INT((J$72-1)/12)+1,0) | K75: =IF(K$74=1,INT((K$72-1)/12)+1,0) | L75: =IF(L$74=1,INT((L$72-1)/12)+1,0) | ... DT75: =IF(DT$74=1,INT((DT$72-1)/12)+1,0)
A76: Exit-month flag (1 at disposition) | E76: =IF(AND(E$74=1,F$74=0),1,0) | F76: =IF(AND(F$74=1,G$74=0),1,0) | G76: =IF(AND(G$74=1,H$74=0),1,0) | H76: =IF(AND(H$74=1,I$74=0),1,0) | I76: =IF(AND(I$74=1,J$74=0),1,0) | J76: =IF(AND(J$74=1,K$74=0),1,0) | K76: =IF(AND(K$74=1,L$74=0),1,0) | L76: =IF(AND(L$74=1,M$74=0),1,0) | ... DS76: =IF(AND(DS$74=1,DT$74=0),1,0) | DT76: =IF(DT$74=1,1,0)
A77: Year-fraction growth factor index (cum-factor col) | E77: =MIN(INT(MAX(E$75-1,0)),10)+1 | F77: =MIN(INT(MAX(F$75-1,0)),10)+1 | G77: =MIN(INT(MAX(G$75-1,0)),10)+1 | H77: =MIN(INT(MAX(H$75-1,0)),10)+1 | I77: =MIN(INT(MAX(I$75-1,0)),10)+1 | J77: =MIN(INT(MAX(J$75-1,0)),10)+1 | K77: =MIN(INT(MAX(K$75-1,0)),10)+1 | L77: =MIN(INT(MAX(L$75-1,0)),10)+1 | ... DT77: =MIN(INT(MAX(DT$75-1,0)),10)+1
A79: Derived exit & cost metrics
A80: Trailing 12-mo exit NOI ($) | B80: =SUMIFS('Monthly CF'!E$12:DT$12,Assumptions!E$72:DT$72,">"&(HoldMonths-12),Assumptions!E$72:DT$72,"<="&HoldMonths)
A81: Forward 12-mo exit NOI ($) | B81: =ExitNOI_Trailing*(1+INDEX(Vec_MFRent,1,1))
A82: Exit NOI (basis-selected) ($) | B82: =IF(ExitNOIBasis="Trailing 12-mo",ExitNOI_Trailing,ExitNOI_Forward)
A83: MF NOI share (exit, by EGI) | B83: =SUMIFS('Monthly CF'!E$7:DT$7,Assumptions!E$72:DT$72,">"&(HoldMonths-12),Assumptions!E$72:DT$72,"<="&HoldMonths)/MAX(1,SUMIFS('Monthly CF'!E$7:DT$7,Assumptions!E$72:DT$72,">"&(HoldMonths-12),Assumptions!E$72:DT$72,"<="&HoldMonths)+SUMIFS('Monthly CF'!E$8:DT$8,Assumptions!E$72:DT$72,">"&(HoldMonths-12),Assumptions!E$72:DT$72,"<="&HoldMonths))
A84: Exit gross value ($) | B84: =IF(ExitValMethod="Component Caps (MF + Retail summed)",ExitNOI*MF_NOI_Share/ExitCapMF+ExitNOI*(1-MF_NOI_Share)/ExitCapRetail,ExitNOI/ExitCapBlended)
A85: Total cost ($) | B85: =PurchasePrice+PurchasePrice*ClosingCostPct+TotalCapBudget+FinancingCosts
A86: Yield-on-cost (stabilized) (%) | B86: =StabNOI/TotalCost
A87: Development spread (YoC - exit cap) (bps) | B87: =(YieldOnCost-ExitCapBlended)*10000
A88: Going-in cap (%) | B88: =GoingInNOI/PurchasePrice
A89: Stabilized cap (%) | B89: =StabNOI/PurchasePrice
A90: Initial equity ($) [= total cost - loan] | B90: =TotalCost-LoanAmount

Sheet MF Revenue
A1: MF REVENUE — Unit-by-Unit Rent Roll
A2: Asset: | B2: =AssetName | D2: Run date: | E2: =RunDate | G2: Business plan: | H2: =BusinessPlanMode | J2: Hold (mo): | K2: =HoldMonths
A3: Model status: | B3: =ModelStatus
A5: Unit ID | B5: Type | C5: SF | D5: In-place rent ($/mo) | E5: Market rent ($/mo) | F5: Lease expiry (mo idx) | G5: Status
A6: U001 | B6: Studio | C6: 520 | D6: 1452 | E6: 1650 | F6: 1 | G6: Occupied
A7: U002 | B7: 1BR | C7: 720 | D7: 1905 | E7: 2165 | F7: 2 | G7: Occupied
A8: U003 | B8: 1BR | C8: 760 | D8: 2006 | E8: 2280 | F8: 3 | G8: Occupied
A9: U004 | B9: 2BR | C9: 1050 | D9: 2504 | E9: 2845 | F9: 4 | G9: Occupied
A10: U005 | B10: 2BR | C10: 1080 | D10: 2561 | E10: 2910 | F10: 5 | G10: Occupied
A11: U006 | B11: 3BR | C11: 1320 | D11: 3080 | E11: 3500 | F11: 6 | G11: Occupied
A12: U007 | B12: Studio | C12: 520 | D12: 1465 | E12: 1665 | F12: 7 | G12: Occupied
A13: U008 | B13: 1BR | C13: 720 | D13: 1918 | E13: 2180 | F13: 8 | G13: Occupied
A14: U009 | B14: 1BR | C14: 760 | D14: 2020 | E14: 2295 | F14: 9 | G14: Occupied
A15: U010 | B15: 2BR | C15: 1050 | D15: 2517 | E15: 2860 | F15: 10 | G15: Occupied
A16: U011 | B16: 2BR | C16: 1080 | D16: 2508 | E16: 2850 | F16: 11 | G16: Occupied
A17: U012 | B17: 3BR | C17: 1320 | D17: 3093 | E17: 3515 | F17: 12 | G17: Occupied
... A93: U088 | B93: 2BR | C93: 1050 | D93: 2490 | E93: 2830 | F93: 16 | G93: Occupied
A94: TOTALS | C94: =SUM(C6:C93) | D94: =SUM(D6:D93) | E94: =SUM(E6:E93) | H94: =COUNTA(A6:A93) | I94: <- unit count
A95: Loss-to-lease = Market - In-place, burning off over LTL_Months to market.
A97: MONTHLY MF BUILD (-> MF EGI). Cols E.. align to Assumptions period header.
A98: Month index | E98: =Assumptions!E$72 | F98: =Assumptions!F$72 | G98: =Assumptions!G$72 | H98: =Assumptions!H$72 | I98: =Assumptions!I$72 | J98: =Assumptions!J$72 | K98: =Assumptions!K$72 | L98: =Assumptions!L$72 | ... DT98: =Assumptions!DT$72
A99: Occupied units (count) | E99: =IF(Assumptions!E$74=0,0,IF(BusinessPlanMode="Core-Plus Lease-Up",MIN(MF_UnitCount*StabilizedOcc, MF_UnitCount*LeaseUpStartOcc + LeaseUpAbsorption*Assumptions!E$72),MF_UnitCount*StabilizedOcc)) | F99: =IF(Assumptions!F$74=0,0,IF(BusinessPlanMode="Core-Plus Lease-Up",MIN(MF_UnitCount*StabilizedOcc, MF_UnitCount*LeaseUpStartOcc + LeaseUpAbsorption*Assumptions!F$72),MF_UnitCount*StabilizedOcc)) | G99: =IF(Assumptions!G$74=0,0,IF(BusinessPlanMode="Core-Plus Lease-Up",MIN(MF_UnitCount*StabilizedOcc, MF_UnitCount*LeaseUpStartOcc + LeaseUpAbsorption*Assumptions!G$72),MF_UnitCount*StabilizedOcc)) | H99: =IF(Assumptions!H$74=0,0,IF(BusinessPlanMode="Core-Plus Lease-Up",MIN(MF_UnitCount*StabilizedOcc, MF_UnitCount*LeaseUpStartOcc + LeaseUpAbsorption*Assumptions!H$72),MF_UnitCount*StabilizedOcc)) | I99: =IF(Assumptions!I$74=0,0,IF(BusinessPlanMode="Core-Plus Lease-Up",MIN(MF_UnitCount*StabilizedOcc, MF_UnitCount*LeaseUpStartOcc + LeaseUpAbsorption*Assumptions!I$72),MF_UnitCount*StabilizedOcc)) | J99: =IF(Assumptions!J$74=0,0,IF(BusinessPlanMode="Core-Plus Lease-Up",MIN(MF_UnitCount*StabilizedOcc, MF_UnitCount*LeaseUpStartOcc + LeaseUpAbsorption*Assumptions!J$72),MF_UnitCount*StabilizedOcc)) | K99: =IF(Assumptions!K$74=0,0,IF(BusinessPlanMode="Core-Plus Lease-Up",MIN(MF_UnitCount*StabilizedOcc, MF_UnitCount*LeaseUpStartOcc + LeaseUpAbsorption*Assumptions!K$72),MF_UnitCount*StabilizedOcc)) | L99: =IF(Assumptions!L$74=0,0,IF(BusinessPlanMode="Core-Plus Lease-Up",MIN(MF_UnitCount*StabilizedOcc, MF_UnitCount*LeaseUpStartOcc + LeaseUpAbsorption*Assumptions!L$72),MF_UnitCount*StabilizedOcc)) | ... DT99: =IF(Assumptions!DT$74=0,0,IF(BusinessPlanMode="Core-Plus Lease-Up",MIN(MF_UnitCount*StabilizedOcc, MF_UnitCount*LeaseUpStartOcc + LeaseUpAbsorption*Assumptions!DT$72),MF_UnitCount*StabilizedOcc))
A100: Renovated units (cumulative) | E100: =IF(BusinessPlanMode="Value-Add",MIN(MF_UnitCount,MAX(0,RenoPace*(Assumptions!E$72-RenoDowntime)))*Assumptions!E$74,0) | F100: =IF(BusinessPlanMode="Value-Add",MIN(MF_UnitCount,MAX(0,RenoPace*(Assumptions!F$72-RenoDowntime)))*Assumptions!F$74,0) | G100: =IF(BusinessPlanMode="Value-Add",MIN(MF_UnitCount,MAX(0,RenoPace*(Assumptions!G$72-RenoDowntime)))*Assumptions!G$74,0) | H100: =IF(BusinessPlanMode="Value-Add",MIN(MF_UnitCount,MAX(0,RenoPace*(Assumptions!H$72-RenoDowntime)))*Assumptions!H$74,0) | I100: =IF(BusinessPlanMode="Value-Add",MIN(MF_UnitCount,MAX(0,RenoPace*(Assumptions!I$72-RenoDowntime)))*Assumptions!I$74,0) | J100: =IF(BusinessPlanMode="Value-Add",MIN(MF_UnitCount,MAX(0,RenoPace*(Assumptions!J$72-RenoDowntime)))*Assumptions!J$74,0) | K100: =IF(BusinessPlanMode="Value-Add",MIN(MF_UnitCount,MAX(0,RenoPace*(Assumptions!K$72-RenoDowntime)))*Assumptions!K$74,0) | L100: =IF(BusinessPlanMode="Value-Add",MIN(MF_UnitCount,MAX(0,RenoPace*(Assumptions!L$72-RenoDowntime)))*Assumptions!L$74,0) | ... DT100: =IF(BusinessPlanMode="Value-Add",MIN(MF_UnitCount,MAX(0,RenoPace*(Assumptions!DT$72-RenoDowntime)))*Assumptions!DT$74,0)
A101: Total in-place rent ($/mo, roll) | E101: =$D$94 | F101: =$D$94 | G101: =$D$94 | H101: =$D$94 | I101: =$D$94 | J101: =$D$94 | K101: =$D$94 | L101: =$D$94 | ... DT101: =$D$94
A102: Total market rent ($/mo, roll) | E102: =$E$94 | F102: =$E$94 | G102: =$E$94 | H102: =$E$94 | I102: =$E$94 | J102: =$E$94 | K102: =$E$94 | L102: =$E$94 | ... DT102: =$E$94
A103: Gross Potential Rent ($/mo) | E103: =(E$102*INDEX(Cum_MFRent,1,Assumptions!E$77)+E$100*RenoPremium)*Assumptions!E$74 | F103: =(F$102*INDEX(Cum_MFRent,1,Assumptions!F$77)+F$100*RenoPremium)*Assumptions!F$74 | G103: =(G$102*INDEX(Cum_MFRent,1,Assumptions!G$77)+G$100*RenoPremium)*Assumptions!G$74 | H103: =(H$102*INDEX(Cum_MFRent,1,Assumptions!H$77)+H$100*RenoPremium)*Assumptions!H$74 | I103: =(I$102*INDEX(Cum_MFRent,1,Assumptions!I$77)+I$100*RenoPremium)*Assumptions!I$74 | J103: =(J$102*INDEX(Cum_MFRent,1,Assumptions!J$77)+J$100*RenoPremium)*Assumptions!J$74 | K103: =(K$102*INDEX(Cum_MFRent,1,Assumptions!K$77)+K$100*RenoPremium)*Assumptions!K$74 | L103: =(L$102*INDEX(Cum_MFRent,1,Assumptions!L$77)+L$100*RenoPremium)*Assumptions!L$74 | ... DT103: =(DT$102*INDEX(Cum_MFRent,1,Assumptions!DT$77)+DT$100*RenoPremium)*Assumptions!DT$74
A104: Loss-to-lease ($/mo, negative) | E104: =-(E$102-E$101)*MAX(0,1-Assumptions!E$72/LTL_Months)*Assumptions!E$74 | F104: =-(F$102-F$101)*MAX(0,1-Assumptions!F$72/LTL_Months)*Assumptions!F$74 | G104: =-(G$102-G$101)*MAX(0,1-Assumptions!G$72/LTL_Months)*Assumptions!G$74 | H104: =-(H$102-H$101)*MAX(0,1-Assumptions!H$72/LTL_Months)*Assumptions!H$74 | I104: =-(I$102-I$101)*MAX(0,1-Assumptions!I$72/LTL_Months)*Assumptions!I$74 | J104: =-(J$102-J$101)*MAX(0,1-Assumptions!J$72/LTL_Months)*Assumptions!J$74 | K104: =-(K$102-K$101)*MAX(0,1-Assumptions!K$72/LTL_Months)*Assumptions!K$74 | L104: =-(L$102-L$101)*MAX(0,1-Assumptions!L$72/LTL_Months)*Assumptions!L$74 | ... DT104: =-(DT$102-DT$101)*MAX(0,1-Assumptions!DT$72/LTL_Months)*Assumptions!DT$74
A105: Vacancy / concessions / bad debt ($/mo, neg) | E105: =-(E$103*(MF_Vacancy+MF_Concessions+MF_BadDebt)+E$103*(1-(E$99/MF_UnitCount))) | F105: =-(F$103*(MF_Vacancy+MF_Concessions+MF_BadDebt)+F$103*(1-(F$99/MF_UnitCount))) | G105: =-(G$103*(MF_Vacancy+MF_Concessions+MF_BadDebt)+G$103*(1-(G$99/MF_UnitCount))) | H105: =-(H$103*(MF_Vacancy+MF_Concessions+MF_BadDebt)+H$103*(1-(H$99/MF_UnitCount))) | I105: =-(I$103*(MF_Vacancy+MF_Concessions+MF_BadDebt)+I$103*(1-(I$99/MF_UnitCount))) | J105: =-(J$103*(MF_Vacancy+MF_Concessions+MF_BadDebt)+J$103*(1-(J$99/MF_UnitCount))) | K105: =-(K$103*(MF_Vacancy+MF_Concessions+MF_BadDebt)+K$103*(1-(K$99/MF_UnitCount))) | L105: =-(L$103*(MF_Vacancy+MF_Concessions+MF_BadDebt)+L$103*(1-(L$99/MF_UnitCount))) | ... DT105: =-(DT$103*(MF_Vacancy+MF_Concessions+MF_BadDebt)+DT$103*(1-(DT$99/MF_UnitCount)))
A106: Other income — itemized ($/unit/mo)
A107: RUBS / utility reimbursement | B107: 45 | E107: =$B$107*E$99*INDEX(Cum_OtherInc,1,Assumptions!E$77)*Assumptions!E$74 | F107: =$B$107*F$99*INDEX(Cum_OtherInc,1,Assumptions!F$77)*Assumptions!F$74 | G107: =$B$107*G$99*INDEX(Cum_OtherInc,1,Assumptions!G$77)*Assumptions!G$74 | H107: =$B$107*H$99*INDEX(Cum_OtherInc,1,Assumptions!H$77)*Assumptions!H$74 | I107: =$B$107*I$99*INDEX(Cum_OtherInc,1,Assumptions!I$77)*Assumptions!I$74 | J107: =$B$107*J$99*INDEX(Cum_OtherInc,1,Assumptions!J$77)*Assumptions!J$74 | K107: =$B$107*K$99*INDEX(Cum_OtherInc,1,Assumptions!K$77)*Assumptions!K$74 | L107: =$B$107*L$99*INDEX(Cum_OtherInc,1,Assumptions!L$77)*Assumptions!L$74 | ... DT107: =$B$107*DT$99*INDEX(Cum_OtherInc,1,Assumptions!DT$77)*Assumptions!DT$74
A108: Parking | B108: 30 | E108: =$B$108*E$99*INDEX(Cum_OtherInc,1,Assumptions!E$77)*Assumptions!E$74 | F108: =$B$108*F$99*INDEX(Cum_OtherInc,1,Assumptions!F$77)*Assumptions!F$74 | G108: =$B$108*G$99*INDEX(Cum_OtherInc,1,Assumptions!G$77)*Assumptions!G$74 | H108: =$B$108*H$99*INDEX(Cum_OtherInc,1,Assumptions!H$77)*Assumptions!H$74 | I108: =$B$108*I$99*INDEX(Cum_OtherInc,1,Assumptions!I$77)*Assumptions!I$74 | J108: =$B$108*J$99*INDEX(Cum_OtherInc,1,Assumptions!J$77)*Assumptions!J$74 | K108: =$B$108*K$99*INDEX(Cum_OtherInc,1,Assumptions!K$77)*Assumptions!K$74 | L108: =$B$108*L$99*INDEX(Cum_OtherInc,1,Assumptions!L$77)*Assumptions!L$74 | ... DT108: =$B$108*DT$99*INDEX(Cum_OtherInc,1,Assumptions!DT$77)*Assumptions!DT$74
A109: Storage | B109: 12 | E109: =$B$109*E$99*INDEX(Cum_OtherInc,1,Assumptions!E$77)*Assumptions!E$74 | F109: =$B$109*F$99*INDEX(Cum_OtherInc,1,Assumptions!F$77)*Assumptions!F$74 | G109: =$B$109*G$99*INDEX(Cum_OtherInc,1,Assumptions!G$77)*Assumptions!G$74 | H109: =$B$109*H$99*INDEX(Cum_OtherInc,1,Assumptions!H$77)*Assumptions!H$74 | I109: =$B$109*I$99*INDEX(Cum_OtherInc,1,Assumptions!I$77)*Assumptions!I$74 | J109: =$B$109*J$99*INDEX(Cum_OtherInc,1,Assumptions!J$77)*Assumptions!J$74 | K109: =$B$109*K$99*INDEX(Cum_OtherInc,1,Assumptions!K$77)*Assumptions!K$74 | L109: =$B$109*L$99*INDEX(Cum_OtherInc,1,Assumptions!L$77)*Assumptions!L$74 | ... DT109: =$B$109*DT$99*INDEX(Cum_OtherInc,1,Assumptions!DT$77)*Assumptions!DT$74
A110: Pet | B110: 8 | E110: =$B$110*E$99*INDEX(Cum_OtherInc,1,Assumptions!E$77)*Assumptions!E$74 | F110: =$B$110*F$99*INDEX(Cum_OtherInc,1,Assumptions!F$77)*Assumptions!F$74 | G110: =$B$110*G$99*INDEX(Cum_OtherInc,1,Assumptions!G$77)*Assumptions!G$74 | H110: =$B$110*H$99*INDEX(Cum_OtherInc,1,Assumptions!H$77)*Assumptions!H$74 | I110: =$B$110*I$99*INDEX(Cum_OtherInc,1,Assumptions!I$77)*Assumptions!I$74 | J110: =$B$110*J$99*INDEX(Cum_OtherInc,1,Assumptions!J$77)*Assumptions!J$74 | K110: =$B$110*K$99*INDEX(Cum_OtherInc,1,Assumptions!K$77)*Assumptions!K$74 | L110: =$B$110*L$99*INDEX(Cum_OtherInc,1,Assumptions!L$77)*Assumptions!L$74 | ... DT110: =$B$110*DT$99*INDEX(Cum_OtherInc,1,Assumptions!DT$77)*Assumptions!DT$74
A111: Application / admin fees | B111: 5 | E111: =$B$111*E$99*INDEX(Cum_OtherInc,1,Assumptions!E$77)*Assumptions!E$74 | F111: =$B$111*F$99*INDEX(Cum_OtherInc,1,Assumptions!F$77)*Assumptions!F$74 | G111: =$B$111*G$99*INDEX(Cum_OtherInc,1,Assumptions!G$77)*Assumptions!G$74 | H111: =$B$111*H$99*INDEX(Cum_OtherInc,1,Assumptions!H$77)*Assumptions!H$74 | I111: =$B$111*I$99*INDEX(Cum_OtherInc,1,Assumptions!I$77)*Assumptions!I$74 | J111: =$B$111*J$99*INDEX(Cum_OtherInc,1,Assumptions!J$77)*Assumptions!J$74 | K111: =$B$111*K$99*INDEX(Cum_OtherInc,1,Assumptions!K$77)*Assumptions!K$74 | L111: =$B$111*L$99*INDEX(Cum_OtherInc,1,Assumptions!L$77)*Assumptions!L$74 | ... DT111: =$B$111*DT$99*INDEX(Cum_OtherInc,1,Assumptions!DT$77)*Assumptions!DT$74
A112: Other | B112: 6 | E112: =$B$112*E$99*INDEX(Cum_OtherInc,1,Assumptions!E$77)*Assumptions!E$74 | F112: =$B$112*F$99*INDEX(Cum_OtherInc,1,Assumptions!F$77)*Assumptions!F$74 | G112: =$B$112*G$99*INDEX(Cum_OtherInc,1,Assumptions!G$77)*Assumptions!G$74 | H112: =$B$112*H$99*INDEX(Cum_OtherInc,1,Assumptions!H$77)*Assumptions!H$74 | I112: =$B$112*I$99*INDEX(Cum_OtherInc,1,Assumptions!I$77)*Assumptions!I$74 | J112: =$B$112*J$99*INDEX(Cum_OtherInc,1,Assumptions!J$77)*Assumptions!J$74 | K112: =$B$112*K$99*INDEX(Cum_OtherInc,1,Assumptions!K$77)*Assumptions!K$74 | L112: =$B$112*L$99*INDEX(Cum_OtherInc,1,Assumptions!L$77)*Assumptions!L$74 | ... DT112: =$B$112*DT$99*INDEX(Cum_OtherInc,1,Assumptions!DT$77)*Assumptions!DT$74
A113: Total other income ($/mo) | E113: =SUM(E107:E112) | F113: =SUM(F107:F112) | G113: =SUM(G107:G112) | H113: =SUM(H107:H112) | I113: =SUM(I107:I112) | J113: =SUM(J107:J112) | K113: =SUM(K107:K112) | L113: =SUM(L107:L112) | ... DT113: =SUM(DT107:DT112)
A114: MF EGI ($/mo) | E114: =E$103+E$104+E$105+E$113 | F114: =F$103+F$104+F$105+F$113 | G114: =G$103+G$104+G$105+G$113 | H114: =H$103+H$104+H$105+H$113 | I114: =I$103+I$104+I$105+I$113 | J114: =J$103+J$104+J$105+J$113 | K114: =K$103+K$104+K$105+K$113 | L114: =L$103+L$104+L$105+L$113 | ... DT114: =DT$103+DT$104+DT$105+DT$113

Sheet Retail Revenue
A1: RETAIL REVENUE — Tenant-by-Tenant
A2: Asset: | B2: =AssetName | D2: Run date: | E2: =RunDate | G2: Business plan: | H2: =BusinessPlanMode | J2: Hold (mo): | K2: =HoldMonths
A3: Model status: | B3: =ModelStatus
A5: Recovery matrix (editable: 1=tenant reimburses, 0=landlord absorbs)
A6: Structure | B6: CAM | C6: Tax | D6: Insurance | E6: Base-year stop?
A7: NNN | B7: 1 | C7: 1 | D7: 1 | E7: 0
A8: Gross | B8: 0 | C8: 0 | D8: 0 | E8: 0
A9: Modified Gross | B9: 1 | C9: 1 | D9: 1 | E9: 1
A11: Recoverable CAM ($/SF/yr) | B11: 6.5
A12: Recoverable Tax ($/SF/yr) | B12: 4
A13: Recoverable Insurance ($/SF/yr) | B13: 1.25
A16: Tenant | B16: Suite SF | C16: Lease start (mo) | D16: Lease expiry (mo) | E16: Base rent ($/SF/yr) | F16: Annual step (%) | G16: Structure (override) | H16: %rent: sales ($/SF/yr) | I16: %rent: overage %
A17: Grocer Anchor | B17: 16000 | C17: 0 | D17: 60 | E17: 30 | F17: 0.02 | G17: NNN | H17: 0 | I17: 0.06
A18: Pharmacy | B18: 9000 | C18: 0 | D18: 84 | E18: 33 | F18: 0.015 | G18: NNN | H18: 0 | I18: 0.05
A19: Cafe | B19: 2400 | C19: 0 | D19: 36 | E19: 46 | F19: 0.03 | G19: NNN | H19: 0 | I19: 0.07
A20: Fitness | B20: 6000 | C20: 0 | D20: 48 | E20: 31 | F20: 0.025 | G20: Modified Gross | H20: 0 | I20: 0.06
A21: Bank | B21: 3200 | C21: 0 | D21: 72 | E21: 40 | F21: 0.02 | G21: NNN | H21: 0 | I21: 0.05
A22: Restaurant | B22: 3600 | C22: 0 | D22: 54 | E22: 42 | F22: 0.025 | G22: NNN | H22: 0 | I22: 0.07
A23: TOTAL GLA | B23: =SUM(B17:B22) | C23: =COUNTA(A17:A22) | I23: Set GLA rows to 0 for pure-MF.
A26: MONTHLY RETAIL BUILD (-> Retail EGI). Per-tenant base rent + steps, then pool lines.
A27: Month index | E27: =Assumptions!E$72 | F27: =Assumptions!F$72 | G27: =Assumptions!G$72 | H27: =Assumptions!H$72 | I27: =Assumptions!I$72 | J27: =Assumptions!J$72 | K27: =Assumptions!K$72 | L27: =Assumptions!L$72 | ... DT27: =Assumptions!DT$72
A28: Per-tenant in-place + rollover base rent ($/mo)
A29: Grocer Anchor | E29: =IF(Assumptions!E$74=0,0,IF(Assumptions!E$72<$C$17,0,IF(Assumptions!E$72<=$D$17,$E$17*$B$17/12*(1+$F$17)^INT((Assumptions!E$72-$C$17)/12),IF(Assumptions!E$72<=$D$17+RetailDowntime,0,1)*$E$17*$B$17/12*INDEX(Cum_RetailRent,1,Assumptions!E$77)*RenewalRentFactor))) | F29: =IF(Assumptions!F$74=0,0,IF(Assumptions!F$72<$C$17,0,IF(Assumptions!F$72<=$D$17,$E$17*$B$17/12*(1+$F$17)^INT((Assumptions!F$72-$C$17)/12),IF(Assumptions!F$72<=$D$17+RetailDowntime,0,1)*$E$17*$B$17/12*INDEX(Cum_RetailRent,1,Assumptions!F$77)*RenewalRentFactor))) | G29: =IF(Assumptions!G$74=0,0,IF(Assumptions!G$72<$C$17,0,IF(Assumptions!G$72<=$D$17,$E$17*$B$17/12*(1+$F$17)^INT((Assumptions!G$72-$C$17)/12),IF(Assumptions!G$72<=$D$17+RetailDowntime,0,1)*$E$17*$B$17/12*INDEX(Cum_RetailRent,1,Assumptions!G$77)*RenewalRentFactor))) | H29: =IF(Assumptions!H$74=0,0,IF(Assumptions!H$72<$C$17,0,IF(Assumptions!H$72<=$D$17,$E$17*$B$17/12*(1+$F$17)^INT((Assumptions!H$72-$C$17)/12),IF(Assumptions!H$72<=$D$17+RetailDowntime,0,1)*$E$17*$B$17/12*INDEX(Cum_RetailRent,1,Assumptions!H$77)*RenewalRentFactor))) | I29: =IF(Assumptions!I$74=0,0,IF(Assumptions!I$72<$C$17,0,IF(Assumptions!I$72<=$D$17,$E$17*$B$17/12*(1+$F$17)^INT((Assumptions!I$72-$C$17)/12),IF(Assumptions!I$72<=$D$17+RetailDowntime,0,1)*$E$17*$B$17/12*INDEX(Cum_RetailRent,1,Assumptions!I$77)*RenewalRentFactor))) | J29: =IF(Assumptions!J$74=0,0,IF(Assumptions!J$72<$C$17,0,IF(Assumptions!J$72<=$D$17,$E$17*$B$17/12*(1+$F$17)^INT((Assumptions!J$72-$C$17)/12),IF(Assumptions!J$72<=$D$17+RetailDowntime,0,1)*$E$17*$B$17/12*INDEX(Cum_RetailRent,1,Assumptions!J$77)*RenewalRentFactor))) | K29: =IF(Assumptions!K$74=0,0,IF(Assumptions!K$72<$C$17,0,IF(Assumptions!K$72<=$D$17,$E$17*$B$17/12*(1+$F$17)^INT((Assumptions!K$72-$C$17)/12),IF(Assumptions!K$72<=$D$17+RetailDowntime,0,1)*$E$17*$B$17/12*INDEX(Cum_RetailRent,1,Assumptions!K$77)*RenewalRentFactor))) | L29: =IF(Assumptions!L$74=0,0,IF(Assumptions!L$72<$C$17,0,IF(Assumptions!L$72<=$D$17,$E$17*$B$17/12*(1+$F$17)^INT((Assumptions!L$72-$C$17)/12),IF(Assumptions!L$72<=$D$17+RetailDowntime,0,1)*$E$17*$B$17/12*INDEX(Cum_RetailRent,1,Assumptions!L$77)*RenewalRentFactor))) | ... DT29: =IF(Assumptions!DT$74=0,0,IF(Assumptions!DT$72<$C$17,0,IF(Assumptions!DT$72<=$D$17,$E$17*$B$17/12*(1+$F$17)^INT((Assumptions!DT$72-$C$17)/12),IF(Assumptions!DT$72<=$D$17+RetailDowntime,0,1)*$E$17*$B$17/12*INDEX(Cum_RetailRent,1,Assumptions!DT$77)*RenewalRentFactor)))
A30: Pharmacy | E30: =IF(Assumptions!E$74=0,0,IF(Assumptions!E$72<$C$18,0,IF(Assumptions!E$72<=$D$18,$E$18*$B$18/12*(1+$F$18)^INT((Assumptions!E$72-$C$18)/12),IF(Assumptions!E$72<=$D$18+RetailDowntime,0,1)*$E$18*$B$18/12*INDEX(Cum_RetailRent,1,Assumptions!E$77)*RenewalRentFactor))) | F30: =IF(Assumptions!F$74=0,0,IF(Assumptions!F$72<$C$18,0,IF(Assumptions!F$72<=$D$18,$E$18*$B$18/12*(1+$F$18)^INT((Assumptions!F$72-$C$18)/12),IF(Assumptions!F$72<=$D$18+RetailDowntime,0,1)*$E$18*$B$18/12*INDEX(Cum_RetailRent,1,Assumptions!F$77)*RenewalRentFactor))) | G30: =IF(Assumptions!G$74=0,0,IF(Assumptions!G$72<$C$18,0,IF(Assumptions!G$72<=$D$18,$E$18*$B$18/12*(1+$F$18)^INT((Assumptions!G$72-$C$18)/12),IF(Assumptions!G$72<=$D$18+RetailDowntime,0,1)*$E$18*$B$18/12*INDEX(Cum_RetailRent,1,Assumptions!G$77)*RenewalRentFactor))) | H30: =IF(Assumptions!H$74=0,0,IF(Assumptions!H$72<$C$18,0,IF(Assumptions!H$72<=$D$18,$E$18*$B$18/12*(1+$F$18)^INT((Assumptions!H$72-$C$18)/12),IF(Assumptions!H$72<=$D$18+RetailDowntime,0,1)*$E$18*$B$18/12*INDEX(Cum_RetailRent,1,Assumptions!H$77)*RenewalRentFactor))) | I30: =IF(Assumptions!I$74=0,0,IF(Assumptions!I$72<$C$18,0,IF(Assumptions!I$72<=$D$18,$E$18*$B$18/12*(1+$F$18)^INT((Assumptions!I$72-$C$18)/12),IF(Assumptions!I$72<=$D$18+RetailDowntime,0,1)*$E$18*$B$18/12*INDEX(Cum_RetailRent,1,Assumptions!I$77)*RenewalRentFactor))) | J30: =IF(Assumptions!J$74=0,0,IF(Assumptions!J$72<$C$18,0,IF(Assumptions!J$72<=$D$18,$E$18*$B$18/12*(1+$F$18)^INT((Assumptions!J$72-$C$18)/12),IF(Assumptions!J$72<=$D$18+RetailDowntime,0,1)*$E$18*$B$18/12*INDEX(Cum_RetailRent,1,Assumptions!J$77)*RenewalRentFactor))) | K30: =IF(Assumptions!K$74=0,0,IF(Assumptions!K$72<$C$18,0,IF(Assumptions!K$72<=$D$18,$E$18*$B$18/12*(1+$F$18)^INT((Assumptions!K$72-$C$18)/12),IF(Assumptions!K$72<=$D$18+RetailDowntime,0,1)*$E$18*$B$18/12*INDEX(Cum_RetailRent,1,Assumptions!K$77)*RenewalRentFactor))) | L30: =IF(Assumptions!L$74=0,0,IF(Assumptions!L$72<$C$18,0,IF(Assumptions!L$72<=$D$18,$E$18*$B$18/12*(1+$F$18)^INT((Assumptions!L$72-$C$18)/12),IF(Assumptions!L$72<=$D$18+RetailDowntime,0,1)*$E$18*$B$18/12*INDEX(Cum_RetailRent,1,Assumptions!L$77)*RenewalRentFactor))) | ... DT30: =IF(Assumptions!DT$74=0,0,IF(Assumptions!DT$72<$C$18,0,IF(Assumptions!DT$72<=$D$18,$E$18*$B$18/12*(1+$F$18)^INT((Assumptions!DT$72-$C$18)/12),IF(Assumptions!DT$72<=$D$18+RetailDowntime,0,1)*$E$18*$B$18/12*INDEX(Cum_RetailRent,1,Assumptions!DT$77)*RenewalRentFactor)))
A31: Cafe | E31: =IF(Assumptions!E$74=0,0,IF(Assumptions!E$72<$C$19,0,IF(Assumptions!E$72<=$D$19,$E$19*$B$19/12*(1+$F$19)^INT((Assumptions!E$72-$C$19)/12),IF(Assumptions!E$72<=$D$19+RetailDowntime,0,1)*$E$19*$B$19/12*INDEX(Cum_RetailRent,1,Assumptions!E$77)*RenewalRentFactor))) | F31: =IF(Assumptions!F$74=0,0,IF(Assumptions!F$72<$C$19,0,IF(Assumptions!F$72<=$D$19,$E$19*$B$19/12*(1+$F$19)^INT((Assumptions!F$72-$C$19)/12),IF(Assumptions!F$72<=$D$19+RetailDowntime,0,1)*$E$19*$B$19/12*INDEX(Cum_RetailRent,1,Assumptions!F$77)*RenewalRentFactor))) | G31: =IF(Assumptions!G$74=0,0,IF(Assumptions!G$72<$C$19,0,IF(Assumptions!G$72<=$D$19,$E$19*$B$19/12*(1+$F$19)^INT((Assumptions!G$72-$C$19)/12),IF(Assumptions!G$72<=$D$19+RetailDowntime,0,1)*$E$19*$B$19/12*INDEX(Cum_RetailRent,1,Assumptions!G$77)*RenewalRentFactor))) | H31: =IF(Assumptions!H$74=0,0,IF(Assumptions!H$72<$C$19,0,IF(Assumptions!H$72<=$D$19,$E$19*$B$19/12*(1+$F$19)^INT((Assumptions!H$72-$C$19)/12),IF(Assumptions!H$72<=$D$19+RetailDowntime,0,1)*$E$19*$B$19/12*INDEX(Cum_RetailRent,1,Assumptions!H$77)*RenewalRentFactor))) | I31: =IF(Assumptions!I$74=0,0,IF(Assumptions!I$72<$C$19,0,IF(Assumptions!I$72<=$D$19,$E$19*$B$19/12*(1+$F$19)^INT((Assumptions!I$72-$C$19)/12),IF(Assumptions!I$72<=$D$19+RetailDowntime,0,1)*$E$19*$B$19/12*INDEX(Cum_RetailRent,1,Assumptions!I$77)*RenewalRentFactor))) | J31: =IF(Assumptions!J$74=0,0,IF(Assumptions!J$72<$C$19,0,IF(Assumptions!J$72<=$D$19,$E$19*$B$19/12*(1+$F$19)^INT((Assumptions!J$72-$C$19)/12),IF(Assumptions!J$72<=$D$19+RetailDowntime,0,1)*$E$19*$B$19/12*INDEX(Cum_RetailRent,1,Assumptions!J$77)*RenewalRentFactor))) | K31: =IF(Assumptions!K$74=0,0,IF(Assumptions!K$72<$C$19,0,IF(Assumptions!K$72<=$D$19,$E$19*$B$19/12*(1+$F$19)^INT((Assumptions!K$72-$C$19)/12),IF(Assumptions!K$72<=$D$19+RetailDowntime,0,1)*$E$19*$B$19/12*INDEX(Cum_RetailRent,1,Assumptions!K$77)*RenewalRentFactor))) | L31: =IF(Assumptions!L$74=0,0,IF(Assumptions!L$72<$C$19,0,IF(Assumptions!L$72<=$D$19,$E$19*$B$19/12*(1+$F$19)^INT((Assumptions!L$72-$C$19)/12),IF(Assumptions!L$72<=$D$19+RetailDowntime,0,1)*$E$19*$B$19/12*INDEX(Cum_RetailRent,1,Assumptions!L$77)*RenewalRentFactor))) | ... DT31: =IF(Assumptions!DT$74=0,0,IF(Assumptions!DT$72<$C$19,0,IF(Assumptions!DT$72<=$D$19,$E$19*$B$19/12*(1+$F$19)^INT((Assumptions!DT$72-$C$19)/12),IF(Assumptions!DT$72<=$D$19+RetailDowntime,0,1)*$E$19*$B$19/12*INDEX(Cum_RetailRent,1,Assumptions!DT$77)*RenewalRentFactor)))
A32: Fitness | E32: =IF(Assumptions!E$74=0,0,IF(Assumptions!E$72<$C$20,0,IF(Assumptions!E$72<=$D$20,$E$20*$B$20/12*(1+$F$20)^INT((Assumptions!E$72-$C$20)/12),IF(Assumptions!E$72<=$D$20+RetailDowntime,0,1)*$E$20*$B$20/12*INDEX(Cum_RetailRent,1,Assumptions!E$77)*RenewalRentFactor))) | F32: =IF(Assumptions!F$74=0,0,IF(Assumptions!F$72<$C$20,0,IF(Assumptions!F$72<=$D$20,$E$20*$B$20/12*(1+$F$20)^INT((Assumptions!F$72-$C$20)/12),IF(Assumptions!F$72<=$D$20+RetailDowntime,0,1)*$E$20*$B$20/12*INDEX(Cum_RetailRent,1,Assumptions!F$77)*RenewalRentFactor))) | G32: =IF(Assumptions!G$74=0,0,IF(Assumptions!G$72<$C$20,0,IF(Assumptions!G$72<=$D$20,$E$20*$B$20/12*(1+$F$20)^INT((Assumptions!G$72-$C$20)/12),IF(Assumptions!G$72<=$D$20+RetailDowntime,0,1)*$E$20*$B$20/12*INDEX(Cum_RetailRent,1,Assumptions!G$77)*RenewalRentFactor))) | H32: =IF(Assumptions!H$74=0,0,IF(Assumptions!H$72<$C$20,0,IF(Assumptions!H$72<=$D$20,$E$20*$B$20/12*(1+$F$20)^INT((Assumptions!H$72-$C$20)/12),IF(Assumptions!H$72<=$D$20+RetailDowntime,0,1)*$E$20*$B$20/12*INDEX(Cum_RetailRent,1,Assumptions!H$77)*RenewalRentFactor))) | I32: =IF(Assumptions!I$74=0,0,IF(Assumptions!I$72<$C$20,0,IF(Assumptions!I$72<=$D$20,$E$20*$B$20/12*(1+$F$20)^INT((Assumptions!I$72-$C$20)/12),IF(Assumptions!I$72<=$D$20+RetailDowntime,0,1)*$E$20*$B$20/12*INDEX(Cum_RetailRent,1,Assumptions!I$77)*RenewalRentFactor))) | J32: =IF(Assumptions!J$74=0,0,IF(Assumptions!J$72<$C$20,0,IF(Assumptions!J$72<=$D$20,$E$20*$B$20/12*(1+$F$20)^INT((Assumptions!J$72-$C$20)/12),IF(Assumptions!J$72<=$D$20+RetailDowntime,0,1)*$E$20*$B$20/12*INDEX(Cum_RetailRent,1,Assumptions!J$77)*RenewalRentFactor))) | K32: =IF(Assumptions!K$74=0,0,IF(Assumptions!K$72<$C$20,0,IF(Assumptions!K$72<=$D$20,$E$20*$B$20/12*(1+$F$20)^INT((Assumptions!K$72-$C$20)/12),IF(Assumptions!K$72<=$D$20+RetailDowntime,0,1)*$E$20*$B$20/12*INDEX(Cum_RetailRent,1,Assumptions!K$77)*RenewalRentFactor))) | L32: =IF(Assumptions!L$74=0,0,IF(Assumptions!L$72<$C$20,0,IF(Assumptions!L$72<=$D$20,$E$20*$B$20/12*(1+$F$20)^INT((Assumptions!L$72-$C$20)/12),IF(Assumptions!L$72<=$D$20+RetailDowntime,0,1)*$E$20*$B$20/12*INDEX(Cum_RetailRent,1,Assumptions!L$77)*RenewalRentFactor))) | ... DT32: =IF(Assumptions!DT$74=0,0,IF(Assumptions!DT$72<$C$20,0,IF(Assumptions!DT$72<=$D$20,$E$20*$B$20/12*(1+$F$20)^INT((Assumptions!DT$72-$C$20)/12),IF(Assumptions!DT$72<=$D$20+RetailDowntime,0,1)*$E$20*$B$20/12*INDEX(Cum_RetailRent,1,Assumptions!DT$77)*RenewalRentFactor)))
A33: Bank | E33: =IF(Assumptions!E$74=0,0,IF(Assumptions!E$72<$C$21,0,IF(Assumptions!E$72<=$D$21,$E$21*$B$21/12*(1+$F$21)^INT((Assumptions!E$72-$C$21)/12),IF(Assumptions!E$72<=$D$21+RetailDowntime,0,1)*$E$21*$B$21/12*INDEX(Cum_RetailRent,1,Assumptions!E$77)*RenewalRentFactor))) | F33: =IF(Assumptions!F$74=0,0,IF(Assumptions!F$72<$C$21,0,IF(Assumptions!F$72<=$D$21,$E$21*$B$21/12*(1+$F$21)^INT((Assumptions!F$72-$C$21)/12),IF(Assumptions!F$72<=$D$21+RetailDowntime,0,1)*$E$21*$B$21/12*INDEX(Cum_RetailRent,1,Assumptions!F$77)*RenewalRentFactor))) | G33: =IF(Assumptions!G$74=0,0,IF(Assumptions!G$72<$C$21,0,IF(Assumptions!G$72<=$D$21,$E$21*$B$21/12*(1+$F$21)^INT((Assumptions!G$72-$C$21)/12),IF(Assumptions!G$72<=$D$21+RetailDowntime,0,1)*$E$21*$B$21/12*INDEX(Cum_RetailRent,1,Assumptions!G$77)*RenewalRentFactor))) | H33: =IF(Assumptions!H$74=0,0,IF(Assumptions!H$72<$C$21,0,IF(Assumptions!H$72<=$D$21,$E$21*$B$21/12*(1+$F$21)^INT((Assumptions!H$72-$C$21)/12),IF(Assumptions!H$72<=$D$21+RetailDowntime,0,1)*$E$21*$B$21/12*INDEX(Cum_RetailRent,1,Assumptions!H$77)*RenewalRentFactor))) | I33: =IF(Assumptions!I$74=0,0,IF(Assumptions!I$72<$C$21,0,IF(Assumptions!I$72<=$D$21,$E$21*$B$21/12*(1+$F$21)^INT((Assumptions!I$72-$C$21)/12),IF(Assumptions!I$72<=$D$21+RetailDowntime,0,1)*$E$21*$B$21/12*INDEX(Cum_RetailRent,1,Assumptions!I$77)*RenewalRentFactor))) | J33: =IF(Assumptions!J$74=0,0,IF(Assumptions!J$72<$C$21,0,IF(Assumptions!J$72<=$D$21,$E$21*$B$21/12*(1+$F$21)^INT((Assumptions!J$72-$C$21)/12),IF(Assumptions!J$72<=$D$21+RetailDowntime,0,1)*$E$21*$B$21/12*INDEX(Cum_RetailRent,1,Assumptions!J$77)*RenewalRentFactor))) | K33: =IF(Assumptions!K$74=0,0,IF(Assumptions!K$72<$C$21,0,IF(Assumptions!K$72<=$D$21,$E$21*$B$21/12*(1+$F$21)^INT((Assumptions!K$72-$C$21)/12),IF(Assumptions!K$72<=$D$21+RetailDowntime,0,1)*$E$21*$B$21/12*INDEX(Cum_RetailRent,1,Assumptions!K$77)*RenewalRentFactor))) | L33: =IF(Assumptions!L$74=0,0,IF(Assumptions!L$72<$C$21,0,IF(Assumptions!L$72<=$D$21,$E$21*$B$21/12*(1+$F$21)^INT((Assumptions!L$72-$C$21)/12),IF(Assumptions!L$72<=$D$21+RetailDowntime,0,1)*$E$21*$B$21/12*INDEX(Cum_RetailRent,1,Assumptions!L$77)*RenewalRentFactor))) | ... DT33: =IF(Assumptions!DT$74=0,0,IF(Assumptions!DT$72<$C$21,0,IF(Assumptions!DT$72<=$D$21,$E$21*$B$21/12*(1+$F$21)^INT((Assumptions!DT$72-$C$21)/12),IF(Assumptions!DT$72<=$D$21+RetailDowntime,0,1)*$E$21*$B$21/12*INDEX(Cum_RetailRent,1,Assumptions!DT$77)*RenewalRentFactor)))
A34: Restaurant | E34: =IF(Assumptions!E$74=0,0,IF(Assumptions!E$72<$C$22,0,IF(Assumptions!E$72<=$D$22,$E$22*$B$22/12*(1+$F$22)^INT((Assumptions!E$72-$C$22)/12),IF(Assumptions!E$72<=$D$22+RetailDowntime,0,1)*$E$22*$B$22/12*INDEX(Cum_RetailRent,1,Assumptions!E$77)*RenewalRentFactor))) | F34: =IF(Assumptions!F$74=0,0,IF(Assumptions!F$72<$C$22,0,IF(Assumptions!F$72<=$D$22,$E$22*$B$22/12*(1+$F$22)^INT((Assumptions!F$72-$C$22)/12),IF(Assumptions!F$72<=$D$22+RetailDowntime,0,1)*$E$22*$B$22/12*INDEX(Cum_RetailRent,1,Assumptions!F$77)*RenewalRentFactor))) | G34: =IF(Assumptions!G$74=0,0,IF(Assumptions!G$72<$C$22,0,IF(Assumptions!G$72<=$D$22,$E$22*$B$22/12*(1+$F$22)^INT((Assumptions!G$72-$C$22)/12),IF(Assumptions!G$72<=$D$22+RetailDowntime,0,1)*$E$22*$B$22/12*INDEX(Cum_RetailRent,1,Assumptions!G$77)*RenewalRentFactor))) | H34: =IF(Assumptions!H$74=0,0,IF(Assumptions!H$72<$C$22,0,IF(Assumptions!H$72<=$D$22,$E$22*$B$22/12*(1+$F$22)^INT((Assumptions!H$72-$C$22)/12),IF(Assumptions!H$72<=$D$22+RetailDowntime,0,1)*$E$22*$B$22/12*INDEX(Cum_RetailRent,1,Assumptions!H$77)*RenewalRentFactor))) | I34: =IF(Assumptions!I$74=0,0,IF(Assumptions!I$72<$C$22,0,IF(Assumptions!I$72<=$D$22,$E$22*$B$22/12*(1+$F$22)^INT((Assumptions!I$72-$C$22)/12),IF(Assumptions!I$72<=$D$22+RetailDowntime,0,1)*$E$22*$B$22/12*INDEX(Cum_RetailRent,1,Assumptions!I$77)*RenewalRentFactor))) | J34: =IF(Assumptions!J$74=0,0,IF(Assumptions!J$72<$C$22,0,IF(Assumptions!J$72<=$D$22,$E$22*$B$22/12*(1+$F$22)^INT((Assumptions!J$72-$C$22)/12),IF(Assumptions!J$72<=$D$22+RetailDowntime,0,1)*$E$22*$B$22/12*INDEX(Cum_RetailRent,1,Assumptions!J$77)*RenewalRentFactor))) | K34: =IF(Assumptions!K$74=0,0,IF(Assumptions!K$72<$C$22,0,IF(Assumptions!K$72<=$D$22,$E$22*$B$22/12*(1+$F$22)^INT((Assumptions!K$72-$C$22)/12),IF(Assumptions!K$72<=$D$22+RetailDowntime,0,1)*$E$22*$B$22/12*INDEX(Cum_RetailRent,1,Assumptions!K$77)*RenewalRentFactor))) | L34: =IF(Assumptions!L$74=0,0,IF(Assumptions!L$72<$C$22,0,IF(Assumptions!L$72<=$D$22,$E$22*$B$22/12*(1+$F$22)^INT((Assumptions!L$72-$C$22)/12),IF(Assumptions!L$72<=$D$22+RetailDowntime,0,1)*$E$22*$B$22/12*INDEX(Cum_RetailRent,1,Assumptions!L$77)*RenewalRentFactor))) | ... DT34: =IF(Assumptions!DT$74=0,0,IF(Assumptions!DT$72<$C$22,0,IF(Assumptions!DT$72<=$D$22,$E$22*$B$22/12*(1+$F$22)^INT((Assumptions!DT$72-$C$22)/12),IF(Assumptions!DT$72<=$D$22+RetailDowntime,0,1)*$E$22*$B$22/12*INDEX(Cum_RetailRent,1,Assumptions!DT$77)*RenewalRentFactor)))
A35: Total base + steps + rollover ($/mo) | E35: =SUM(E29:E34) | F35: =SUM(F29:F34) | G35: =SUM(G29:G34) | H35: =SUM(H29:H34) | I35: =SUM(I29:I34) | J35: =SUM(J29:J34) | K35: =SUM(K29:K34) | L35: =SUM(L29:L34) | ... DT35: =SUM(DT29:DT34)
A36: Percentage rent ($/mo) | E36: =(IF($I$17=0,0,MAX(0,$H$17*$B$17-($E$17*$B$17/$I$17))*$I$17/12)+IF($I$18=0,0,MAX(0,$H$18*$B$18-($E$18*$B$18/$I$18))*$I$18/12)+IF($I$19=0,0,MAX(0,$H$19*$B$19-($E$19*$B$19/$I$19))*$I$19/12)+IF($I$20=0,0,MAX(0,$H$20*$B$20-($E$20*$B$20/$I$20))*$I$20/12)+IF($I$21=0,0,MAX(0,$H$21*$B$21-($E$21*$B$21/$I$21))*$I$21/12)+IF($I$22=0,0,MAX(0,$H$22*$B$22-($E$22*$B$22/$I$22))*$I$22/12))*Assumptions!E$74 | F36: =(IF($I$17=0,0,MAX(0,$H$17*$B$17-($E$17*$B$17/$I$17))*$I$17/12)+IF($I$18=0,0,MAX(0,$H$18*$B$18-($E$18*$B$18/$I$18))*$I$18/12)+IF($I$19=0,0,MAX(0,$H$19*$B$19-($E$19*$B$19/$I$19))*$I$19/12)+IF($I$20=0,0,MAX(0,$H$20*$B$20-($E$20*$B$20/$I$20))*$I$20/12)+IF($I$21=0,0,MAX(0,$H$21*$B$21-($E$21*$B$21/$I$21))*$I$21/12)+IF($I$22=0,0,MAX(0,$H$22*$B$22-($E$22*$B$22/$I$22))*$I$22/12))*Assumptions!F$74 | G36: =(IF($I$17=0,0,MAX(0,$H$17*$B$17-($E$17*$B$17/$I$17))*$I$17/12)+IF($I$18=0,0,MAX(0,$H$18*$B$18-($E$18*$B$18/$I$18))*$I$18/12)+IF($I$19=0,0,MAX(0,$H$19*$B$19-($E$19*$B$19/$I$19))*$I$19/12)+IF($I$20=0,0,MAX(0,$H$20*$B$20-($E$20*$B$20/$I$20))*$I$20/12)+IF($I$21=0,0,MAX(0,$H$21*$B$21-($E$21*$B$21/$I$21))*$I$21/12)+IF($I$22=0,0,MAX(0,$H$22*$B$22-($E$22*$B$22/$I$22))*$I$22/12))*Assumptions!G$74 | H36: =(IF($I$17=0,0,MAX(0,$H$17*$B$17-($E$17*$B$17/$I$17))*$I$17/12)+IF($I$18=0,0,MAX(0,$H$18*$B$18-($E$18*$B$18/$I$18))*$I$18/12)+IF($I$19=0,0,MAX(0,$H$19*$B$19-($E$19*$B$19/$I$19))*$I$19/12)+IF($I$20=0,0,MAX(0,$H$20*$B$20-($E$20*$B$20/$I$20))*$I$20/12)+IF($I$21=0,0,MAX(0,$H$21*$B$21-($E$21*$B$21/$I$21))*$I$21/12)+IF($I$22=0,0,MAX(0,$H$22*$B$22-($E$22*$B$22/$I$22))*$I$22/12))*Assumptions!H$74 | I36: =(IF($I$17=0,0,MAX(0,$H$17*$B$17-($E$17*$B$17/$I$17))*$I$17/12)+IF($I$18=0,0,MAX(0,$H$18*$B$18-($E$18*$B$18/$I$18))*$I$18/12)+IF($I$19=0,0,MAX(0,$H$19*$B$19-($E$19*$B$19/$I$19))*$I$19/12)+IF($I$20=0,0,MAX(0,$H$20*$B$20-($E$20*$B$20/$I$20))*$I$20/12)+IF($I$21=0,0,MAX(0,$H$21*$B$21-($E$21*$B$21/$I$21))*$I$21/12)+IF($I$22=0,0,MAX(0,$H$22*$B$22-($E$22*$B$22/$I$22))*$I$22/12))*Assumptions!I$74 | J36: =(IF($I$17=0,0,MAX(0,$H$17*$B$17-($E$17*$B$17/$I$17))*$I$17/12)+IF($I$18=0,0,MAX(0,$H$18*$B$18-($E$18*$B$18/$I$18))*$I$18/12)+IF($I$19=0,0,MAX(0,$H$19*$B$19-($E$19*$B$19/$I$19))*$I$19/12)+IF($I$20=0,0,MAX(0,$H$20*$B$20-($E$20*$B$20/$I$20))*$I$20/12)+IF($I$21=0,0,MAX(0,$H$21*$B$21-($E$21*$B$21/$I$21))*$I$21/12)+IF($I$22=0,0,MAX(0,$H$22*$B$22-($E$22*$B$22/$I$22))*$I$22/12))*Assumptions!J$74 | K36: =(IF($I$17=0,0,MAX(0,$H$17*$B$17-($E$17*$B$17/$I$17))*$I$17/12)+IF($I$18=0,0,MAX(0,$H$18*$B$18-($E$18*$B$18/$I$18))*$I$18/12)+IF($I$19=0,0,MAX(0,$H$19*$B$19-($E$19*$B$19/$I$19))*$I$19/12)+IF($I$20=0,0,MAX(0,$H$20*$B$20-($E$20*$B$20/$I$20))*$I$20/12)+IF($I$21=0,0,MAX(0,$H$21*$B$21-($E$21*$B$21/$I$21))*$I$21/12)+IF($I$22=0,0,MAX(0,$H$22*$B$22-($E$22*$B$22/$I$22))*$I$22/12))*Assumptions!K$74 | L36: =(IF($I$17=0,0,MAX(0,$H$17*$B$17-($E$17*$B$17/$I$17))*$I$17/12)+IF($I$18=0,0,MAX(0,$H$18*$B$18-($E$18*$B$18/$I$18))*$I$18/12)+IF($I$19=0,0,MAX(0,$H$19*$B$19-($E$19*$B$19/$I$19))*$I$19/12)+IF($I$20=0,0,MAX(0,$H$20*$B$20-($E$20*$B$20/$I$20))*$I$20/12)+IF($I$21=0,0,MAX(0,$H$21*$B$21-($E$21*$B$21/$I$21))*$I$21/12)+IF($I$22=0,0,MAX(0,$H$22*$B$22-($E$22*$B$22/$I$22))*$I$22/12))*Assumptions!L$74 | ... DT36: =(IF($I$17=0,0,MAX(0,$H$17*$B$17-($E$17*$B$17/$I$17))*$I$17/12)+IF($I$18=0,0,MAX(0,$H$18*$B$18-($E$18*$B$18/$I$18))*$I$18/12)+IF($I$19=0,0,MAX(0,$H$19*$B$19-($E$19*$B$19/$I$19))*$I$19/12)+IF($I$20=0,0,MAX(0,$H$20*$B$20-($E$20*$B$20/$I$20))*$I$20/12)+IF($I$21=0,0,MAX(0,$H$21*$B$21-($E$21*$B$21/$I$21))*$I$21/12)+IF($I$22=0,0,MAX(0,$H$22*$B$22-($E$22*$B$22/$I$22))*$I$22/12))*Assumptions!DT$74
A37: Recoveries ($/mo) | E37: =((VLOOKUP($G$17,RecovMatrix,2,FALSE)*RecovCAM+VLOOKUP($G$17,RecovMatrix,3,FALSE)*RecovTax+VLOOKUP($G$17,RecovMatrix,4,FALSE)*RecovIns)*$B$17/12*IF(GrossUpOn="On",1/(1-RetailGenVacancy),1)*(1+IF(AdminFeeOn="On",AdminFeePct,0))*IF(VLOOKUP($G$17,RecovMatrix,5,FALSE)=1,MAX(0,INDEX(Cum_OpEx,1,Assumptions!E$77)-1),INDEX(Cum_OpEx,1,Assumptions!E$77))+(VLOOKUP($G$18,RecovMatrix,2,FALSE)*RecovCAM+VLOOKUP($G$18,RecovMatrix,3,FALSE)*RecovTax+VLOOKUP($G$18,RecovMatrix,4,FALSE)*RecovIns)*$B$18/12*IF(GrossUpOn="On",1/(1-RetailGenVacancy),1)*(1+IF(AdminFeeOn="On",AdminFeePct,0))*IF(VLOOKUP($G$18,RecovMatrix,5,FALSE)=1,MAX(0,INDEX(Cum_OpEx,1,Assumptions!E$77)-1),INDEX(Cum_OpEx,1,Assumptions!E$77))+(VLOOKUP($G$19,RecovMatrix,2,FALSE)*RecovCAM+VLOOKUP($G$19,RecovMatrix,3,FALSE)*RecovTax+VLOOKUP($G$19,RecovMatrix,4,FALSE)*RecovIns)*$B$19/12*IF(GrossUpOn="On",1/(1-RetailGenVacancy),1)*(1+IF(AdminFeeOn="On",AdminFeePct,0))*IF(VLOOKUP($G$19,RecovMatrix,5,FALSE)=1,MAX(0,INDEX(Cum_OpEx,1,Assumptions!E$77)-1),INDEX(Cum_OpEx,1,Assumptions!E$77))+(VLOOKUP($G$20,RecovMatrix,2,FALSE)*RecovCAM+VLOOKUP($G$20,RecovMatrix,3,FALSE)*RecovTax+VLOOKUP($G$20,RecovMatrix,4,FALSE)*RecovIns)*$B$20/12*IF(GrossUpOn="On",1/(1-RetailGenVacancy),1)*(1+IF(AdminFeeOn="On",AdminFeePct,0))*IF(VLOOKUP($G$20,RecovMatrix,5,FALSE)=1,MAX(0,INDEX(Cum_OpEx,1,Assumptions!E$77)-1),INDEX(Cum_OpEx,1,Assumptions!E$77))+(VLOOKUP($G$21,RecovMatrix,2,FALSE)*RecovCAM+VLOOKUP($G$21,RecovMatrix,3,FALSE)*RecovTax+VLOOKUP($G$21,RecovMatrix,4,FALSE)*RecovIns)*$B$21/12*IF(GrossUpOn="On",1/(1-RetailGenVacancy),1)*(1+IF(AdminFeeOn="On",AdminFeePct,0))*IF(VLOOKUP($G$21,RecovMatrix,5,FALSE)=1,MAX(0,INDEX(Cum_OpEx,1,Assumptions!E$77)-1),INDEX(Cum_OpEx,1,Assumptions!E$77))+(VLOOKUP($G$22,RecovMatrix,2,FALSE)*RecovCAM+VLOOKUP($G$22,RecovMatrix,3,FALSE)*RecovTax+VLOOKUP($G$22,RecovMatrix,4,FALSE)*RecovIns)*$B$22/12*IF(GrossUpOn="On",1/(1-RetailGenVacancy),1)*(1+IF(AdminFeeOn="On",AdminFeePct,0))*IF(VLOOKUP($G$22,RecovMatrix,5,FALSE)=1,MAX(0,INDEX(Cum_OpEx,1,Assumptions!E$77)-1),INDEX(Cum_OpEx,1,Assumptions!E$77)))*Assumptions!E$74 | F37: =((VLOOKUP($G$17,RecovMatrix,2,FALSE)*RecovCAM+VLOOKUP($G$17,RecovMatrix,3,FALSE)*RecovTax+VLOOKUP($G$17,RecovMatrix,4,FALSE)*RecovIns)*$B$17/12*IF(GrossUpOn="On",1/(1-RetailGenVacancy),1)*(1+IF(AdminFeeOn="On",AdminFeePct,0))*IF(VLOOKUP($G$17,RecovMatrix,5,FALSE)=1,MAX(0,INDEX(Cum_OpEx,1,Assumptions!F$77)-1),INDEX(Cum_OpEx,1,Assumptions!F$77))+(VLOOKUP($G$18,RecovMatrix,2,FALSE)*RecovCAM+VLOOKUP($G$18,RecovMatrix,3,FALSE)*RecovTax+VLOOKUP($G$18,RecovMatrix,4,FALSE)*RecovIns)*$B$18/12*IF(GrossUpOn="On",1/(1-RetailGenVacancy),1)*(1+IF(AdminFeeOn="On",AdminFeePct,0))*IF(VLOOKUP($G$18,RecovMatrix,5,FALSE)=1,MAX(0,INDEX(Cum_OpEx,1,Assumptions!F$77)-1),INDEX(Cum_OpEx,1,Assumptions!F$77))+(VLOOKUP($G$19,RecovMatrix,2,FALSE)*RecovCAM+VLOOKUP($G$19,RecovMatrix,3,FALSE)*RecovTax+VLOOKUP($G$19,RecovMatrix,4,FALSE)*RecovIns)*$B$19/12*IF(GrossUpOn="On",1/(1-RetailGenVacancy),1)*(1+IF(AdminFeeOn="On",AdminFeePct,0))*IF(VLOOKUP($G$19,RecovMatrix,5,FALSE)=1,MAX(0,INDEX(Cum_OpEx,1,Assumptions!F$77)-1),INDEX(Cum_OpEx,1,Assumptions!F$77))+(VLOOKUP($G$20,RecovMatrix,2,FALSE)*RecovCAM+VLOOKUP($G$20,RecovMatrix,3,FALSE)*RecovTax+VLOOKUP($G$20,RecovMatrix,4,FALSE)*RecovIns)*$B$20/12*IF(GrossUpOn="On",1/(1-RetailGenVacancy),1)*(1+IF(AdminFeeOn="On",AdminFeePct,0))*IF(VLOOKUP($G$20,RecovMatrix,5,FALSE)=1,MAX(0,INDEX(Cum_OpEx,1,Assumptions!F$77)-1),INDEX(Cum_OpEx,1,Assumptions!F$77))+(VLOOKUP($G$21,RecovMatrix,2,FALSE)*RecovCAM+VLOOKUP($G$21,RecovMatrix,3,FALSE)*RecovTax+VLOOKUP($G$21,RecovMatrix,4,FALSE)*RecovIns)*$B$21/12*IF(GrossUpOn="On",1/(1-RetailGenVacancy),1)*(1+IF(AdminFeeOn="On",AdminFeePct,0))*IF(VLOOKUP($G$21,RecovMatrix,5,FALSE)=1,MAX(0,INDEX(Cum_OpEx,1,Assumptions!F$77)-1),INDEX(Cum_OpEx,1,Assumptions!F$77))+(VLOOKUP($G$22,RecovMatrix,2,FALSE)*RecovCAM+VLOOKUP($G$22,RecovMatrix,3,FALSE)*RecovTax+VLOOKUP($G$22,RecovMatrix,4,FALSE)*RecovIns)*$B$22/12*IF(GrossUpOn="On",1/(1-RetailGenVacancy),1)*(1+IF(AdminFeeOn="On",AdminFeePct,0))*IF(VLOOKUP($G$22,RecovMatrix,5,FALSE)=1,MAX(0,INDEX(Cum_OpEx,1,Assumptions!F$77)-1),INDEX(Cum_OpEx,1,Assumptions!F$77)))*Assumptions!F$74 | G37: =((VLOOKUP($G$17,RecovMatrix,2,FALSE)*RecovCAM+VLOOKUP($G$17,RecovMatrix,3,FALSE)*RecovTax+VLOOKUP($G$17,RecovMatrix,4,FALSE)*RecovIns)*$B$17/12*IF(GrossUpOn="On",1/(1-RetailGenVacancy),1)*(1+IF(AdminFeeOn="On",AdminFeePct,0))*IF(VLOOKUP($G$17,RecovMatrix,5,FALSE)=1,MAX(0,INDEX(Cum_OpEx,1,Assumptions!G$77)-1),INDEX(Cum_OpEx,1,Assumptions!G$77))+(VLOOKUP($G$18,RecovMatrix,2,FALSE)*RecovCAM+VLOOKUP($G$18,RecovMatrix,3,FALSE)*RecovTax+VLOOKUP($G$18,RecovMatrix,4,FALSE)*RecovIns)*$B$18/12*IF(GrossUpOn="On",1/(1-RetailGenVacancy),1)*(1+IF(AdminFeeOn="On",AdminFeePct,0))*IF(VLOOKUP($G$18,RecovMatrix,5,FALSE)=1,MAX(0,INDEX(Cum_OpEx,1,Assumptions!G$77)-1),INDEX(Cum_OpEx,1,Assumptions!G$77))+(VLOOKUP($G$19,RecovMatrix,2,FALSE)*RecovCAM+VLOOKUP($G$19,RecovMatrix,3,FALSE)*RecovTax+VLOOKUP($G$19,RecovMatrix,4,FALSE)*RecovIns)*$B$19/12*IF(GrossUpOn="On",1/(1-RetailGenVacancy),1)*(1+IF(AdminFeeOn="On",AdminFeePct,0))*IF(VLOOKUP($G$19,RecovMatrix,5,FALSE)=1,MAX(0,INDEX(Cum_OpEx,1,Assumptions!G$77)-1),INDEX(Cum_OpEx,1,Assumptions!G$77))+(VLOOKUP($G$20,RecovMatrix,2,FALSE)*RecovCAM+VLOOKUP($G$20,RecovMatrix,3,FALSE)*RecovTax+VLOOKUP($G$20,RecovMatrix,4,FALSE)*RecovIns)*$B$20/12*IF(GrossUpOn="On",1/(1-RetailGenVacancy),1)*(1+IF(AdminFeeOn="On",AdminFeePct,0))*IF(VLOOKUP($G$20,RecovMatrix,5,FALSE)=1,MAX(0,INDEX(Cum_OpEx,1,Assumptions!G$77)-1),INDEX(Cum_OpEx,1,Assumptions!G$77))+(VLOOKUP($G$21,RecovMatrix,2,FALSE)*RecovCAM+VLOOKUP($G$21,RecovMatrix,3,FALSE)*RecovTax+VLOOKUP($G$21,RecovMatrix,4,FALSE)*RecovIns)*$B$21/12*IF(GrossUpOn="On",1/(1-RetailGenVacancy),1)*(1+IF(AdminFeeOn="On",AdminFeePct,0))*IF(VLOOKUP($G$21,RecovMatrix,5,FALSE)=1,MAX(0,INDEX(Cum_OpEx,1,Assumptions!G$77)-1),INDEX(Cum_OpEx,1,Assumptions!G$77))+(VLOOKUP($G$22,RecovMatrix,2,FALSE)*RecovCAM+VLOOKUP($G$22,RecovMatrix,3,FALSE)*RecovTax+VLOOKUP($G$22,RecovMatrix,4,FALSE)*RecovIns)*$B$22/12*IF(GrossUpOn="On",1/(1-RetailGenVacancy),1)*(1+IF(AdminFeeOn="On",AdminFeePct,0))*IF(VLOOKUP($G$22,RecovMatrix,5,FALSE)=1,MAX(0,INDEX(Cum_OpEx,1,Assumptions!G$77)-1),INDEX(Cum_OpEx,1,Assumptions!G$77)))*Assumptions!G$74 | H37: =((VLOOKUP($G$17,RecovMatrix,2,FALSE)*RecovCAM+VLOOKUP($G$17,RecovMatrix,3,FALSE)*RecovTax+VLOOKUP($G$17,RecovMatrix,4,FALSE)*RecovIns)*$B$17/12*IF(GrossUpOn="On",1/(1-RetailGenVacancy),1)*(1+IF(AdminFeeOn="On",AdminFeePct,0))*IF(VLOOKUP($G$17,RecovMatrix,5,FALSE)=1,MAX(0,INDEX(Cum_OpEx,1,Assumptions!H$77)-1),INDEX(Cum_OpEx,1,Assumptions!H$77))+(VLOOKUP($G$18,RecovMatrix,2,FALSE)*RecovCAM+VLOOKUP($G$18,RecovMatrix,3,FALSE)*RecovTax+VLOOKUP($G$18,RecovMatrix,4,FALSE)*RecovIns)*$B$18/12*IF(GrossUpOn="On",1/(1-RetailGenVacancy),1)*(1+IF(AdminFeeOn="On",AdminFeePct,0))*IF(VLOOKUP($G$18,RecovMatrix,5,FALSE)=1,MAX(0,INDEX(Cum_OpEx,1,Assumptions!H$77)-1),INDEX(Cum_OpEx,1,Assumptions!H$77))+(VLOOKUP($G$19,RecovMatrix,2,FALSE)*RecovCAM+VLOOKUP($G$19,RecovMatrix,3,FALSE)*RecovTax+VLOOKUP($G$19,RecovMatrix,4,FALSE)*RecovIns)*$B$19/12*IF(GrossUpOn="On",1/(1-RetailGenVacancy),1)*(1+IF(AdminFeeOn="On",AdminFeePct,0))*IF(VLOOKUP($G$19,RecovMatrix,5,FALSE)=1,MAX(0,INDEX(Cum_OpEx,1,Assumptions!H$77)-1),INDEX(Cum_OpEx,1,Assumptions!H$77))+(VLOOKUP($G$20,RecovMatrix,2,FALSE)*RecovCAM+VLOOKUP($G$20,RecovMatrix,3,FALSE)*RecovTax+VLOOKUP($G$20,RecovMatrix,4,FALSE)*RecovIns)*$B$20/12*IF(GrossUpOn="On",1/(1-RetailGenVacancy),1)*(1+IF(AdminFeeOn="On",AdminFeePct,0))*IF(VLOOKUP($G$20,RecovMatrix,5,FALSE)=1,MAX(0,INDEX(Cum_OpEx,1,Assumptions!H$77)-1),INDEX(Cum_OpEx,1,Assumptions!H$77))+(VLOOKUP($G$21,RecovMatrix,2,FALSE)*RecovCAM+VLOOKUP($G$21,RecovMatrix,3,FALSE)*RecovTax+VLOOKUP($G$21,RecovMatrix,4,FALSE)*RecovIns)*$B$21/12*IF(GrossUpOn="On",1/(1-RetailGenVacancy),1)*(1+IF(AdminFeeOn="On",AdminFeePct,0))*IF(VLOOKUP($G$21,RecovMatrix,5,FALSE)=1,MAX(0,INDEX(Cum_OpEx,1,Assumptions!H$77)-1),INDEX(Cum_OpEx,1,Assumptions!H$77))+(VLOOKUP($G$22,RecovMatrix,2,FALSE)*RecovCAM+VLOOKUP($G$22,RecovMatrix,3,FALSE)*RecovTax+VLOOKUP($G$22,RecovMatrix,4,FALSE)*RecovIns)*$B$22/12*IF(GrossUpOn="On",1/(1-RetailGenVacancy),1)*(1+IF(AdminFeeOn="On",AdminFeePct,0))*IF(VLOOKUP($G$22,RecovMatrix,5,FALSE)=1,MAX(0,INDEX(Cum_OpEx,1,Assumptions!H$77)-1),INDEX(Cum_OpEx,1,Assumptions!H$77)))*Assumptions!H$74 | I37: =((VLOOKUP($G$17,RecovMatrix,2,FALSE)*RecovCAM+VLOOKUP($G$17,RecovMatrix,3,FALSE)*RecovTax+VLOOKUP($G$17,RecovMatrix,4,FALSE)*RecovIns)*$B$17/12*IF(GrossUpOn="On",1/(1-RetailGenVacancy),1)*(1+IF(AdminFeeOn="On",AdminFeePct,0))*IF(VLOOKUP($G$17,RecovMatrix,5,FALSE)=1,MAX(0,INDEX(Cum_OpEx,1,Assumptions!I$77)-1),INDEX(Cum_OpEx,1,Assumptions!I$77))+(VLOOKUP($G$18,RecovMatrix,2,FALSE)*RecovCAM+VLOOKUP($G$18,RecovMatrix,3,FALSE)*RecovTax+VLOOKUP($G$18,RecovMatrix,4,FALSE)*RecovIns)*$B$18/12*IF(GrossUpOn="On",1/(1-RetailGenVacancy),1)*(1+IF(AdminFeeOn="On",AdminFeePct,0))*IF(VLOOKUP($G$18,RecovMatrix,5,FALSE)=1,MAX(0,INDEX(Cum_OpEx,1,Assumptions!I$77)-1),INDEX(Cum_OpEx,1,Assumptions!I$77))+(VLOOKUP($G$19,RecovMatrix,2,FALSE)*RecovCAM+VLOOKUP($G$19,RecovMatrix,3,FALSE)*RecovTax+VLOOKUP($G$19,RecovMatrix,4,FALSE)*RecovIns)*$B$19/12*IF(GrossUpOn="On",1/(1-RetailGenVacancy),1)*(1+IF(AdminFeeOn="On",AdminFeePct,0))*IF(VLOOKUP($G$19,RecovMatrix,5,FALSE)=1,MAX(0,INDEX(Cum_OpEx,1,Assumptions!I$77)-1),INDEX(Cum_OpEx,1,Assumptions!I$77))+(VLOOKUP($G$20,RecovMatrix,2,FALSE)*RecovCAM+VLOOKUP($G$20,RecovMatrix,3,FALSE)*RecovTax+VLOOKUP($G$20,RecovMatrix,4,FALSE)*RecovIns)*$B$20/12*IF(GrossUpOn="On",1/(1-RetailGenVacancy),1)*(1+IF(AdminFeeOn="On",AdminFeePct,0))*IF(VLOOKUP($G$20,RecovMatrix,5,FALSE)=1,MAX(0,INDEX(Cum_OpEx,1,Assumptions!I$77)-1),INDEX(Cum_OpEx,1,Assumptions!I$77))+(VLOOKUP($G$21,RecovMatrix,2,FALSE)*RecovCAM+VLOOKUP($G$21,RecovMatrix,3,FALSE)*RecovTax+VLOOKUP($G$21,RecovMatrix,4,FALSE)*RecovIns)*$B$21/12*IF(GrossUpOn="On",1/(1-RetailGenVacancy),1)*(1+IF(AdminFeeOn="On",AdminFeePct,0))*IF(VLOOKUP($G$21,RecovMatrix,5,FALSE)=1,MAX(0,INDEX(Cum_OpEx,1,Assumptions!I$77)-1),INDEX(Cum_OpEx,1,Assumptions!I$77))+(VLOOKUP($G$22,RecovMatrix,2,FALSE)*RecovCAM+VLOOKUP($G$22,RecovMatrix,3,FALSE)*RecovTax+VLOOKUP($G$22,RecovMatrix,4,FALSE)*RecovIns)*$B$22/12*IF(GrossUpOn="On",1/(1-RetailGenVacancy),1)*(1+IF(AdminFeeOn="On",AdminFeePct,0))*IF(VLOOKUP($G$22,RecovMatrix,5,FALSE)=1,MAX(0,INDEX(Cum_OpEx,1,Assumptions!I$77)-1),INDEX(Cum_OpEx,1,Assumptions!I$77)))*Assumptions!I$74 | J37: =((VLOOKUP($G$17,RecovMatrix,2,FALSE)*RecovCAM+VLOOKUP($G$17,RecovMatrix,3,FALSE)*RecovTax+VLOOKUP($G$17,RecovMatrix,4,FALSE)*RecovIns)*$B$17/12*IF(GrossUpOn="On",1/(1-RetailGenVacancy),1)*(1+IF(AdminFeeOn="On",AdminFeePct,0))*IF(VLOOKUP($G$17,RecovMatrix,5,FALSE)=1,MAX(0,INDEX(Cum_OpEx,1,Assumptions!J$77)-1),INDEX(Cum_OpEx,1,Assumptions!J$77))+(VLOOKUP($G$18,RecovMatrix,2,FALSE)*RecovCAM+VLOOKUP($G$18,RecovMatrix,3,FALSE)*RecovTax+VLOOKUP($G$18,RecovMatrix,4,FALSE)*RecovIns)*$B$18/12*IF(GrossUpOn="On",1/(1-RetailGenVacancy),1)*(1+IF(AdminFeeOn="On",AdminFeePct,0))*IF(VLOOKUP($G$18,RecovMatrix,5,FALSE)=1,MAX(0,INDEX(Cum_OpEx,1,Assumptions!J$77)-1),INDEX(Cum_OpEx,1,Assumptions!J$77))+(VLOOKUP($G$19,RecovMatrix,2,FALSE)*RecovCAM+VLOOKUP($G$19,RecovMatrix,3,FALSE)*RecovTax+VLOOKUP($G$19,RecovMatrix,4,FALSE)*RecovIns)*$B$19/12*IF(GrossUpOn="On",1/(1-RetailGenVacancy),1)*(1+IF(AdminFeeOn="On",AdminFeePct,0))*IF(VLOOKUP($G$19,RecovMatrix,5,FALSE)=1,MAX(0,INDEX(Cum_OpEx,1,Assumptions!J$77)-1),INDEX(Cum_OpEx,1,Assumptions!J$77))+(VLOOKUP($G$20,RecovMatrix,2,FALSE)*RecovCAM+VLOOKUP($G$20,RecovMatrix,3,FALSE)*RecovTax+VLOOKUP($G$20,RecovMatrix,4,FALSE)*RecovIns)*$B$20/12*IF(GrossUpOn="On",1/(1-RetailGenVacancy),1)*(1+IF(AdminFeeOn="On",AdminFeePct,0))*IF(VLOOKUP($G$20,RecovMatrix,5,FALSE)=1,MAX(0,INDEX(Cum_OpEx,1,Assumptions!J$77)-1),INDEX(Cum_OpEx,1,Assumptions!J$77))+(VLOOKUP($G$21,RecovMatrix,2,FALSE)*RecovCAM+VLOOKUP($G$21,RecovMatrix,3,FALSE)*RecovTax+VLOOKUP($G$21,RecovMatrix,4,FALSE)*RecovIns)*$B$21/12*IF(GrossUpOn="On",1/(1-RetailGenVacancy),1)*(1+IF(AdminFeeOn="On",AdminFeePct,0))*IF(VLOOKUP($G$21,RecovMatrix,5,FALSE)=1,MAX(0,INDEX(Cum_OpEx,1,Assumptions!J$77)-1),INDEX(Cum_OpEx,1,Assumptions!J$77))+(VLOOKUP($G$22,RecovMatrix,2,FALSE)*RecovCAM+VLOOKUP($G$22,RecovMatrix,3,FALSE)*RecovTax+VLOOKUP($G$22,RecovMatrix,4,FALSE)*RecovIns)*$B$22/12*IF(GrossUpOn="On",1/(1-RetailGenVacancy),1)*(1+IF(AdminFeeOn="On",AdminFeePct,0))*IF(VLOOKUP($G$22,RecovMatrix,5,FALSE)=1,MAX(0,INDEX(Cum_OpEx,1,Assumptions!J$77)-1),INDEX(Cum_OpEx,1,Assumptions!J$77)))*Assumptions!J$74 | K37: =((VLOOKUP($G$17,RecovMatrix,2,FALSE)*RecovCAM+VLOOKUP($G$17,RecovMatrix,3,FALSE)*RecovTax+VLOOKUP($G$17,RecovMatrix,4,FALSE)*RecovIns)*$B$17/12*IF(GrossUpOn="On",1/(1-RetailGenVacancy),1)*(1+IF(AdminFeeOn="On",AdminFeePct,0))*IF(VLOOKUP($G$17,RecovMatrix,5,FALSE)=1,MAX(0,INDEX(Cum_OpEx,1,Assumptions!K$77)-1),INDEX(Cum_OpEx,1,Assumptions!K$77))+(VLOOKUP($G$18,RecovMatrix,2,FALSE)*RecovCAM+VLOOKUP($G$18,RecovMatrix,3,FALSE)*RecovTax+VLOOKUP($G$18,RecovMatrix,4,FALSE)*RecovIns)*$B$18/12*IF(GrossUpOn="On",1/(1-RetailGenVacancy),1)*(1+IF(AdminFeeOn="On",AdminFeePct,0))*IF(VLOOKUP($G$18,RecovMatrix,5,FALSE)=1,MAX(0,INDEX(Cum_OpEx,1,Assumptions!K$77)-1),INDEX(Cum_OpEx,1,Assumptions!K$77))+(VLOOKUP($G$19,RecovMatrix,2,FALSE)*RecovCAM+VLOOKUP($G$19,RecovMatrix,3,FALSE)*RecovTax+VLOOKUP($G$19,RecovMatrix,4,FALSE)*RecovIns)*$B$19/12*IF(GrossUpOn="On",1/(1-RetailGenVacancy),1)*(1+IF(AdminFeeOn="On",AdminFeePct,0))*IF(VLOOKUP($G$19,RecovMatrix,5,FALSE)=1,MAX(0,INDEX(Cum_OpEx,1,Assumptions!K$77)-1),INDEX(Cum_OpEx,1,Assumptions!K$77))+(VLOOKUP($G$20,RecovMatrix,2,FALSE)*RecovCAM+VLOOKUP($G$20,RecovMatrix,3,FALSE)*RecovTax+VLOOKUP($G$20,RecovMatrix,4,FALSE)*RecovIns)*$B$20/12*IF(GrossUpOn="On",1/(1-RetailGenVacancy),1)*(1+IF(AdminFeeOn="On",AdminFeePct,0))*IF(VLOOKUP($G$20,RecovMatrix,5,FALSE)=1,MAX(0,INDEX(Cum_OpEx,1,Assumptions!K$77)-1),INDEX(Cum_OpEx,1,Assumptions!K$77))+(VLOOKUP($G$21,RecovMatrix,2,FALSE)*RecovCAM+VLOOKUP($G$21,RecovMatrix,3,FALSE)*RecovTax+VLOOKUP($G$21,RecovMatrix,4,FALSE)*RecovIns)*$B$21/12*IF(GrossUpOn="On",1/(1-RetailGenVacancy),1)*(1+IF(AdminFeeOn="On",AdminFeePct,0))*IF(VLOOKUP($G$21,RecovMatrix,5,FALSE)=1,MAX(0,INDEX(Cum_OpEx,1,Assumptions!K$77)-1),INDEX(Cum_OpEx,1,Assumptions!K$77))+(VLOOKUP($G$22,RecovMatrix,2,FALSE)*RecovCAM+VLOOKUP($G$22,RecovMatrix,3,FALSE)*RecovTax+VLOOKUP($G$22,RecovMatrix,4,FALSE)*RecovIns)*$B$22/12*IF(GrossUpOn="On",1/(1-RetailGenVacancy),1)*(1+IF(AdminFeeOn="On",AdminFeePct,0))*IF(VLOOKUP($G$22,RecovMatrix,5,FALSE)=1,MAX(0,INDEX(Cum_OpEx,1,Assumptions!K$77)-1),INDEX(Cum_OpEx,1,Assumptions!K$77)))*Assumptions!K$74 | L37: =((VLOOKUP($G$17,RecovMatrix,2,FALSE)*RecovCAM+VLOOKUP($G$17,RecovMatrix,3,FALSE)*RecovTax+VLOOKUP($G$17,RecovMatrix,4,FALSE)*RecovIns)*$B$17/12*IF(GrossUpOn="On",1/(1-RetailGenVacancy),1)*(1+IF(AdminFeeOn="On",AdminFeePct,0))*IF(VLOOKUP($G$17,RecovMatrix,5,FALSE)=1,MAX(0,INDEX(Cum_OpEx,1,Assumptions!L$77)-1),INDEX(Cum_OpEx,1,Assumptions!L$77))+(VLOOKUP($G$18,RecovMatrix,2,FALSE)*RecovCAM+VLOOKUP($G$18,RecovMatrix,3,FALSE)*RecovTax+VLOOKUP($G$18,RecovMatrix,4,FALSE)*RecovIns)*$B$18/12*IF(GrossUpOn="On",1/(1-RetailGenVacancy),1)*(1+IF(AdminFeeOn="On",AdminFeePct,0))*IF(VLOOKUP($G$18,RecovMatrix,5,FALSE)=1,MAX(0,INDEX(Cum_OpEx,1,Assumptions!L$77)-1),INDEX(Cum_OpEx,1,Assumptions!L$77))+(VLOOKUP($G$19,RecovMatrix,2,FALSE)*RecovCAM+VLOOKUP($G$19,RecovMatrix,3,FALSE)*RecovTax+VLOOKUP($G$19,RecovMatrix,4,FALSE)*RecovIns)*$B$19/12*IF(GrossUpOn="On",1/(1-RetailGenVacancy),1)*(1+IF(AdminFeeOn="On",AdminFeePct,0))*IF(VLOOKUP($G$19,RecovMatrix,5,FALSE)=1,MAX(0,INDEX(Cum_OpEx,1,Assumptions!L$77)-1),INDEX(Cum_OpEx,1,Assumptions!L$77))+(VLOOKUP($G$20,RecovMatrix,2,FALSE)*RecovCAM+VLOOKUP($G$20,RecovMatrix,3,FALSE)*RecovTax+VLOOKUP($G$20,RecovMatrix,4,FALSE)*RecovIns)*$B$20/12*IF(GrossUpOn="On",1/(1-RetailGenVacancy),1)*(1+IF(AdminFeeOn="On",AdminFeePct,0))*IF(VLOOKUP($G$20,RecovMatrix,5,FALSE)=1,MAX(0,INDEX(Cum_OpEx,1,Assumptions!L$77)-1),INDEX(Cum_OpEx,1,Assumptions!L$77))+(VLOOKUP($G$21,RecovMatrix,2,FALSE)*RecovCAM+VLOOKUP($G$21,RecovMatrix,3,FALSE)*RecovTax+VLOOKUP($G$21,RecovMatrix,4,FALSE)*RecovIns)*$B$21/12*IF(GrossUpOn="On",1/(1-RetailGenVacancy),1)*(1+IF(AdminFeeOn="On",AdminFeePct,0))*IF(VLOOKUP($G$21,RecovMatrix,5,FALSE)=1,MAX(0,INDEX(Cum_OpEx,1,Assumptions!L$77)-1),INDEX(Cum_OpEx,1,Assumptions!L$77))+(VLOOKUP($G$22,RecovMatrix,2,FALSE)*RecovCAM+VLOOKUP($G$22,RecovMatrix,3,FALSE)*RecovTax+VLOOKUP($G$22,RecovMatrix,4,FALSE)*RecovIns)*$B$22/12*IF(GrossUpOn="On",1/(1-RetailGenVacancy),1)*(1+IF(AdminFeeOn="On",AdminFeePct,0))*IF(VLOOKUP($G$22,RecovMatrix,5,FALSE)=1,MAX(0,INDEX(Cum_OpEx,1,Assumptions!L$77)-1),INDEX(Cum_OpEx,1,Assumptions!L$77)))*Assumptions!L$74 | ... DT37: =((VLOOKUP($G$17,RecovMatrix,2,FALSE)*RecovCAM+VLOOKUP($G$17,RecovMatrix,3,FALSE)*RecovTax+VLOOKUP($G$17,RecovMatrix,4,FALSE)*RecovIns)*$B$17/12*IF(GrossUpOn="On",1/(1-RetailGenVacancy),1)*(1+IF(AdminFeeOn="On",AdminFeePct,0))*IF(VLOOKUP($G$17,RecovMatrix,5,FALSE)=1,MAX(0,INDEX(Cum_OpEx,1,Assumptions!DT$77)-1),INDEX(Cum_OpEx,1,Assumptions!DT$77))+(VLOOKUP($G$18,RecovMatrix,2,FALSE)*RecovCAM+VLOOKUP($G$18,RecovMatrix,3,FALSE)*RecovTax+VLOOKUP($G$18,RecovMatrix,4,FALSE)*RecovIns)*$B$18/12*IF(GrossUpOn="On",1/(1-RetailGenVacancy),1)*(1+IF(AdminFeeOn="On",AdminFeePct,0))*IF(VLOOKUP($G$18,RecovMatrix,5,FALSE)=1,MAX(0,INDEX(Cum_OpEx,1,Assumptions!DT$77)-1),INDEX(Cum_OpEx,1,Assumptions!DT$77))+(VLOOKUP($G$19,RecovMatrix,2,FALSE)*RecovCAM+VLOOKUP($G$19,RecovMatrix,3,FALSE)*RecovTax+VLOOKUP($G$19,RecovMatrix,4,FALSE)*RecovIns)*$B$19/12*IF(GrossUpOn="On",1/(1-RetailGenVacancy),1)*(1+IF(AdminFeeOn="On",AdminFeePct,0))*IF(VLOOKUP($G$19,RecovMatrix,5,FALSE)=1,MAX(0,INDEX(Cum_OpEx,1,Assumptions!DT$77)-1),INDEX(Cum_OpEx,1,Assumptions!DT$77))+(VLOOKUP($G$20,RecovMatrix,2,FALSE)*RecovCAM+VLOOKUP($G$20,RecovMatrix,3,FALSE)*RecovTax+VLOOKUP($G$20,RecovMatrix,4,FALSE)*RecovIns)*$B$20/12*IF(GrossUpOn="On",1/(1-RetailGenVacancy),1)*(1+IF(AdminFeeOn="On",AdminFeePct,0))*IF(VLOOKUP($G$20,RecovMatrix,5,FALSE)=1,MAX(0,INDEX(Cum_OpEx,1,Assumptions!DT$77)-1),INDEX(Cum_OpEx,1,Assumptions!DT$77))+(VLOOKUP($G$21,RecovMatrix,2,FALSE)*RecovCAM+VLOOKUP($G$21,RecovMatrix,3,FALSE)*RecovTax+VLOOKUP($G$21,RecovMatrix,4,FALSE)*RecovIns)*$B$21/12*IF(GrossUpOn="On",1/(1-RetailGenVacancy),1)*(1+IF(AdminFeeOn="On",AdminFeePct,0))*IF(VLOOKUP($G$21,RecovMatrix,5,FALSE)=1,MAX(0,INDEX(Cum_OpEx,1,Assumptions!DT$77)-1),INDEX(Cum_OpEx,1,Assumptions!DT$77))+(VLOOKUP($G$22,RecovMatrix,2,FALSE)*RecovCAM+VLOOKUP($G$22,RecovMatrix,3,FALSE)*RecovTax+VLOOKUP($G$22,RecovMatrix,4,FALSE)*RecovIns)*$B$22/12*IF(GrossUpOn="On",1/(1-RetailGenVacancy),1)*(1+IF(AdminFeeOn="On",AdminFeePct,0))*IF(VLOOKUP($G$22,RecovMatrix,5,FALSE)=1,MAX(0,INDEX(Cum_OpEx,1,Assumptions!DT$77)-1),INDEX(Cum_OpEx,1,Assumptions!DT$77)))*Assumptions!DT$74
A38: General vacancy ($/mo, neg) | E38: =-(E$35+E$36+E$37)*RetailGenVacancy | F38: =-(F$35+F$36+F$37)*RetailGenVacancy | G38: =-(G$35+G$36+G$37)*RetailGenVacancy | H38: =-(H$35+H$36+H$37)*RetailGenVacancy | I38: =-(I$35+I$36+I$37)*RetailGenVacancy | J38: =-(J$35+J$36+J$37)*RetailGenVacancy | K38: =-(K$35+K$36+K$37)*RetailGenVacancy | L38: =-(L$35+L$36+L$37)*RetailGenVacancy | ... DT38: =-(DT$35+DT$36+DT$37)*RetailGenVacancy
A39: Credit loss / bad debt ($/mo, neg) | E39: =-(E$35+E$36+E$37)*(1-RetailGenVacancy)*RetailCreditLoss | F39: =-(F$35+F$36+F$37)*(1-RetailGenVacancy)*RetailCreditLoss | G39: =-(G$35+G$36+G$37)*(1-RetailGenVacancy)*RetailCreditLoss | H39: =-(H$35+H$36+H$37)*(1-RetailGenVacancy)*RetailCreditLoss | I39: =-(I$35+I$36+I$37)*(1-RetailGenVacancy)*RetailCreditLoss | J39: =-(J$35+J$36+J$37)*(1-RetailGenVacancy)*RetailCreditLoss | K39: =-(K$35+K$36+K$37)*(1-RetailGenVacancy)*RetailCreditLoss | L39: =-(L$35+L$36+L$37)*(1-RetailGenVacancy)*RetailCreditLoss | ... DT39: =-(DT$35+DT$36+DT$37)*(1-RetailGenVacancy)*RetailCreditLoss
A40: Retail EGI ($/mo) | E40: =E$35+E$36+E$37+E$38+E$39 | F40: =F$35+F$36+F$37+F$38+F$39 | G40: =G$35+G$36+G$37+G$38+G$39 | H40: =H$35+H$36+H$37+H$38+H$39 | I40: =I$35+I$36+I$37+I$38+I$39 | J40: =J$35+J$36+J$37+J$38+J$39 | K40: =K$35+K$36+K$37+K$38+K$39 | L40: =L$35+L$36+L$37+L$38+L$39 | ... DT40: =DT$35+DT$36+DT$37+DT$38+DT$39
A41: Rollover TI/LC ($, at re-let) | E41: =(IF(Assumptions!E$72=$D$17+RetailDowntime,((1-RetailRenewalProb)*NewLeaseTI+RetailRenewalProb*RenewalTI)*$B$17*INDEX(Cum_TILC,1,Assumptions!E$77)+LeasingCommissionPct*$E$17*$B$17*INDEX(Cum_TILC,1,Assumptions!E$77),0)+IF(Assumptions!E$72=$D$18+RetailDowntime,((1-RetailRenewalProb)*NewLeaseTI+RetailRenewalProb*RenewalTI)*$B$18*INDEX(Cum_TILC,1,Assumptions!E$77)+LeasingCommissionPct*$E$18*$B$18*INDEX(Cum_TILC,1,Assumptions!E$77),0)+IF(Assumptions!E$72=$D$19+RetailDowntime,((1-RetailRenewalProb)*NewLeaseTI+RetailRenewalProb*RenewalTI)*$B$19*INDEX(Cum_TILC,1,Assumptions!E$77)+LeasingCommissionPct*$E$19*$B$19*INDEX(Cum_TILC,1,Assumptions!E$77),0)+IF(Assumptions!E$72=$D$20+RetailDowntime,((1-RetailRenewalProb)*NewLeaseTI+RetailRenewalProb*RenewalTI)*$B$20*INDEX(Cum_TILC,1,Assumptions!E$77)+LeasingCommissionPct*$E$20*$B$20*INDEX(Cum_TILC,1,Assumptions!E$77),0)+IF(Assumptions!E$72=$D$21+RetailDowntime,((1-RetailRenewalProb)*NewLeaseTI+RetailRenewalProb*RenewalTI)*$B$21*INDEX(Cum_TILC,1,Assumptions!E$77)+LeasingCommissionPct*$E$21*$B$21*INDEX(Cum_TILC,1,Assumptions!E$77),0)+IF(Assumptions!E$72=$D$22+RetailDowntime,((1-RetailRenewalProb)*NewLeaseTI+RetailRenewalProb*RenewalTI)*$B$22*INDEX(Cum_TILC,1,Assumptions!E$77)+LeasingCommissionPct*$E$22*$B$22*INDEX(Cum_TILC,1,Assumptions!E$77),0))*Assumptions!E$74 | F41: =(IF(Assumptions!F$72=$D$17+RetailDowntime,((1-RetailRenewalProb)*NewLeaseTI+RetailRenewalProb*RenewalTI)*$B$17*INDEX(Cum_TILC,1,Assumptions!F$77)+LeasingCommissionPct*$E$17*$B$17*INDEX(Cum_TILC,1,Assumptions!F$77),0)+IF(Assumptions!F$72=$D$18+RetailDowntime,((1-RetailRenewalProb)*NewLeaseTI+RetailRenewalProb*RenewalTI)*$B$18*INDEX(Cum_TILC,1,Assumptions!F$77)+LeasingCommissionPct*$E$18*$B$18*INDEX(Cum_TILC,1,Assumptions!F$77),0)+IF(Assumptions!F$72=$D$19+RetailDowntime,((1-RetailRenewalProb)*NewLeaseTI+RetailRenewalProb*RenewalTI)*$B$19*INDEX(Cum_TILC,1,Assumptions!F$77)+LeasingCommissionPct*$E$19*$B$19*INDEX(Cum_TILC,1,Assumptions!F$77),0)+IF(Assumptions!F$72=$D$20+RetailDowntime,((1-RetailRenewalProb)*NewLeaseTI+RetailRenewalProb*RenewalTI)*$B$20*INDEX(Cum_TILC,1,Assumptions!F$77)+LeasingCommissionPct*$E$20*$B$20*INDEX(Cum_TILC,1,Assumptions!F$77),0)+IF(Assumptions!F$72=$D$21+RetailDowntime,((1-RetailRenewalProb)*NewLeaseTI+RetailRenewalProb*RenewalTI)*$B$21*INDEX(Cum_TILC,1,Assumptions!F$77)+LeasingCommissionPct*$E$21*$B$21*INDEX(Cum_TILC,1,Assumptions!F$77),0)+IF(Assumptions!F$72=$D$22+RetailDowntime,((1-RetailRenewalProb)*NewLeaseTI+RetailRenewalProb*RenewalTI)*$B$22*INDEX(Cum_TILC,1,Assumptions!F$77)+LeasingCommissionPct*$E$22*$B$22*INDEX(Cum_TILC,1,Assumptions!F$77),0))*Assumptions!F$74 | G41: =(IF(Assumptions!G$72=$D$17+RetailDowntime,((1-RetailRenewalProb)*NewLeaseTI+RetailRenewalProb*RenewalTI)*$B$17*INDEX(Cum_TILC,1,Assumptions!G$77)+LeasingCommissionPct*$E$17*$B$17*INDEX(Cum_TILC,1,Assumptions!G$77),0)+IF(Assumptions!G$72=$D$18+RetailDowntime,((1-RetailRenewalProb)*NewLeaseTI+RetailRenewalProb*RenewalTI)*$B$18*INDEX(Cum_TILC,1,Assumptions!G$77)+LeasingCommissionPct*$E$18*$B$18*INDEX(Cum_TILC,1,Assumptions!G$77),0)+IF(Assumptions!G$72=$D$19+RetailDowntime,((1-RetailRenewalProb)*NewLeaseTI+RetailRenewalProb*RenewalTI)*$B$19*INDEX(Cum_TILC,1,Assumptions!G$77)+LeasingCommissionPct*$E$19*$B$19*INDEX(Cum_TILC,1,Assumptions!G$77),0)+IF(Assumptions!G$72=$D$20+RetailDowntime,((1-RetailRenewalProb)*NewLeaseTI+RetailRenewalProb*RenewalTI)*$B$20*INDEX(Cum_TILC,1,Assumptions!G$77)+LeasingCommissionPct*$E$20*$B$20*INDEX(Cum_TILC,1,Assumptions!G$77),0)+IF(Assumptions!G$72=$D$21+RetailDowntime,((1-RetailRenewalProb)*NewLeaseTI+RetailRenewalProb*RenewalTI)*$B$21*INDEX(Cum_TILC,1,Assumptions!G$77)+LeasingCommissionPct*$E$21*$B$21*INDEX(Cum_TILC,1,Assumptions!G$77),0)+IF(Assumptions!G$72=$D$22+RetailDowntime,((1-RetailRenewalProb)*NewLeaseTI+RetailRenewalProb*RenewalTI)*$B$22*INDEX(Cum_TILC,1,Assumptions!G$77)+LeasingCommissionPct*$E$22*$B$22*INDEX(Cum_TILC,1,Assumptions!G$77),0))*Assumptions!G$74 | H41: =(IF(Assumptions!H$72=$D$17+RetailDowntime,((1-RetailRenewalProb)*NewLeaseTI+RetailRenewalProb*RenewalTI)*$B$17*INDEX(Cum_TILC,1,Assumptions!H$77)+LeasingCommissionPct*$E$17*$B$17*INDEX(Cum_TILC,1,Assumptions!H$77),0)+IF(Assumptions!H$72=$D$18+RetailDowntime,((1-RetailRenewalProb)*NewLeaseTI+RetailRenewalProb*RenewalTI)*$B$18*INDEX(Cum_TILC,1,Assumptions!H$77)+LeasingCommissionPct*$E$18*$B$18*INDEX(Cum_TILC,1,Assumptions!H$77),0)+IF(Assumptions!H$72=$D$19+RetailDowntime,((1-RetailRenewalProb)*NewLeaseTI+RetailRenewalProb*RenewalTI)*$B$19*INDEX(Cum_TILC,1,Assumptions!H$77)+LeasingCommissionPct*$E$19*$B$19*INDEX(Cum_TILC,1,Assumptions!H$77),0)+IF(Assumptions!H$72=$D$20+RetailDowntime,((1-RetailRenewalProb)*NewLeaseTI+RetailRenewalProb*RenewalTI)*$B$20*INDEX(Cum_TILC,1,Assumptions!H$77)+LeasingCommissionPct*$E$20*$B$20*INDEX(Cum_TILC,1,Assumptions!H$77),0)+IF(Assumptions!H$72=$D$21+RetailDowntime,((1-RetailRenewalProb)*NewLeaseTI+RetailRenewalProb*RenewalTI)*$B$21*INDEX(Cum_TILC,1,Assumptions!H$77)+LeasingCommissionPct*$E$21*$B$21*INDEX(Cum_TILC,1,Assumptions!H$77),0)+IF(Assumptions!H$72=$D$22+RetailDowntime,((1-RetailRenewalProb)*NewLeaseTI+RetailRenewalProb*RenewalTI)*$B$22*INDEX(Cum_TILC,1,Assumptions!H$77)+LeasingCommissionPct*$E$22*$B$22*INDEX(Cum_TILC,1,Assumptions!H$77),0))*Assumptions!H$74 | I41: =(IF(Assumptions!I$72=$D$17+RetailDowntime,((1-RetailRenewalProb)*NewLeaseTI+RetailRenewalProb*RenewalTI)*$B$17*INDEX(Cum_TILC,1,Assumptions!I$77)+LeasingCommissionPct*$E$17*$B$17*INDEX(Cum_TILC,1,Assumptions!I$77),0)+IF(Assumptions!I$72=$D$18+RetailDowntime,((1-RetailRenewalProb)*NewLeaseTI+RetailRenewalProb*RenewalTI)*$B$18*INDEX(Cum_TILC,1,Assumptions!I$77)+LeasingCommissionPct*$E$18*$B$18*INDEX(Cum_TILC,1,Assumptions!I$77),0)+IF(Assumptions!I$72=$D$19+RetailDowntime,((1-RetailRenewalProb)*NewLeaseTI+RetailRenewalProb*RenewalTI)*$B$19*INDEX(Cum_TILC,1,Assumptions!I$77)+LeasingCommissionPct*$E$19*$B$19*INDEX(Cum_TILC,1,Assumptions!I$77),0)+IF(Assumptions!I$72=$D$20+RetailDowntime,((1-RetailRenewalProb)*NewLeaseTI+RetailRenewalProb*RenewalTI)*$B$20*INDEX(Cum_TILC,1,Assumptions!I$77)+LeasingCommissionPct*$E$20*$B$20*INDEX(Cum_TILC,1,Assumptions!I$77),0)+IF(Assumptions!I$72=$D$21+RetailDowntime,((1-RetailRenewalProb)*NewLeaseTI+RetailRenewalProb*RenewalTI)*$B$21*INDEX(Cum_TILC,1,Assumptions!I$77)+LeasingCommissionPct*$E$21*$B$21*INDEX(Cum_TILC,1,Assumptions!I$77),0)+IF(Assumptions!I$72=$D$22+RetailDowntime,((1-RetailRenewalProb)*NewLeaseTI+RetailRenewalProb*RenewalTI)*$B$22*INDEX(Cum_TILC,1,Assumptions!I$77)+LeasingCommissionPct*$E$22*$B$22*INDEX(Cum_TILC,1,Assumptions!I$77),0))*Assumptions!I$74 | J41: =(IF(Assumptions!J$72=$D$17+RetailDowntime,((1-RetailRenewalProb)*NewLeaseTI+RetailRenewalProb*RenewalTI)*$B$17*INDEX(Cum_TILC,1,Assumptions!J$77)+LeasingCommissionPct*$E$17*$B$17*INDEX(Cum_TILC,1,Assumptions!J$77),0)+IF(Assumptions!J$72=$D$18+RetailDowntime,((1-RetailRenewalProb)*NewLeaseTI+RetailRenewalProb*RenewalTI)*$B$18*INDEX(Cum_TILC,1,Assumptions!J$77)+LeasingCommissionPct*$E$18*$B$18*INDEX(Cum_TILC,1,Assumptions!J$77),0)+IF(Assumptions!J$72=$D$19+RetailDowntime,((1-RetailRenewalProb)*NewLeaseTI+RetailRenewalProb*RenewalTI)*$B$19*INDEX(Cum_TILC,1,Assumptions!J$77)+LeasingCommissionPct*$E$19*$B$19*INDEX(Cum_TILC,1,Assumptions!J$77),0)+IF(Assumptions!J$72=$D$20+RetailDowntime,((1-RetailRenewalProb)*NewLeaseTI+RetailRenewalProb*RenewalTI)*$B$20*INDEX(Cum_TILC,1,Assumptions!J$77)+LeasingCommissionPct*$E$20*$B$20*INDEX(Cum_TILC,1,Assumptions!J$77),0)+IF(Assumptions!J$72=$D$21+RetailDowntime,((1-RetailRenewalProb)*NewLeaseTI+RetailRenewalProb*RenewalTI)*$B$21*INDEX(Cum_TILC,1,Assumptions!J$77)+LeasingCommissionPct*$E$21*$B$21*INDEX(Cum_TILC,1,Assumptions!J$77),0)+IF(Assumptions!J$72=$D$22+RetailDowntime,((1-RetailRenewalProb)*NewLeaseTI+RetailRenewalProb*RenewalTI)*$B$22*INDEX(Cum_TILC,1,Assumptions!J$77)+LeasingCommissionPct*$E$22*$B$22*INDEX(Cum_TILC,1,Assumptions!J$77),0))*Assumptions!J$74 | K41: =(IF(Assumptions!K$72=$D$17+RetailDowntime,((1-RetailRenewalProb)*NewLeaseTI+RetailRenewalProb*RenewalTI)*$B$17*INDEX(Cum_TILC,1,Assumptions!K$77)+LeasingCommissionPct*$E$17*$B$17*INDEX(Cum_TILC,1,Assumptions!K$77),0)+IF(Assumptions!K$72=$D$18+RetailDowntime,((1-RetailRenewalProb)*NewLeaseTI+RetailRenewalProb*RenewalTI)*$B$18*INDEX(Cum_TILC,1,Assumptions!K$77)+LeasingCommissionPct*$E$18*$B$18*INDEX(Cum_TILC,1,Assumptions!K$77),0)+IF(Assumptions!K$72=$D$19+RetailDowntime,((1-RetailRenewalProb)*NewLeaseTI+RetailRenewalProb*RenewalTI)*$B$19*INDEX(Cum_TILC,1,Assumptions!K$77)+LeasingCommissionPct*$E$19*$B$19*INDEX(Cum_TILC,1,Assumptions!K$77),0)+IF(Assumptions!K$72=$D$20+RetailDowntime,((1-RetailRenewalProb)*NewLeaseTI+RetailRenewalProb*RenewalTI)*$B$20*INDEX(Cum_TILC,1,Assumptions!K$77)+LeasingCommissionPct*$E$20*$B$20*INDEX(Cum_TILC,1,Assumptions!K$77),0)+IF(Assumptions!K$72=$D$21+RetailDowntime,((1-RetailRenewalProb)*NewLeaseTI+RetailRenewalProb*RenewalTI)*$B$21*INDEX(Cum_TILC,1,Assumptions!K$77)+LeasingCommissionPct*$E$21*$B$21*INDEX(Cum_TILC,1,Assumptions!K$77),0)+IF(Assumptions!K$72=$D$22+RetailDowntime,((1-RetailRenewalProb)*NewLeaseTI+RetailRenewalProb*RenewalTI)*$B$22*INDEX(Cum_TILC,1,Assumptions!K$77)+LeasingCommissionPct*$E$22*$B$22*INDEX(Cum_TILC,1,Assumptions!K$77),0))*Assumptions!K$74 | L41: =(IF(Assumptions!L$72=$D$17+RetailDowntime,((1-RetailRenewalProb)*NewLeaseTI+RetailRenewalProb*RenewalTI)*$B$17*INDEX(Cum_TILC,1,Assumptions!L$77)+LeasingCommissionPct*$E$17*$B$17*INDEX(Cum_TILC,1,Assumptions!L$77),0)+IF(Assumptions!L$72=$D$18+RetailDowntime,((1-RetailRenewalProb)*NewLeaseTI+RetailRenewalProb*RenewalTI)*$B$18*INDEX(Cum_TILC,1,Assumptions!L$77)+LeasingCommissionPct*$E$18*$B$18*INDEX(Cum_TILC,1,Assumptions!L$77),0)+IF(Assumptions!L$72=$D$19+RetailDowntime,((1-RetailRenewalProb)*NewLeaseTI+RetailRenewalProb*RenewalTI)*$B$19*INDEX(Cum_TILC,1,Assumptions!L$77)+LeasingCommissionPct*$E$19*$B$19*INDEX(Cum_TILC,1,Assumptions!L$77),0)+IF(Assumptions!L$72=$D$20+RetailDowntime,((1-RetailRenewalProb)*NewLeaseTI+RetailRenewalProb*RenewalTI)*$B$20*INDEX(Cum_TILC,1,Assumptions!L$77)+LeasingCommissionPct*$E$20*$B$20*INDEX(Cum_TILC,1,Assumptions!L$77),0)+IF(Assumptions!L$72=$D$21+RetailDowntime,((1-RetailRenewalProb)*NewLeaseTI+RetailRenewalProb*RenewalTI)*$B$21*INDEX(Cum_TILC,1,Assumptions!L$77)+LeasingCommissionPct*$E$21*$B$21*INDEX(Cum_TILC,1,Assumptions!L$77),0)+IF(Assumptions!L$72=$D$22+RetailDowntime,((1-RetailRenewalProb)*NewLeaseTI+RetailRenewalProb*RenewalTI)*$B$22*INDEX(Cum_TILC,1,Assumptions!L$77)+LeasingCommissionPct*$E$22*$B$22*INDEX(Cum_TILC,1,Assumptions!L$77),0))*Assumptions!L$74 | ... DT41: =(IF(Assumptions!DT$72=$D$17+RetailDowntime,((1-RetailRenewalProb)*NewLeaseTI+RetailRenewalProb*RenewalTI)*$B$17*INDEX(Cum_TILC,1,Assumptions!DT$77)+LeasingCommissionPct*$E$17*$B$17*INDEX(Cum_TILC,1,Assumptions!DT$77),0)+IF(Assumptions!DT$72=$D$18+RetailDowntime,((1-RetailRenewalProb)*NewLeaseTI+RetailRenewalProb*RenewalTI)*$B$18*INDEX(Cum_TILC,1,Assumptions!DT$77)+LeasingCommissionPct*$E$18*$B$18*INDEX(Cum_TILC,1,Assumptions!DT$77),0)+IF(Assumptions!DT$72=$D$19+RetailDowntime,((1-RetailRenewalProb)*NewLeaseTI+RetailRenewalProb*RenewalTI)*$B$19*INDEX(Cum_TILC,1,Assumptions!DT$77)+LeasingCommissionPct*$E$19*$B$19*INDEX(Cum_TILC,1,Assumptions!DT$77),0)+IF(Assumptions!DT$72=$D$20+RetailDowntime,((1-RetailRenewalProb)*NewLeaseTI+RetailRenewalProb*RenewalTI)*$B$20*INDEX(Cum_TILC,1,Assumptions!DT$77)+LeasingCommissionPct*$E$20*$B$20*INDEX(Cum_TILC,1,Assumptions!DT$77),0)+IF(Assumptions!DT$72=$D$21+RetailDowntime,((1-RetailRenewalProb)*NewLeaseTI+RetailRenewalProb*RenewalTI)*$B$21*INDEX(Cum_TILC,1,Assumptions!DT$77)+LeasingCommissionPct*$E$21*$B$21*INDEX(Cum_TILC,1,Assumptions!DT$77),0)+IF(Assumptions!DT$72=$D$22+RetailDowntime,((1-RetailRenewalProb)*NewLeaseTI+RetailRenewalProb*RenewalTI)*$B$22*INDEX(Cum_TILC,1,Assumptions!DT$77)+LeasingCommissionPct*$E$22*$B$22*INDEX(Cum_TILC,1,Assumptions!DT$77),0))*Assumptions!DT$74

Sheet OpEx
A1: OPERATING EXPENSES
A2: Asset: | B2: =AssetName | D2: Run date: | E2: =RunDate | G2: Business plan: | H2: =BusinessPlanMode | J2: Hold (mo): | K2: =HoldMonths
A3: Model status: | B3: =ModelStatus
A5: Line item | B5: $/unit/yr (base)
A6: Payroll | B6: 1400
A7: R&M | B7: 900
A8: Utilities | B8: 1100
A9: G&A | B9: 500
A10: Marketing | B10: 250
A11: Insurance | B11: 600
A12: Other | B12: 300
A14: MONTHLY OPEX BUILD (negative outflows)
A15: Month index | E15: =Assumptions!E$72 | F15: =Assumptions!F$72 | G15: =Assumptions!G$72 | H15: =Assumptions!H$72 | I15: =Assumptions!I$72 | J15: =Assumptions!J$72 | K15: =Assumptions!K$72 | L15: =Assumptions!L$72 | ... DT15: =Assumptions!DT$72
A16: Controllable OpEx ($/mo, neg) | E16: =-SUM($B$6:$B$12)*MF_UnitCount/12*INDEX(Cum_OpEx,1,Assumptions!E$77)*Assumptions!E$74 | F16: =-SUM($B$6:$B$12)*MF_UnitCount/12*INDEX(Cum_OpEx,1,Assumptions!F$77)*Assumptions!F$74 | G16: =-SUM($B$6:$B$12)*MF_UnitCount/12*INDEX(Cum_OpEx,1,Assumptions!G$77)*Assumptions!G$74 | H16: =-SUM($B$6:$B$12)*MF_UnitCount/12*INDEX(Cum_OpEx,1,Assumptions!H$77)*Assumptions!H$74 | I16: =-SUM($B$6:$B$12)*MF_UnitCount/12*INDEX(Cum_OpEx,1,Assumptions!I$77)*Assumptions!I$74 | J16: =-SUM($B$6:$B$12)*MF_UnitCount/12*INDEX(Cum_OpEx,1,Assumptions!J$77)*Assumptions!J$74 | K16: =-SUM($B$6:$B$12)*MF_UnitCount/12*INDEX(Cum_OpEx,1,Assumptions!K$77)*Assumptions!K$74 | L16: =-SUM($B$6:$B$12)*MF_UnitCount/12*INDEX(Cum_OpEx,1,Assumptions!L$77)*Assumptions!L$74 | ... DT16: =-SUM($B$6:$B$12)*MF_UnitCount/12*INDEX(Cum_OpEx,1,Assumptions!DT$77)*Assumptions!DT$74
A17: Management fee ($/mo, neg) | E17: =-('MF Revenue'!E$114+'Retail Revenue'!E$40)*MgmtFeePct | F17: =-('MF Revenue'!F$114+'Retail Revenue'!F$40)*MgmtFeePct | G17: =-('MF Revenue'!G$114+'Retail Revenue'!G$40)*MgmtFeePct | H17: =-('MF Revenue'!H$114+'Retail Revenue'!H$40)*MgmtFeePct | I17: =-('MF Revenue'!I$114+'Retail Revenue'!I$40)*MgmtFeePct | J17: =-('MF Revenue'!J$114+'Retail Revenue'!J$40)*MgmtFeePct | K17: =-('MF Revenue'!K$114+'Retail Revenue'!K$40)*MgmtFeePct | L17: =-('MF Revenue'!L$114+'Retail Revenue'!L$40)*MgmtFeePct | ... DT17: =-('MF Revenue'!DT$114+'Retail Revenue'!DT$40)*MgmtFeePct
A18: Replacement reserves ($/mo, neg) | E18: =-ReplReservePU*MF_UnitCount/12*Assumptions!E$74 | F18: =-ReplReservePU*MF_UnitCount/12*Assumptions!F$74 | G18: =-ReplReservePU*MF_UnitCount/12*Assumptions!G$74 | H18: =-ReplReservePU*MF_UnitCount/12*Assumptions!H$74 | I18: =-ReplReservePU*MF_UnitCount/12*Assumptions!I$74 | J18: =-ReplReservePU*MF_UnitCount/12*Assumptions!J$74 | K18: =-ReplReservePU*MF_UnitCount/12*Assumptions!K$74 | L18: =-ReplReservePU*MF_UnitCount/12*Assumptions!L$74 | ... DT18: =-ReplReservePU*MF_UnitCount/12*Assumptions!DT$74
A19: Total OpEx excl. taxes & reserves ($/mo, neg) | E19: =E$16+E$17 | F19: =F$16+F$17 | G19: =G$16+G$17 | H19: =H$16+H$17 | I19: =I$16+I$17 | J19: =J$16+J$17 | K19: =K$16+K$17 | L19: =L$16+L$17 | ... DT19: =DT$16+DT$17

Sheet Taxes
A1: REAL ESTATE TAXES
A2: Asset: | B2: =AssetName | D2: Run date: | E2: =RunDate | G2: Business plan: | H2: =BusinessPlanMode | J2: Hold (mo): | K2: =HoldMonths
A3: Model status: | B3: =ModelStatus
A5: PILOT / Abatement schedule (annual $ by hold year; used when Tax Method = PILOT)
A6: Hold year | E6: 1 | F6: 2 | G6: 3 | H6: 4 | I6: 5 | J6: 6 | K6: 7 | L6: 8 | M6: 9 | N6: 10 | O6: 11
A7: PILOT annual tax ($) | E7: 200000 | F7: 250000 | G7: 300000 | H7: 350000 | I7: 400000 | J7: 450000 | K7: 500000 | L7: 550000 | M7: 600000 | N7: 650000 | O7: 700000
A9: MONTHLY TAX BUILD (method per toggle #13)
A10: Month index | E10: =Assumptions!E$72 | F10: =Assumptions!F$72 | G10: =Assumptions!G$72 | H10: =Assumptions!H$72 | I10: =Assumptions!I$72 | J10: =Assumptions!J$72 | K10: =Assumptions!K$72 | L10: =Assumptions!L$72 | ... DT10: =Assumptions!DT$72
A11: Annual tax (method-driven $) | E11: =IF(TaxMethod="Flat Growth",BaseAnnualTax*(1+TaxFlatGrowth)^(MAX(Assumptions!E$75-1,0)),IF(TaxMethod="PILOT / Abatement",INDEX(PILOTSchedule,1,MIN(MAX(Assumptions!E$75,1),11)),PurchasePrice*AssessRatio*MillRate*(1+TaxFlatGrowth)^(MAX(Assumptions!E$75-1,0)))) | F11: =IF(TaxMethod="Flat Growth",BaseAnnualTax*(1+TaxFlatGrowth)^(MAX(Assumptions!F$75-1,0)),IF(TaxMethod="PILOT / Abatement",INDEX(PILOTSchedule,1,MIN(MAX(Assumptions!F$75,1),11)),PurchasePrice*AssessRatio*MillRate*(1+TaxFlatGrowth)^(MAX(Assumptions!F$75-1,0)))) | G11: =IF(TaxMethod="Flat Growth",BaseAnnualTax*(1+TaxFlatGrowth)^(MAX(Assumptions!G$75-1,0)),IF(TaxMethod="PILOT / Abatement",INDEX(PILOTSchedule,1,MIN(MAX(Assumptions!G$75,1),11)),PurchasePrice*AssessRatio*MillRate*(1+TaxFlatGrowth)^(MAX(Assumptions!G$75-1,0)))) | H11: =IF(TaxMethod="Flat Growth",BaseAnnualTax*(1+TaxFlatGrowth)^(MAX(Assumptions!H$75-1,0)),IF(TaxMethod="PILOT / Abatement",INDEX(PILOTSchedule,1,MIN(MAX(Assumptions!H$75,1),11)),PurchasePrice*AssessRatio*MillRate*(1+TaxFlatGrowth)^(MAX(Assumptions!H$75-1,0)))) | I11: =IF(TaxMethod="Flat Growth",BaseAnnualTax*(1+TaxFlatGrowth)^(MAX(Assumptions!I$75-1,0)),IF(TaxMethod="PILOT / Abatement",INDEX(PILOTSchedule,1,MIN(MAX(Assumptions!I$75,1),11)),PurchasePrice*AssessRatio*MillRate*(1+TaxFlatGrowth)^(MAX(Assumptions!I$75-1,0)))) | J11: =IF(TaxMethod="Flat Growth",BaseAnnualTax*(1+TaxFlatGrowth)^(MAX(Assumptions!J$75-1,0)),IF(TaxMethod="PILOT / Abatement",INDEX(PILOTSchedule,1,MIN(MAX(Assumptions!J$75,1),11)),PurchasePrice*AssessRatio*MillRate*(1+TaxFlatGrowth)^(MAX(Assumptions!J$75-1,0)))) | K11: =IF(TaxMethod="Flat Growth",BaseAnnualTax*(1+TaxFlatGrowth)^(MAX(Assumptions!K$75-1,0)),IF(TaxMethod="PILOT / Abatement",INDEX(PILOTSchedule,1,MIN(MAX(Assumptions!K$75,1),11)),PurchasePrice*AssessRatio*MillRate*(1+TaxFlatGrowth)^(MAX(Assumptions!K$75-1,0)))) | L11: =IF(TaxMethod="Flat Growth",BaseAnnualTax*(1+TaxFlatGrowth)^(MAX(Assumptions!L$75-1,0)),IF(TaxMethod="PILOT / Abatement",INDEX(PILOTSchedule,1,MIN(MAX(Assumptions!L$75,1),11)),PurchasePrice*AssessRatio*MillRate*(1+TaxFlatGrowth)^(MAX(Assumptions!L$75-1,0)))) | ... DT11: =IF(TaxMethod="Flat Growth",BaseAnnualTax*(1+TaxFlatGrowth)^(MAX(Assumptions!DT$75-1,0)),IF(TaxMethod="PILOT / Abatement",INDEX(PILOTSchedule,1,MIN(MAX(Assumptions!DT$75,1),11)),PurchasePrice*AssessRatio*MillRate*(1+TaxFlatGrowth)^(MAX(Assumptions!DT$75-1,0))))
A12: Monthly tax ($/mo, neg) | E12: =-E$11/12*Assumptions!E$74 | F12: =-F$11/12*Assumptions!F$74 | G12: =-G$11/12*Assumptions!G$74 | H12: =-H$11/12*Assumptions!H$74 | I12: =-I$11/12*Assumptions!I$74 | J12: =-J$11/12*Assumptions!J$74 | K12: =-K$11/12*Assumptions!K$74 | L12: =-L$11/12*Assumptions!L$74 | ... DT12: =-DT$11/12*Assumptions!DT$74

Sheet CapEx
A1: CAPEX / CAPITAL BUDGET
A2: Asset: | B2: =AssetName | D2: Run date: | E2: =RunDate | G2: Business plan: | H2: =BusinessPlanMode | J2: Hold (mo): | K2: =HoldMonths
A3: Model status: | B3: =ModelStatus
A5: Capital budget buckets
A6: Bucket | B6: Amount ($) | C6: Funding | D6: Spend start (mo) | E6: Spend months
A7: Immediate/deferred repairs | B7: 1500000 | C7: =Fund_Repairs | D7: 1 | E7: 6
A8: Value-add unit renovation | B8: =IF(BusinessPlanMode="Value-Add",RenoCostUnit*MF_UnitCount,0) | C8: =Fund_Reno | D8: 1 | E8: 24
A9: Retail TI/LC reserve | B9: 1200000 | C9: =Fund_TILC | D9: 1 | E9: 36
A10: Contingency | B10: 600000 | C10: =Fund_Contingency | D10: 1 | E10: 12
A11: Total capital budget | B11: =SUM(B7:B10)
A12: Equity-funded capital | B12: =SUMIF(C7:C10,"Equity",B7:B10)
A13: Financed capital (loan holdback) | B13: =SUMIF(C7:C10,"Financed",B7:B10)
A15: MONTHLY CAPITAL SPEND ($/mo, neg)
A16: Month index | E16: =Assumptions!E$72 | F16: =Assumptions!F$72 | G16: =Assumptions!G$72 | H16: =Assumptions!H$72 | I16: =Assumptions!I$72 | J16: =Assumptions!J$72 | K16: =Assumptions!K$72 | L16: =Assumptions!L$72 | ... DT16: =Assumptions!DT$72
A17: Capital budget spend ($/mo, neg) | E17: =-(IF(AND(Assumptions!E$72>=$D$7,Assumptions!E$72<$D$7+$E$7),$B$7/$E$7,0)+IF(AND(Assumptions!E$72>=$D$8,Assumptions!E$72<$D$8+$E$8),$B$8/$E$8,0)+IF(AND(Assumptions!E$72>=$D$9,Assumptions!E$72<$D$9+$E$9),$B$9/$E$9,0)+IF(AND(Assumptions!E$72>=$D$10,Assumptions!E$72<$D$10+$E$10),$B$10/$E$10,0)) | F17: =-(IF(AND(Assumptions!F$72>=$D$7,Assumptions!F$72<$D$7+$E$7),$B$7/$E$7,0)+IF(AND(Assumptions!F$72>=$D$8,Assumptions!F$72<$D$8+$E$8),$B$8/$E$8,0)+IF(AND(Assumptions!F$72>=$D$9,Assumptions!F$72<$D$9+$E$9),$B$9/$E$9,0)+IF(AND(Assumptions!F$72>=$D$10,Assumptions!F$72<$D$10+$E$10),$B$10/$E$10,0)) | G17: =-(IF(AND(Assumptions!G$72>=$D$7,Assumptions!G$72<$D$7+$E$7),$B$7/$E$7,0)+IF(AND(Assumptions!G$72>=$D$8,Assumptions!G$72<$D$8+$E$8),$B$8/$E$8,0)+IF(AND(Assumptions!G$72>=$D$9,Assumptions!G$72<$D$9+$E$9),$B$9/$E$9,0)+IF(AND(Assumptions!G$72>=$D$10,Assumptions!G$72<$D$10+$E$10),$B$10/$E$10,0)) | H17: =-(IF(AND(Assumptions!H$72>=$D$7,Assumptions!H$72<$D$7+$E$7),$B$7/$E$7,0)+IF(AND(Assumptions!H$72>=$D$8,Assumptions!H$72<$D$8+$E$8),$B$8/$E$8,0)+IF(AND(Assumptions!H$72>=$D$9,Assumptions!H$72<$D$9+$E$9),$B$9/$E$9,0)+IF(AND(Assumptions!H$72>=$D$10,Assumptions!H$72<$D$10+$E$10),$B$10/$E$10,0)) | I17: =-(IF(AND(Assumptions!I$72>=$D$7,Assumptions!I$72<$D$7+$E$7),$B$7/$E$7,0)+IF(AND(Assumptions!I$72>=$D$8,Assumptions!I$72<$D$8+$E$8),$B$8/$E$8,0)+IF(AND(Assumptions!I$72>=$D$9,Assumptions!I$72<$D$9+$E$9),$B$9/$E$9,0)+IF(AND(Assumptions!I$72>=$D$10,Assumptions!I$72<$D$10+$E$10),$B$10/$E$10,0)) | J17: =-(IF(AND(Assumptions!J$72>=$D$7,Assumptions!J$72<$D$7+$E$7),$B$7/$E$7,0)+IF(AND(Assumptions!J$72>=$D$8,Assumptions!J$72<$D$8+$E$8),$B$8/$E$8,0)+IF(AND(Assumptions!J$72>=$D$9,Assumptions!J$72<$D$9+$E$9),$B$9/$E$9,0)+IF(AND(Assumptions!J$72>=$D$10,Assumptions!J$72<$D$10+$E$10),$B$10/$E$10,0)) | K17: =-(IF(AND(Assumptions!K$72>=$D$7,Assumptions!K$72<$D$7+$E$7),$B$7/$E$7,0)+IF(AND(Assumptions!K$72>=$D$8,Assumptions!K$72<$D$8+$E$8),$B$8/$E$8,0)+IF(AND(Assumptions!K$72>=$D$9,Assumptions!K$72<$D$9+$E$9),$B$9/$E$9,0)+IF(AND(Assumptions!K$72>=$D$10,Assumptions!K$72<$D$10+$E$10),$B$10/$E$10,0)) | L17: =-(IF(AND(Assumptions!L$72>=$D$7,Assumptions!L$72<$D$7+$E$7),$B$7/$E$7,0)+IF(AND(Assumptions!L$72>=$D$8,Assumptions!L$72<$D$8+$E$8),$B$8/$E$8,0)+IF(AND(Assumptions!L$72>=$D$9,Assumptions!L$72<$D$9+$E$9),$B$9/$E$9,0)+IF(AND(Assumptions!L$72>=$D$10,Assumptions!L$72<$D$10+$E$10),$B$10/$E$10,0)) | ... DT17: =-(IF(AND(Assumptions!DT$72>=$D$7,Assumptions!DT$72<$D$7+$E$7),$B$7/$E$7,0)+IF(AND(Assumptions!DT$72>=$D$8,Assumptions!DT$72<$D$8+$E$8),$B$8/$E$8,0)+IF(AND(Assumptions!DT$72>=$D$9,Assumptions!DT$72<$D$9+$E$9),$B$9/$E$9,0)+IF(AND(Assumptions!DT$72>=$D$10,Assumptions!DT$72<$D$10+$E$10),$B$10/$E$10,0))
A18: Financed capital draw ($/mo, +) | E18: =(IF(AND(Assumptions!E$72>=$D$7,Assumptions!E$72<$D$7+$E$7,$C$7="Financed"),$B$7/$E$7,0)+IF(AND(Assumptions!E$72>=$D$8,Assumptions!E$72<$D$8+$E$8,$C$8="Financed"),$B$8/$E$8,0)+IF(AND(Assumptions!E$72>=$D$9,Assumptions!E$72<$D$9+$E$9,$C$9="Financed"),$B$9/$E$9,0)+IF(AND(Assumptions!E$72>=$D$10,Assumptions!E$72<$D$10+$E$10,$C$10="Financed"),$B$10/$E$10,0)) | F18: =(IF(AND(Assumptions!F$72>=$D$7,Assumptions!F$72<$D$7+$E$7,$C$7="Financed"),$B$7/$E$7,0)+IF(AND(Assumptions!F$72>=$D$8,Assumptions!F$72<$D$8+$E$8,$C$8="Financed"),$B$8/$E$8,0)+IF(AND(Assumptions!F$72>=$D$9,Assumptions!F$72<$D$9+$E$9,$C$9="Financed"),$B$9/$E$9,0)+IF(AND(Assumptions!F$72>=$D$10,Assumptions!F$72<$D$10+$E$10,$C$10="Financed"),$B$10/$E$10,0)) | G18: =(IF(AND(Assumptions!G$72>=$D$7,Assumptions!G$72<$D$7+$E$7,$C$7="Financed"),$B$7/$E$7,0)+IF(AND(Assumptions!G$72>=$D$8,Assumptions!G$72<$D$8+$E$8,$C$8="Financed"),$B$8/$E$8,0)+IF(AND(Assumptions!G$72>=$D$9,Assumptions!G$72<$D$9+$E$9,$C$9="Financed"),$B$9/$E$9,0)+IF(AND(Assumptions!G$72>=$D$10,Assumptions!G$72<$D$10+$E$10,$C$10="Financed"),$B$10/$E$10,0)) | H18: =(IF(AND(Assumptions!H$72>=$D$7,Assumptions!H$72<$D$7+$E$7,$C$7="Financed"),$B$7/$E$7,0)+IF(AND(Assumptions!H$72>=$D$8,Assumptions!H$72<$D$8+$E$8,$C$8="Financed"),$B$8/$E$8,0)+IF(AND(Assumptions!H$72>=$D$9,Assumptions!H$72<$D$9+$E$9,$C$9="Financed"),$B$9/$E$9,0)+IF(AND(Assumptions!H$72>=$D$10,Assumptions!H$72<$D$10+$E$10,$C$10="Financed"),$B$10/$E$10,0)) | I18: =(IF(AND(Assumptions!I$72>=$D$7,Assumptions!I$72<$D$7+$E$7,$C$7="Financed"),$B$7/$E$7,0)+IF(AND(Assumptions!I$72>=$D$8,Assumptions!I$72<$D$8+$E$8,$C$8="Financed"),$B$8/$E$8,0)+IF(AND(Assumptions!I$72>=$D$9,Assumptions!I$72<$D$9+$E$9,$C$9="Financed"),$B$9/$E$9,0)+IF(AND(Assumptions!I$72>=$D$10,Assumptions!I$72<$D$10+$E$10,$C$10="Financed"),$B$10/$E$10,0)) | J18: =(IF(AND(Assumptions!J$72>=$D$7,Assumptions!J$72<$D$7+$E$7,$C$7="Financed"),$B$7/$E$7,0)+IF(AND(Assumptions!J$72>=$D$8,Assumptions!J$72<$D$8+$E$8,$C$8="Financed"),$B$8/$E$8,0)+IF(AND(Assumptions!J$72>=$D$9,Assumptions!J$72<$D$9+$E$9,$C$9="Financed"),$B$9/$E$9,0)+IF(AND(Assumptions!J$72>=$D$10,Assumptions!J$72<$D$10+$E$10,$C$10="Financed"),$B$10/$E$10,0)) | K18: =(IF(AND(Assumptions!K$72>=$D$7,Assumptions!K$72<$D$7+$E$7,$C$7="Financed"),$B$7/$E$7,0)+IF(AND(Assumptions!K$72>=$D$8,Assumptions!K$72<$D$8+$E$8,$C$8="Financed"),$B$8/$E$8,0)+IF(AND(Assumptions!K$72>=$D$9,Assumptions!K$72<$D$9+$E$9,$C$9="Financed"),$B$9/$E$9,0)+IF(AND(Assumptions!K$72>=$D$10,Assumptions!K$72<$D$10+$E$10,$C$10="Financed"),$B$10/$E$10,0)) | L18: =(IF(AND(Assumptions!L$72>=$D$7,Assumptions!L$72<$D$7+$E$7,$C$7="Financed"),$B$7/$E$7,0)+IF(AND(Assumptions!L$72>=$D$8,Assumptions!L$72<$D$8+$E$8,$C$8="Financed"),$B$8/$E$8,0)+IF(AND(Assumptions!L$72>=$D$9,Assumptions!L$72<$D$9+$E$9,$C$9="Financed"),$B$9/$E$9,0)+IF(AND(Assumptions!L$72>=$D$10,Assumptions!L$72<$D$10+$E$10,$C$10="Financed"),$B$10/$E$10,0)) | ... DT18: =(IF(AND(Assumptions!DT$72>=$D$7,Assumptions!DT$72<$D$7+$E$7,$C$7="Financed"),$B$7/$E$7,0)+IF(AND(Assumptions!DT$72>=$D$8,Assumptions!DT$72<$D$8+$E$8,$C$8="Financed"),$B$8/$E$8,0)+IF(AND(Assumptions!DT$72>=$D$9,Assumptions!DT$72<$D$9+$E$9,$C$9="Financed"),$B$9/$E$9,0)+IF(AND(Assumptions!DT$72>=$D$10,Assumptions!DT$72<$D$10+$E$10,$C$10="Financed"),$B$10/$E$10,0))
A19: Retail rollover TI/LC ($/mo, neg) | E19: =-'Retail Revenue'!E$41 | F19: =-'Retail Revenue'!F$41 | G19: =-'Retail Revenue'!G$41 | H19: =-'Retail Revenue'!H$41 | I19: =-'Retail Revenue'!I$41 | J19: =-'Retail Revenue'!J$41 | K19: =-'Retail Revenue'!K$41 | L19: =-'Retail Revenue'!L$41 | ... DT19: =-'Retail Revenue'!DT$41
A20: Total capital outflow ($/mo, neg) | E20: =E$17+E$19 | F20: =F$17+F$19 | G20: =G$17+G$19 | H20: =H$17+H$19 | I20: =I$17+I$19 | J20: =J$17+J$19 | K20: =K$17+K$19 | L20: =L$17+L$19 | ... DT20: =DT$17+DT$19

Sheet Debt
A1: DEBT — Sizing (min-of), Single/Separate Loans, Refi
A2: Asset: | B2: =AssetName | D2: Run date: | E2: =RunDate | G2: Business plan: | H2: =BusinessPlanMode | J2: Hold (mo): | K2: =HoldMonths
A3: Model status: | B3: =ModelStatus
A5: Blended loan terms (Single Blended Loan mode)
A6: Max LTV (%) | B6: 0.65
A7: Max LTC (%) | B7: 0.7
A8: Min DSCR (x) | B8: 1.25
A9: Min Debt Yield (%) | B9: 0.085
A10: Fixed rate (%) | B10: 0.0575
A11: SOFR (%) | B11: 0.043
A12: Spread (bps) | B12: 250
A13: All-in rate (%) | B13: =IF(LoanRateType="Fixed",FixedRate,SOFR+SpreadBps/10000)
A14: IO period (months) | B14: 36
A15: Amortization (years) | B15: 30
A16: Financing cost (% of loan) | B16: 0.01
A17: Blended debt constant | B17: =LoanRate/12/(1-(1+LoanRate/12)^(-AmortYears*12))*12
A19: MF loan terms (Separate mode)
A20: Max LTV (%) | B20: 0.65
A21: Max LTC (%) | B21: 0.7
A22: Min DSCR (x) | B22: 1.25
A23: Min Debt Yield (%) | B23: 0.085
A24: Rate type (Fixed/Floating) | B24: Fixed
A25: Fixed rate (%) | B25: 0.056
A26: SOFR (%) | B26: 0.043
A27: Spread (bps) | B27: 250
A28: All-in rate (%) | B28: =IF(MFLoan_RateType="Fixed",MFLoan_FixedRate,MFLoan_SOFR+MFLoan_Spread/10000)
A29: IO period (months) | B29: 36
A30: Amortization (years) | B30: 30
A31: Financing cost (% of loan) | B31: 0.01
A32: Debt constant | B32: =MFLoan_Rate/12/(1-(1+MFLoan_Rate/12)^(-MFLoan_Amort*12))*12
A34: Retail loan terms (Separate mode)
A35: Max LTV (%) | B35: 0.65
A36: Max LTC (%) | B36: 0.7
A37: Min DSCR (x) | B37: 1.25
A38: Min Debt Yield (%) | B38: 0.085
A39: Rate type (Fixed/Floating) | B39: Fixed
A40: Fixed rate (%) | B40: 0.0625
A41: SOFR (%) | B41: 0.043
A42: Spread (bps) | B42: 250
A43: All-in rate (%) | B43: =IF(RTLoan_RateType="Fixed",RTLoan_FixedRate,RTLoan_SOFR+RTLoan_Spread/10000)
A44: IO period (months) | B44: 36
A45: Amortization (years) | B45: 30
A46: Financing cost (% of loan) | B46: 0.01
A47: Debt constant | B47: =RTLoan_Rate/12/(1-(1+RTLoan_Rate/12)^(-RTLoan_Amort*12))*12
A49: Sizing inputs — NOI, value, cost (component split drives Separate mode)
A50: Going-in NOI — total ($) | B50: =SUM('Monthly CF'!F$12:Q$12)
A51: Stabilized NOI — total ($) | B51: =SUM('Monthly CF'!R$12:AC$12)
A52: Going-in NOI — MF ($) | B52: =SUM('Monthly CF'!F$13:Q$13)
A53: Stabilized NOI — MF ($) | B53: =SUM('Monthly CF'!R$13:AC$13)
A54: Going-in NOI — Retail ($) | B54: =SUM('Monthly CF'!F$14:Q$14)
A55: Stabilized NOI — Retail ($) | B55: =SUM('Monthly CF'!R$14:AC$14)
A56: MF value (alloc. by going-in NOI share) | B56: =PurchasePrice*IFERROR(GoingInNOI_MF/GoingInNOI,0)
A57: Retail value (residual) | B57: =PurchasePrice-Value_MF
A58: MF cost (alloc. share) | B58: =TotalCost*IFERROR(GoingInNOI_MF/GoingInNOI,0)
A59: Retail cost (residual) | B59: =TotalCost-Cost_MF
A61: Loan sizing (min-of constraints; binding flag)
A62: Blend: max loan — LTV | B62: =IF(Use_LTV="On",PurchasePrice*MaxLTV,1000000000000000)
A63: Blend: max loan — LTC | B63: =IF(Use_LTC="On",TotalCost*MaxLTC,1000000000000000)
A64: Blend: max loan — DSCR | B64: =IF(Use_DSCR="On",GoingInNOI/(MinDSCR*DebtConstant),1000000000000000)
A65: Blend: max loan — Debt Yield | B65: =IF(Use_DY="On",GoingInNOI/MinDebtYield,1000000000000000)
A66: Blend: loan (MIN of active) | B66: =MIN(Blend_LTV,Blend_LTC,Blend_DSCRcap,Blend_DYcap,PurchasePrice)
A67: Blend: binding constraint | B67: =IF(BlendedLoan=Blend_LTV,"LTV",IF(BlendedLoan=Blend_LTC,"LTC",IF(BlendedLoan=Blend_DSCRcap,"DSCR",IF(BlendedLoan=Blend_DYcap,"Debt Yield","Value cap"))))
A69: MFLn: max loan — LTV | B69: =IF(Use_LTV="On",Value_MF*MFLoan_MaxLTV,1000000000000000)
A70: MFLn: max loan — LTC | B70: =IF(Use_LTC="On",Cost_MF*MFLoan_MaxLTC,1000000000000000)
A71: MFLn: max loan — DSCR | B71: =IF(Use_DSCR="On",GoingInNOI_MF/(MFLoan_MinDSCR*MFLoan_DebtConstant),1000000000000000)
A72: MFLn: max loan — Debt Yield | B72: =IF(Use_DY="On",GoingInNOI_MF/MFLoan_MinDY,1000000000000000)
A73: MFLn: loan (MIN of active) | B73: =MIN(MFLn_LTV,MFLn_LTC,MFLn_DSCRcap,MFLn_DYcap,Value_MF)
A74: MFLn: binding constraint | B74: =IF(MF_Loan=MFLn_LTV,"LTV",IF(MF_Loan=MFLn_LTC,"LTC",IF(MF_Loan=MFLn_DSCRcap,"DSCR",IF(MF_Loan=MFLn_DYcap,"Debt Yield","Value cap"))))
A76: RTLn: max loan — LTV | B76: =IF(Use_LTV="On",Value_Retail*RTLoan_MaxLTV,1000000000000000)
A77: RTLn: max loan — LTC | B77: =IF(Use_LTC="On",Cost_Retail*RTLoan_MaxLTC,1000000000000000)
A78: RTLn: max loan — DSCR | B78: =IF(Use_DSCR="On",GoingInNOI_Retail/(RTLoan_MinDSCR*RTLoan_DebtConstant),1000000000000000)
A79: RTLn: max loan — Debt Yield | B79: =IF(Use_DY="On",GoingInNOI_Retail/RTLoan_MinDY,1000000000000000)
A80: RTLn: loan (MIN of active) | B80: =MIN(RTLn_LTV,RTLn_LTC,RTLn_DSCRcap,RTLn_DYcap,Value_Retail)
A81: RTLn: binding constraint | B81: =IF(RT_Loan=RTLn_LTV,"LTV",IF(RT_Loan=RTLn_LTC,"LTC",IF(RT_Loan=RTLn_DSCRcap,"DSCR",IF(RT_Loan=RTLn_DYcap,"Debt Yield","Value cap"))))
A83: Active loans (A + B); structure-driven
A84: Loan A amount ($) | B84: =IF(DebtStructure="Separate MF + Retail Loans",MF_Loan,BlendedLoan)
A85: Loan B amount ($) | B85: =IF(DebtStructure="Separate MF + Retail Loans",RT_Loan,0)
A86: Loan A rate (%) | B86: =IF(DebtStructure="Separate MF + Retail Loans",MFLoan_Rate,LoanRate)
A87: Loan B rate (%) | B87: =IF(DebtStructure="Separate MF + Retail Loans",RTLoan_Rate,LoanRate)
A88: Loan A IO (months) | B88: =IF(DebtStructure="Separate MF + Retail Loans",MFLoan_IO,IOMonths)
A89: Loan B IO (months) | B89: =IF(DebtStructure="Separate MF + Retail Loans",RTLoan_IO,IOMonths)
A90: Loan A amort (years) | B90: =IF(DebtStructure="Separate MF + Retail Loans",MFLoan_Amort,AmortYears)
A91: Loan B amort (years) | B91: =IF(DebtStructure="Separate MF + Retail Loans",RTLoan_Amort,AmortYears)
A92: Property loan (A+B) ($) | B92: =LoanA_Amount+LoanB_Amount
A93: Committed loan incl. financed holdback ($) | B93: =PropertyLoan+FinancedCapBudget
A94: Binding constraint | B94: =IF(DebtStructure="Separate MF + Retail Loans","MF:"&MFLn_Binding&" / RT:"&RTLn_Binding,Blend_Binding)
A95: Financing costs ($) | B95: 0
A97: Refi (toggle #5) — refinances total balance into Loan A
A98: Refi month | B98: 36
A99: Refi cap on stabilized value (%) | B99: 0.055
A100: Refi LTV (%) | B100: 0.65
A101: Refi cost (% of new loan) | B101: 0.01
A102: Stabilized value (for refi) | B102: =StabNOI/RefiCap
A103: New refi loan | B103: =IF(RefiOn="On",MIN(StabValue*RefiLTV,StabNOI/(MinDSCR*DebtConstant)),0)
A106: MONTHLY DEBT SCHEDULE (Loan A + Loan B; B inert in Single mode)
A107: Month index | E107: =Assumptions!E$72 | F107: =Assumptions!F$72 | G107: =Assumptions!G$72 | H107: =Assumptions!H$72 | I107: =Assumptions!I$72 | J107: =Assumptions!J$72 | K107: =Assumptions!K$72 | L107: =Assumptions!L$72 | ... DT107: =Assumptions!DT$72
A108: Loan A: opening balance ($) | E108: =0 | F108: =E$114 | G108: =F$114 | H108: =G$114 | I108: =H$114 | J108: =I$114 | K108: =J$114 | L108: =K$114 | M108: =L$114 | ... DT108: =DS$114
A109: Loan A: draw ($) | E109: =LoanA_Amount | F109: =0+CapEx!F$18+IF(AND(RefiOn="On",Assumptions!F$72=RefiMonth),RefiLoan,0) | G109: =0+CapEx!G$18+IF(AND(RefiOn="On",Assumptions!G$72=RefiMonth),RefiLoan,0) | H109: =0+CapEx!H$18+IF(AND(RefiOn="On",Assumptions!H$72=RefiMonth),RefiLoan,0) | I109: =0+CapEx!I$18+IF(AND(RefiOn="On",Assumptions!I$72=RefiMonth),RefiLoan,0) | J109: =0+CapEx!J$18+IF(AND(RefiOn="On",Assumptions!J$72=RefiMonth),RefiLoan,0) | K109: =0+CapEx!K$18+IF(AND(RefiOn="On",Assumptions!K$72=RefiMonth),RefiLoan,0) | L109: =0+CapEx!L$18+IF(AND(RefiOn="On",Assumptions!L$72=RefiMonth),RefiLoan,0) | M109: =0+CapEx!M$18+IF(AND(RefiOn="On",Assumptions!M$72=RefiMonth),RefiLoan,0) | ... DT109: =0+CapEx!DT$18+IF(AND(RefiOn="On",Assumptions!DT$72=RefiMonth),RefiLoan,0)
A110: Loan A: interest ($) | E110: =E$108*LoanA_Rate/12*Assumptions!E$74 | F110: =F$108*LoanA_Rate/12*Assumptions!F$74 | G110: =G$108*LoanA_Rate/12*Assumptions!G$74 | H110: =H$108*LoanA_Rate/12*Assumptions!H$74 | I110: =I$108*LoanA_Rate/12*Assumptions!I$74 | J110: =J$108*LoanA_Rate/12*Assumptions!J$74 | K110: =K$108*LoanA_Rate/12*Assumptions!K$74 | L110: =L$108*LoanA_Rate/12*Assumptions!L$74 | ... DT110: =DT$108*LoanA_Rate/12*Assumptions!DT$74
A111: Loan A: principal ($) | E111: =IF(AND(Assumptions!E$74=1,Assumptions!E$72>LoanA_IO,E$108>0),MIN(E$108,PMT(LoanA_Rate/12,LoanA_Amort*12-LoanA_IO,-E$108)-E$110),0) | F111: =IF(AND(Assumptions!F$74=1,Assumptions!F$72>LoanA_IO,F$108>0),MIN(F$108,PMT(LoanA_Rate/12,LoanA_Amort*12-LoanA_IO,-F$108)-F$110),0) | G111: =IF(AND(Assumptions!G$74=1,Assumptions!G$72>LoanA_IO,G$108>0),MIN(G$108,PMT(LoanA_Rate/12,LoanA_Amort*12-LoanA_IO,-G$108)-G$110),0) | H111: =IF(AND(Assumptions!H$74=1,Assumptions!H$72>LoanA_IO,H$108>0),MIN(H$108,PMT(LoanA_Rate/12,LoanA_Amort*12-LoanA_IO,-H$108)-H$110),0) | I111: =IF(AND(Assumptions!I$74=1,Assumptions!I$72>LoanA_IO,I$108>0),MIN(I$108,PMT(LoanA_Rate/12,LoanA_Amort*12-LoanA_IO,-I$108)-I$110),0) | J111: =IF(AND(Assumptions!J$74=1,Assumptions!J$72>LoanA_IO,J$108>0),MIN(J$108,PMT(LoanA_Rate/12,LoanA_Amort*12-LoanA_IO,-J$108)-J$110),0) | K111: =IF(AND(Assumptions!K$74=1,Assumptions!K$72>LoanA_IO,K$108>0),MIN(K$108,PMT(LoanA_Rate/12,LoanA_Amort*12-LoanA_IO,-K$108)-K$110),0) | L111: =IF(AND(Assumptions!L$74=1,Assumptions!L$72>LoanA_IO,L$108>0),MIN(L$108,PMT(LoanA_Rate/12,LoanA_Amort*12-LoanA_IO,-L$108)-L$110),0) | ... DT111: =IF(AND(Assumptions!DT$74=1,Assumptions!DT$72>LoanA_IO,DT$108>0),MIN(DT$108,PMT(LoanA_Rate/12,LoanA_Amort*12-LoanA_IO,-DT$108)-DT$110),0)
...

Sheet Monthly CF
A1: MONTHLY CASH FLOW + ANNUAL ROLL-UP
A2: Asset: | B2: =AssetName | D2: Run date: | E2: =RunDate | G2: Business plan: | H2: =BusinessPlanMode | J2: Hold (mo): | K2: =HoldMonths
A3: Model status: | B3: =ModelStatus
A5: Month index | E5: =Assumptions!E$72 | F5: =Assumptions!F$72 | G5: =Assumptions!G$72 | H5: =Assumptions!H$72 | I5: =Assumptions!I$72 | J5: =Assumptions!J$72 | K5: =Assumptions!K$72 | L5: =Assumptions!L$72 | ... DT5: =Assumptions!DT$72
A6: Period date | E6: =Assumptions!E$73 | F6: =Assumptions!F$73 | G6: =Assumptions!G$73 | H6: =Assumptions!H$73 | I6: =Assumptions!I$73 | J6: =Assumptions!J$73 | K6: =Assumptions!K$73 | L6: =Assumptions!L$73 | ... DT6: =Assumptions!DT$73
A7: MF EGI | E7: ='MF Revenue'!E$114 | F7: ='MF Revenue'!F$114 | G7: ='MF Revenue'!G$114 | H7: ='MF Revenue'!H$114 | I7: ='MF Revenue'!I$114 | J7: ='MF Revenue'!J$114 | K7: ='MF Revenue'!K$114 | L7: ='MF Revenue'!L$114 | ... DT7: ='MF Revenue'!DT$114
A8: Retail EGI | E8: ='Retail Revenue'!E$40 | F8: ='Retail Revenue'!F$40 | G8: ='Retail Revenue'!G$40 | H8: ='Retail Revenue'!H$40 | I8: ='Retail Revenue'!I$40 | J8: ='Retail Revenue'!J$40 | K8: ='Retail Revenue'!K$40 | L8: ='Retail Revenue'!L$40 | ... DT8: ='Retail Revenue'!DT$40
A9: Total EGI | E9: =E$7+E$8 | F9: =F$7+F$8 | G9: =G$7+G$8 | H9: =H$7+H$8 | I9: =I$7+I$8 | J9: =J$7+J$8 | K9: =K$7+K$8 | L9: =L$7+L$8 | ... DT9: =DT$7+DT$8
A10: OpEx (excl. taxes) | E10: =OpEx!E$19 | F10: =OpEx!F$19 | G10: =OpEx!G$19 | H10: =OpEx!H$19 | I10: =OpEx!I$19 | J10: =OpEx!J$19 | K10: =OpEx!K$19 | L10: =OpEx!L$19 | ... DT10: =OpEx!DT$19
A11: Taxes | E11: =Taxes!E$12 | F11: =Taxes!F$12 | G11: =Taxes!G$12 | H11: =Taxes!H$12 | I11: =Taxes!I$12 | J11: =Taxes!J$12 | K11: =Taxes!K$12 | L11: =Taxes!L$12 | ... DT11: =Taxes!DT$12
A12: NOI | E12: =E$9+E$10+E$11 | F12: =F$9+F$10+F$11 | G12: =G$9+G$10+G$11 | H12: =H$9+H$10+H$11 | I12: =I$9+I$10+I$11 | J12: =J$9+J$10+J$11 | K12: =K$9+K$10+K$11 | L12: =L$9+L$10+L$11 | ... DT12: =DT$9+DT$10+DT$11
A13: MF NOI (allocated) | E13: =E$7+(E$10+E$11)*IFERROR(E$7/(E$7+E$8),0) | F13: =F$7+(F$10+F$11)*IFERROR(F$7/(F$7+F$8),0) | G13: =G$7+(G$10+G$11)*IFERROR(G$7/(G$7+G$8),0) | H13: =H$7+(H$10+H$11)*IFERROR(H$7/(H$7+H$8),0) | I13: =I$7+(I$10+I$11)*IFERROR(I$7/(I$7+I$8),0) | J13: =J$7+(J$10+J$11)*IFERROR(J$7/(J$7+J$8),0) | K13: =K$7+(K$10+K$11)*IFERROR(K$7/(K$7+K$8),0) | L13: =L$7+(L$10+L$11)*IFERROR(L$7/(L$7+L$8),0) | ... DT13: =DT$7+(DT$10+DT$11)*IFERROR(DT$7/(DT$7+DT$8),0)
A14: Retail NOI (allocated) | E14: =E$8+(E$10+E$11)*IFERROR(E$8/(E$7+E$8),0) | F14: =F$8+(F$10+F$11)*IFERROR(F$8/(F$7+F$8),0) | G14: =G$8+(G$10+G$11)*IFERROR(G$8/(G$7+G$8),0) | H14: =H$8+(H$10+H$11)*IFERROR(H$8/(H$7+H$8),0) | I14: =I$8+(I$10+I$11)*IFERROR(I$8/(I$7+I$8),0) | J14: =J$8+(J$10+J$11)*IFERROR(J$8/(J$7+J$8),0) | K14: =K$8+(K$10+K$11)*IFERROR(K$8/(K$7+K$8),0) | L14: =L$8+(L$10+L$11)*IFERROR(L$8/(L$7+L$8),0) | ... DT14: =DT$8+(DT$10+DT$11)*IFERROR(DT$8/(DT$7+DT$8),0)
A15: Replacement reserves | E15: =OpEx!E$18 | F15: =OpEx!F$18 | G15: =OpEx!G$18 | H15: =OpEx!H$18 | I15: =OpEx!I$18 | J15: =OpEx!J$18 | K15: =OpEx!K$18 | L15: =OpEx!L$18 | ... DT15: =OpEx!DT$18
A16: CapEx / TI/LC | E16: =CapEx!E$20 | F16: =CapEx!F$20 | G16: =CapEx!G$20 | H16: =CapEx!H$20 | I16: =CapEx!I$20 | J16: =CapEx!J$20 | K16: =CapEx!K$20 | L16: =CapEx!L$20 | ... DT16: =CapEx!DT$20
A17: Unlevered cash flow (ops) | E17: =E$12+E$15+E$16 | F17: =F$12+F$15+F$16 | G17: =G$12+G$15+G$16 | H17: =H$12+H$15+H$16 | I17: =I$12+I$15+I$16 | J17: =J$12+J$15+J$16 | K17: =K$12+K$15+K$16 | L17: =L$12+L$15+L$16 | ... DT17: =DT$12+DT$15+DT$16
A18: Debt service | E18: =-Debt!E$126 | F18: =-Debt!F$126 | G18: =-Debt!G$126 | H18: =-Debt!H$126 | I18: =-Debt!I$126 | J18: =-Debt!J$126 | K18: =-Debt!K$126 | L18: =-Debt!L$126 | ... DT18: =-Debt!DT$126
A19: Loan draws / refi events | E19: =Debt!E$127+Debt!E$128 | F19: =Debt!F$127+Debt!F$128 | G19: =Debt!G$127+Debt!G$128 | H19: =Debt!H$127+Debt!H$128 | I19: =Debt!I$127+Debt!I$128 | J19: =Debt!J$127+Debt!J$128 | K19: =Debt!K$127+Debt!K$128 | L19: =Debt!L$127+Debt!L$128 | ... DT19: =Debt!DT$127+Debt!DT$128
A20: Acquisition outflow (equity & price, mo 0) | E20: =-(PurchasePrice+PurchasePrice*ClosingCostPct+FinancingCosts) | F20: =0 | G20: =0 | H20: =0 | I20: =0 | J20: =0 | K20: =0 | L20: =0 | M20: =0 | ... DT20: =0
A21: Exit gross value ($) | E21: =IF(Assumptions!E$76=1,ExitGrossValue,0) | F21: =IF(Assumptions!F$76=1,ExitGrossValue,0) | G21: =IF(Assumptions!G$76=1,ExitGrossValue,0) | H21: =IF(Assumptions!H$76=1,ExitGrossValue,0) | I21: =IF(Assumptions!I$76=1,ExitGrossValue,0) | J21: =IF(Assumptions!J$76=1,ExitGrossValue,0) | K21: =IF(Assumptions!K$76=1,ExitGrossValue,0) | L21: =IF(Assumptions!L$76=1,ExitGrossValue,0) | ... DT21: =IF(Assumptions!DT$76=1,ExitGrossValue,0)
A22: Disposition costs ($) | E22: =IF(Assumptions!E$76=1,-ExitGrossValue*DispCostPct,0) | F22: =IF(Assumptions!F$76=1,-ExitGrossValue*DispCostPct,0) | G22: =IF(Assumptions!G$76=1,-ExitGrossValue*DispCostPct,0) | H22: =IF(Assumptions!H$76=1,-ExitGrossValue*DispCostPct,0) | I22: =IF(Assumptions!I$76=1,-ExitGrossValue*DispCostPct,0) | J22: =IF(Assumptions!J$76=1,-ExitGrossValue*DispCostPct,0) | K22: =IF(Assumptions!K$76=1,-ExitGrossValue*DispCostPct,0) | L22: =IF(Assumptions!L$76=1,-ExitGrossValue*DispCostPct,0) | ... DT22: =IF(Assumptions!DT$76=1,-ExitGrossValue*DispCostPct,0)
A23: Loan payoff at exit ($) | E23: =IF(Assumptions!E$76=1,-Debt!E$125,0) | F23: =IF(Assumptions!F$76=1,-Debt!F$125,0) | G23: =IF(Assumptions!G$76=1,-Debt!G$125,0) | H23: =IF(Assumptions!H$76=1,-Debt!H$125,0) | I23: =IF(Assumptions!I$76=1,-Debt!I$125,0) | J23: =IF(Assumptions!J$76=1,-Debt!J$125,0) | K23: =IF(Assumptions!K$76=1,-Debt!K$125,0) | L23: =IF(Assumptions!L$76=1,-Debt!L$125,0) | ... DT23: =IF(Assumptions!DT$76=1,-Debt!DT$125,0)
A24: Levered cash flow ($/mo) | E24: =E$17+E$18+E$19+E$20+E$21+E$22+E$23 | F24: =F$17+F$18+F$19+F$20+F$21+F$22+F$23 | G24: =G$17+G$18+G$19+G$20+G$21+G$22+G$23 | H24: =H$17+H$18+H$19+H$20+H$21+H$22+H$23 | I24: =I$17+I$18+I$19+I$20+I$21+I$22+I$23 | J24: =J$17+J$18+J$19+J$20+J$21+J$22+J$23 | K24: =K$17+K$18+K$19+K$20+K$21+K$22+K$23 | L24: =L$17+L$18+L$19+L$20+L$21+L$22+L$23 | ... DT24: =DT$17+DT$18+DT$19+DT$20+DT$21+DT$22+DT$23
A25: Unlevered total cash flow ($/mo) | E25: =E$17-(PurchasePrice+PurchasePrice*ClosingCostPct)+E$21+E$22 | F25: =F$17+F$21+F$22 | G25: =G$17+G$21+G$22 | H25: =H$17+H$21+H$22 | I25: =I$17+I$21+I$22 | J25: =J$17+J$21+J$22 | K25: =K$17+K$21+K$22 | L25: =L$17+L$21+L$22 | M25: =M$17+M$21+M$22 | ... DT25: =DT$17+DT$21+DT$22
A28: ANNUAL ROLL-UP (hold-year basis)
A29: Hold year | E29: 1 | F29: 2 | G29: 3 | H29: 4 | I29: 5 | J29: 6 | K29: 7 | L29: 8 | M29: 9 | N29: 10
A30: NOI | E30: =SUMIF(Assumptions!F$75:Q$75,1,F$12:Q$12) | F30: =SUMIF(Assumptions!R$75:AC$75,2,R$12:AC$12) | G30: =SUMIF(Assumptions!AD$75:AO$75,3,AD$12:AO$12) | H30: =SUMIF(Assumptions!AP$75:BA$75,4,AP$12:BA$12) | I30: =SUMIF(Assumptions!BB$75:BM$75,5,BB$12:BM$12) | J30: =SUMIF(Assumptions!BN$75:BY$75,6,BN$12:BY$12) | K30: =SUMIF(Assumptions!BZ$75:CK$75,7,BZ$12:CK$12) | L30: =SUMIF(Assumptions!CL$75:CW$75,8,CL$12:CW$12) | M30: =SUMIF(Assumptions!CX$75:DI$75,9,CX$12:DI$12) | N30: =SUMIF(Assumptions!DJ$75:DU$75,10,DJ$12:DU$12)
A31: Unlevered CF | E31: =SUMIF(Assumptions!F$75:Q$75,1,F$25:Q$25) | F31: =SUMIF(Assumptions!R$75:AC$75,2,R$25:AC$25) | G31: =SUMIF(Assumptions!AD$75:AO$75,3,AD$25:AO$25) | H31: =SUMIF(Assumptions!AP$75:BA$75,4,AP$25:BA$25) | I31: =SUMIF(Assumptions!BB$75:BM$75,5,BB$25:BM$25) | J31: =SUMIF(Assumptions!BN$75:BY$75,6,BN$25:BY$25) | K31: =SUMIF(Assumptions!BZ$75:CK$75,7,BZ$25:CK$25) | L31: =SUMIF(Assumptions!CL$75:CW$75,8,CL$25:CW$25) | M31: =SUMIF(Assumptions!CX$75:DI$75,9,CX$25:DI$25) | N31: =SUMIF(Assumptions!DJ$75:DU$75,10,DJ$25:DU$25)
A32: Levered CF | E32: =SUMIF(Assumptions!F$75:Q$75,1,F$24:Q$24) | F32: =SUMIF(Assumptions!R$75:AC$75,2,R$24:AC$24) | G32: =SUMIF(Assumptions!AD$75:AO$75,3,AD$24:AO$24) | H32: =SUMIF(Assumptions!AP$75:BA$75,4,AP$24:BA$24) | I32: =SUMIF(Assumptions!BB$75:BM$75,5,BB$24:BM$24) | J32: =SUMIF(Assumptions!BN$75:BY$75,6,BN$24:BY$24) | K32: =SUMIF(Assumptions!BZ$75:CK$75,7,BZ$24:CK$24) | L32: =SUMIF(Assumptions!CL$75:CW$75,8,CL$24:CW$24) | M32: =SUMIF(Assumptions!CX$75:DI$75,9,CX$24:DI$24) | N32: =SUMIF(Assumptions!DJ$75:DU$75,10,DJ$24:DU$24)

Sheet Waterfall
A1: EQUITY WATERFALL — American (gated by LP Present)
A2: Asset: | B2: =AssetName | D2: Run date: | E2: =RunDate | G2: Business plan: | H2: =BusinessPlanMode | J2: Hold (mo): | K2: =HoldMonths
A3: Model status: | B3: =ModelStatus
A5: Equity split & promote inputs
A6: LP capital split (%) | B6: 0.9
A7: GP capital split (%) | B7: =1-LP_Split
A8: GP co-invest (% of GP share) | B8: 1
A9: Preferred return (%, compounded) | B9: 0.08
A10: GP catch-up (%) | B10: 0.5
A11: ROC vs Pref order | B11: Sequential
A13: Promote / carry tiers (IRR hurdles -> LP/GP split)
A14: Tier hurdle IRR (upper) | B14: LP % | C14: GP %
A15: 0.08 | B15: 0.9 | C15: 0.1
A16: 0.12 | B16: 0.8 | C16: 0.2
A17: 0.15 | B17: 0.7 | C17: 0.3
A18: 9.99 | B18: 0.6 | C18: 0.4
A20: Fees (#15)
A21: Acquisition fee (% of price) | B21: 0.01
A22: AM fee rate (%) | B22: 0.0125
A23: Disposition fee (% of sale) | B23: 0.01
A24: Acquisition fee ($) | B24: =IF(AcqFeeOn="On",PurchasePrice*AcqFeePct,0)
A25: Disposition fee ($) | B25: =IF(DispFeeOn="On",ExitGrossValue*DispFeePct,0)
A26: AM fee basis amount ($/yr) | B26: =IF(AMFeeBasis="% of Cost",TotalCost,IF(AMFeeBasis="% of NOI",StabNOI,InitialEquity))
A27: AM fee ($/yr) | B27: =IF(AMFeeOn="On",AMFeeBaseAmt*AMFeeRate,0)
A29: Headline (project level)
A30: Total levered CF to equity ($) | B30: =SUM('Monthly CF'!E$24:DT$24)
A31: Project levered IRR (%) | B31: =XIRR('Monthly CF'!E$24:DT$24,'Monthly CF'!E$6:DT$6)
A32: Project equity multiple (x) | B32: =SUMIF('Monthly CF'!E$24:DT$24,">0")/MAX(1,-SUMIF('Monthly CF'!E$24:DT$24,"<0"))
A34: Monthly waterfall (cols E.. align to period header)
A35: Month index | E35: =Assumptions!E$72 | F35: =Assumptions!F$72 | G35: =Assumptions!G$72 | H35: =Assumptions!H$72 | I35: =Assumptions!I$72 | J35: =Assumptions!J$72 | K35: =Assumptions!K$72 | L35: =Assumptions!L$72 | ... DT35: =Assumptions!DT$72
A36: Levered CF (project) | E36: ='Monthly CF'!E$24 | F36: ='Monthly CF'!F$24 | G36: ='Monthly CF'!G$24 | H36: ='Monthly CF'!H$24 | I36: ='Monthly CF'!I$24 | J36: ='Monthly CF'!J$24 | K36: ='Monthly CF'!K$24 | L36: ='Monthly CF'!L$24 | ... DT36: ='Monthly CF'!DT$24
A37: Capital contributions | E37: =MAX(0,-E$36) | F37: =MAX(0,-F$36) | G37: =MAX(0,-G$36) | H37: =MAX(0,-H$36) | I37: =MAX(0,-I$36) | J37: =MAX(0,-J$36) | K37: =MAX(0,-K$36) | L37: =MAX(0,-L$36) | ... DT37: =MAX(0,-DT$36)
A38: Cash available to distribute | E38: =MAX(0,E$36) | F38: =MAX(0,F$36) | G38: =MAX(0,G$36) | H38: =MAX(0,H$36) | I38: =MAX(0,I$36) | J38: =MAX(0,J$36) | K38: =MAX(0,K$36) | L38: =MAX(0,L$36) | ... DT38: =MAX(0,DT$36)
A39: Pref accrued this period | E39: =(0+0)*((1+PrefRate)^(1/12)-1) | F39: =(E$52+E$53)*((1+PrefRate)^(1/12)-1) | G39: =(F$52+F$53)*((1+PrefRate)^(1/12)-1) | H39: =(G$52+G$53)*((1+PrefRate)^(1/12)-1) | I39: =(H$52+H$53)*((1+PrefRate)^(1/12)-1) | J39: =(I$52+I$53)*((1+PrefRate)^(1/12)-1) | K39: =(J$52+J$53)*((1+PrefRate)^(1/12)-1) | L39: =(K$52+K$53)*((1+PrefRate)^(1/12)-1) | M39: =(L$52+L$53)*((1+PrefRate)^(1/12)-1) | ... DT39: =(DS$52+DS$53)*((1+PrefRate)^(1/12)-1)
A40: Tier 1 — Return of Capital | E40: =MIN(E$38,0+E$37) | F40: =MIN(F$38,E$52+F$37) | G40: =MIN(G$38,F$52+G$37) | H40: =MIN(H$38,G$52+H$37) | I40: =MIN(I$38,H$52+I$37) | J40: =MIN(J$38,I$52+J$37) | K40: =MIN(K$38,J$52+K$37) | L40: =MIN(L$38,K$52+L$37) | M40: =MIN(M$38,L$52+M$37) | ... DT40: =MIN(DT$38,DS$52+DT$37)
A41: Tier 2 — Preferred return | E41: =MIN(E$38-E$40,0+E$39) | F41: =MIN(F$38-F$40,E$53+F$39) | G41: =MIN(G$38-G$40,F$53+G$39) | H41: =MIN(H$38-H$40,G$53+H$39) | I41: =MIN(I$38-I$40,H$53+I$39) | J41: =MIN(J$38-J$40,I$53+J$39) | K41: =MIN(K$38-K$40,J$53+K$39) | L41: =MIN(L$38-L$40,K$53+L$39) | M41: =MIN(M$38-M$40,L$53+M$39) | ... DT41: =MIN(DT$38-DT$40,DS$53+DT$39)
A42: Tier 3 — Catch-up (total) | E42: =IF(GPCatchUpOn="On",MIN(E$38-E$40-E$41,MAX(0,(INDEX(CarryTiers,2,3)/INDEX(CarryTiers,2,2))*(0+E$41)-0)/MAX(CatchUpPct,0.000001)),0) | F42: =IF(GPCatchUpOn="On",MIN(F$38-F$40-F$41,MAX(0,(INDEX(CarryTiers,2,3)/INDEX(CarryTiers,2,2))*(E$55+F$41)-E$56)/MAX(CatchUpPct,0.000001)),0) | G42: =IF(GPCatchUpOn="On",MIN(G$38-G$40-G$41,MAX(0,(INDEX(CarryTiers,2,3)/INDEX(CarryTiers,2,2))*(F$55+G$41)-F$56)/MAX(CatchUpPct,0.000001)),0) | H42: =IF(GPCatchUpOn="On",MIN(H$38-H$40-H$41,MAX(0,(INDEX(CarryTiers,2,3)/INDEX(CarryTiers,2,2))*(G$55+H$41)-G$56)/MAX(CatchUpPct,0.000001)),0) | I42: =IF(GPCatchUpOn="On",MIN(I$38-I$40-I$41,MAX(0,(INDEX(CarryTiers,2,3)/INDEX(CarryTiers,2,2))*(H$55+I$41)-H$56)/MAX(CatchUpPct,0.000001)),0) | J42: =IF(GPCatchUpOn="On",MIN(J$38-J$40-J$41,MAX(0,(INDEX(CarryTiers,2,3)/INDEX(CarryTiers,2,2))*(I$55+J$41)-I$56)/MAX(CatchUpPct,0.000001)),0) | K42: =IF(GPCatchUpOn="On",MIN(K$38-K$40-K$41,MAX(0,(INDEX(CarryTiers,2,3)/INDEX(CarryTiers,2,2))*(J$55+K$41)-J$56)/MAX(CatchUpPct,0.000001)),0) | L42: =IF(GPCatchUpOn="On",MIN(L$38-L$40-L$41,MAX(0,(INDEX(CarryTiers,2,3)/INDEX(CarryTiers,2,2))*(K$55+L$41)-K$56)/MAX(CatchUpPct,0.000001)),0) | M42: =IF(GPCatchUpOn="On",MIN(M$38-M$40-M$41,MAX(0,(INDEX(CarryTiers,2,3)/INDEX(CarryTiers,2,2))*(L$55+M$41)-L$56)/MAX(CatchUpPct,0.000001)),0) | ... DT42: =IF(GPCatchUpOn="On",MIN(DT$38-DT$40-DT$41,MAX(0,(INDEX(CarryTiers,2,3)/INDEX(CarryTiers,2,2))*(DS$55+DT$41)-DS$56)/MAX(CatchUpPct,0.000001)),0)
A43: Catch-up to GP | E43: =E$42*CatchUpPct | F43: =F$42*CatchUpPct | G43: =G$42*CatchUpPct | H43: =H$42*CatchUpPct | I43: =I$42*CatchUpPct | J43: =J$42*CatchUpPct | K43: =K$42*CatchUpPct | L43: =L$42*CatchUpPct | ... DT43: =DT$42*CatchUpPct
A44: Catch-up to investors | E44: =E$42*(1-CatchUpPct) | F44: =F$42*(1-CatchUpPct) | G44: =G$42*(1-CatchUpPct) | H44: =H$42*(1-CatchUpPct) | I44: =I$42*(1-CatchUpPct) | J44: =J$42*(1-CatchUpPct) | K44: =K$42*(1-CatchUpPct) | L44: =L$42*(1-CatchUpPct) | ... DT44: =DT$42*(1-CatchUpPct)
A45: Investor balance @ tier-2 hurdle | E45: =0*(1+((1+INDEX(CarryTiers,2,1))^(1/12)-1))+E$37 | F45: =E$45*(1+((1+INDEX(CarryTiers,2,1))^(1/12)-1))+F$37 | G45: =F$45*(1+((1+INDEX(CarryTiers,2,1))^(1/12)-1))+G$37 | H45: =G$45*(1+((1+INDEX(CarryTiers,2,1))^(1/12)-1))+H$37 | I45: =H$45*(1+((1+INDEX(CarryTiers,2,1))^(1/12)-1))+I$37 | J45: =I$45*(1+((1+INDEX(CarryTiers,2,1))^(1/12)-1))+J$37 | K45: =J$45*(1+((1+INDEX(CarryTiers,2,1))^(1/12)-1))+K$37 | L45: =K$45*(1+((1+INDEX(CarryTiers,2,1))^(1/12)-1))+L$37 | M45: =L$45*(1+((1+INDEX(CarryTiers,2,1))^(1/12)-1))+M$37 | ... DT45: =DS$45*(1+((1+INDEX(CarryTiers,2,1))^(1/12)-1))+DT$37
A46: Investor balance @ tier-3 hurdle | E46: =0*(1+((1+INDEX(CarryTiers,3,1))^(1/12)-1))+E$37 | F46: =E$46*(1+((1+INDEX(CarryTiers,3,1))^(1/12)-1))+F$37 | G46: =F$46*(1+((1+INDEX(CarryTiers,3,1))^(1/12)-1))+G$37 | H46: =G$46*(1+((1+INDEX(CarryTiers,3,1))^(1/12)-1))+H$37 | I46: =H$46*(1+((1+INDEX(CarryTiers,3,1))^(1/12)-1))+I$37 | J46: =I$46*(1+((1+INDEX(CarryTiers,3,1))^(1/12)-1))+J$37 | K46: =J$46*(1+((1+INDEX(CarryTiers,3,1))^(1/12)-1))+K$37 | L46: =K$46*(1+((1+INDEX(CarryTiers,3,1))^(1/12)-1))+L$37 | M46: =L$46*(1+((1+INDEX(CarryTiers,3,1))^(1/12)-1))+M$37 | ... DT46: =DS$46*(1+((1+INDEX(CarryTiers,3,1))^(1/12)-1))+DT$37
A47: Tier 4a — residual to hurdle 2 | E47: =MIN((E$38-E$40-E$41-E$42),MAX(0,E$45-(0+E$40+E$41+E$44))/INDEX(CarryTiers,2,2)) | F47: =MIN((F$38-F$40-F$41-F$42),MAX(0,F$45-(E$54+F$40+F$41+F$44))/INDEX(CarryTiers,2,2)) | G47: =MIN((G$38-G$40-G$41-G$42),MAX(0,G$45-(F$54+G$40+G$41+G$44))/INDEX(CarryTiers,2,2)) | H47: =MIN((H$38-H$40-H$41-H$42),MAX(0,H$45-(G$54+H$40+H$41+H$44))/INDEX(CarryTiers,2,2)) | I47: =MIN((I$38-I$40-I$41-I$42),MAX(0,I$45-(H$54+I$40+I$41+I$44))/INDEX(CarryTiers,2,2)) | J47: =MIN((J$38-J$40-J$41-J$42),MAX(0,J$45-(I$54+J$40+J$41+J$44))/INDEX(CarryTiers,2,2)) | K47: =MIN((K$38-K$40-K$41-K$42),MAX(0,K$45-(J$54+K$40+K$41+K$44))/INDEX(CarryTiers,2,2)) | L47: =MIN((L$38-L$40-L$41-L$42),MAX(0,L$45-(K$54+L$40+L$41+L$44))/INDEX(CarryTiers,2,2)) | M47: =MIN((M$38-M$40-M$41-M$42),MAX(0,M$45-(L$54+M$40+M$41+M$44))/INDEX(CarryTiers,2,2)) | ... DT47: =MIN((DT$38-DT$40-DT$41-DT$42),MAX(0,DT$45-(DS$54+DT$40+DT$41+DT$44))/INDEX(CarryTiers,2,2))
A48: Tier 4b — residual to hurdle 3 | E48: =MIN((E$38-E$40-E$41-E$42)-E$47,MAX(0,E$46-((0+E$40+E$41+E$44)+INDEX(CarryTiers,2,2)*E$47))/INDEX(CarryTiers,3,2)) | F48: =MIN((F$38-F$40-F$41-F$42)-F$47,MAX(0,F$46-((E$54+F$40+F$41+F$44)+INDEX(CarryTiers,2,2)*F$47))/INDEX(CarryTiers,3,2)) | G48: =MIN((G$38-G$40-G$41-G$42)-G$47,MAX(0,G$46-((F$54+G$40+G$41+G$44)+INDEX(CarryTiers,2,2)*G$47))/INDEX(CarryTiers,3,2)) | H48: =MIN((H$38-H$40-H$41-H$42)-H$47,MAX(0,H$46-((G$54+H$40+H$41+H$44)+INDEX(CarryTiers,2,2)*H$47))/INDEX(CarryTiers,3,2)) | I48: =MIN((I$38-I$40-I$41-I$42)-I$47,MAX(0,I$46-((H$54+I$40+I$41+I$44)+INDEX(CarryTiers,2,2)*I$47))/INDEX(CarryTiers,3,2)) | J48: =MIN((J$38-J$40-J$41-J$42)-J$47,MAX(0,J$46-((I$54+J$40+J$41+J$44)+INDEX(CarryTiers,2,2)*J$47))/INDEX(CarryTiers,3,2)) | K48: =MIN((K$38-K$40-K$41-K$42)-K$47,MAX(0,K$46-((J$54+K$40+K$41+K$44)+INDEX(CarryTiers,2,2)*K$47))/INDEX(CarryTiers,3,2)) | L48: =MIN((L$38-L$40-L$41-L$42)-L$47,MAX(0,L$46-((K$54+L$40+L$41+L$44)+INDEX(CarryTiers,2,2)*L$47))/INDEX(CarryTiers,3,2)) | M48: =MIN((M$38-M$40-M$41-M$42)-M$47,MAX(0,M$46-((L$54+M$40+M$41+M$44)+INDEX(CarryTiers,2,2)*M$47))/INDEX(CarryTiers,3,2)) | ... DT48: =MIN((DT$38-DT$40-DT$41-DT$42)-DT$47,MAX(0,DT$46-((DS$54+DT$40+DT$41+DT$44)+INDEX(CarryTiers,2,2)*DT$47))/INDEX(CarryTiers,3,2))
A49: Tier 4c — residual above hurdle 3 | E49: =(E$38-E$40-E$41-E$42)-E$47-E$48 | F49: =(F$38-F$40-F$41-F$42)-F$47-F$48 | G49: =(G$38-G$40-G$41-G$42)-G$47-G$48 | H49: =(H$38-H$40-H$41-H$42)-H$47-H$48 | I49: =(I$38-I$40-I$41-I$42)-I$47-I$48 | J49: =(J$38-J$40-J$41-J$42)-J$47-J$48 | K49: =(K$38-K$40-K$41-K$42)-K$47-K$48 | L49: =(L$38-L$40-L$41-L$42)-L$47-L$48 | ... DT49: =(DT$38-DT$40-DT$41-DT$42)-DT$47-DT$48
A50: Investor distribution (total) | E50: =E$40+E$41+E$44+INDEX(CarryTiers,2,2)*E$47+INDEX(CarryTiers,3,2)*E$48+INDEX(CarryTiers,4,2)*E$49 | F50: =F$40+F$41+F$44+INDEX(CarryTiers,2,2)*F$47+INDEX(CarryTiers,3,2)*F$48+INDEX(CarryTiers,4,2)*F$49 | G50: =G$40+G$41+G$44+INDEX(CarryTiers,2,2)*G$47+INDEX(CarryTiers,3,2)*G$48+INDEX(CarryTiers,4,2)*G$49 | H50: =H$40+H$41+H$44+INDEX(CarryTiers,2,2)*H$47+INDEX(CarryTiers,3,2)*H$48+INDEX(CarryTiers,4,2)*H$49 | I50: =I$40+I$41+I$44+INDEX(CarryTiers,2,2)*I$47+INDEX(CarryTiers,3,2)*I$48+INDEX(CarryTiers,4,2)*I$49 | J50: =J$40+J$41+J$44+INDEX(CarryTiers,2,2)*J$47+INDEX(CarryTiers,3,2)*J$48+INDEX(CarryTiers,4,2)*J$49 | K50: =K$40+K$41+K$44+INDEX(CarryTiers,2,2)*K$47+INDEX(CarryTiers,3,2)*K$48+INDEX(CarryTiers,4,2)*K$49 | L50: =L$40+L$41+L$44+INDEX(CarryTiers,2,2)*L$47+INDEX(CarryTiers,3,2)*L$48+INDEX(CarryTiers,4,2)*L$49 | ... DT50: =DT$40+DT$41+DT$44+INDEX(CarryTiers,2,2)*DT$47+INDEX(CarryTiers,3,2)*DT$48+INDEX(CarryTiers,4,2)*DT$49
A51: GP promote (catch-up + carry) | E51: =E$43+INDEX(CarryTiers,2,3)*E$47+INDEX(CarryTiers,3,3)*E$48+INDEX(CarryTiers,4,3)*E$49 | F51: =F$43+INDEX(CarryTiers,2,3)*F$47+INDEX(CarryTiers,3,3)*F$48+INDEX(CarryTiers,4,3)*F$49 | G51: =G$43+INDEX(CarryTiers,2,3)*G$47+INDEX(CarryTiers,3,3)*G$48+INDEX(CarryTiers,4,3)*G$49 | H51: =H$43+INDEX(CarryTiers,2,3)*H$47+INDEX(CarryTiers,3,3)*H$48+INDEX(CarryTiers,4,3)*H$49 | I51: =I$43+INDEX(CarryTiers,2,3)*I$47+INDEX(CarryTiers,3,3)*I$48+INDEX(CarryTiers,4,3)*I$49 | J51: =J$43+INDEX(CarryTiers,2,3)*J$47+INDEX(CarryTiers,3,3)*J$48+INDEX(CarryTiers,4,3)*J$49 | K51: =K$43+INDEX(CarryTiers,2,3)*K$47+INDEX(CarryTiers,3,3)*K$48+INDEX(CarryTiers,4,3)*K$49 | L51: =L$43+INDEX(CarryTiers,2,3)*L$47+INDEX(CarryTiers,3,3)*L$48+INDEX(CarryTiers,4,3)*L$49 | ... DT51: =DT$43+INDEX(CarryTiers,2,3)*DT$47+INDEX(CarryTiers,3,3)*DT$48+INDEX(CarryTiers,4,3)*DT$49
A52: Unreturned capital (end) | E52: =0+E$37-E$40 | F52: =E$52+F$37-F$40 | G52: =F$52+G$37-G$40 | H52: =G$52+H$37-H$40 | I52: =H$52+I$37-I$40 | J52: =I$52+J$37-J$40 | K52: =J$52+K$37-K$40 | L52: =K$52+L$37-L$40 | M52: =L$52+M$37-M$40 | ... DT52: =DS$52+DT$37-DT$40
A53: Pref balance (end) | E53: =0+E$39-E$41 | F53: =E$53+F$39-F$41 | G53: =F$53+G$39-G$41 | H53: =G$53+H$39-H$41 | I53: =H$53+I$39-I$41 | J53: =I$53+J$39-J$41 | K53: =J$53+K$39-K$41 | L53: =K$53+L$39-L$41 | M53: =L$53+M$39-M$41 | ... DT53: =DS$53+DT$39-DT$41
A54: Investor cumulative dist (end) | E54: =0+E$50 | F54: =E$54+F$50 | G54: =F$54+G$50 | H54: =G$54+H$50 | I54: =H$54+I$50 | J54: =I$54+J$50 | K54: =J$54+K$50 | L54: =K$54+L$50 | M54: =L$54+M$50 | ... DT54: =DS$54+DT$50
A55: Cumulative pref paid (end) | E55: =0+E$41 | F55: =E$55+F$41 | G55: =F$55+G$41 | H55: =G$55+H$41 | I55: =H$55+I$41 | J55: =I$55+J$41 | K55: =J$55+K$41 | L55: =K$55+L$41 | M55: =L$55+M$41 | ... DT55: =DS$55+DT$41
A56: Cumulative catch-up to GP (end) | E56: =0+E$43 | F56: =E$56+F$43 | G56: =F$56+G$43 | H56: =G$56+H$43 | I56: =H$56+I$43 | J56: =I$56+J$43 | K56: =J$56+K$43 | L56: =K$56+L$43 | M56: =L$56+M$43 | ... DT56: =DS$56+DT$43
A57: LP distribution | E57: =IF(LP_Present="No",0,E$50*(LP_Split+GP_Split*(1-GP_CoInvest))) | F57: =IF(LP_Present="No",0,F$50*(LP_Split+GP_Split*(1-GP_CoInvest))) | G57: =IF(LP_Present="No",0,G$50*(LP_Split+GP_Split*(1-GP_CoInvest))) | H57: =IF(LP_Present="No",0,H$50*(LP_Split+GP_Split*(1-GP_CoInvest))) | I57: =IF(LP_Present="No",0,I$50*(LP_Split+GP_Split*(1-GP_CoInvest))) | J57: =IF(LP_Present="No",0,J$50*(LP_Split+GP_Split*(1-GP_CoInvest))) | K57: =IF(LP_Present="No",0,K$50*(LP_Split+GP_Split*(1-GP_CoInvest))) | L57: =IF(LP_Present="No",0,L$50*(LP_Split+GP_Split*(1-GP_CoInvest))) | ... DT57: =IF(LP_Present="No",0,DT$50*(LP_Split+GP_Split*(1-GP_CoInvest)))
A58: GP co-invest distribution | E58: =IF(LP_Present="No",0,E$50*(GP_Split*GP_CoInvest)) | F58: =IF(LP_Present="No",0,F$50*(GP_Split*GP_CoInvest)) | G58: =IF(LP_Present="No",0,G$50*(GP_Split*GP_CoInvest)) | H58: =IF(LP_Present="No",0,H$50*(GP_Split*GP_CoInvest)) | I58: =IF(LP_Present="No",0,I$50*(GP_Split*GP_CoInvest)) | J58: =IF(LP_Present="No",0,J$50*(GP_Split*GP_CoInvest)) | K58: =IF(LP_Present="No",0,K$50*(GP_Split*GP_CoInvest)) | L58: =IF(LP_Present="No",0,L$50*(GP_Split*GP_CoInvest)) | ... DT58: =IF(LP_Present="No",0,DT$50*(GP_Split*GP_CoInvest))
A59: GP distribution (co-invest + promote) | E59: =IF(LP_Present="No",E$38,E$58+E$51) | F59: =IF(LP_Present="No",F$38,F$58+F$51) | G59: =IF(LP_Present="No",G$38,G$58+G$51) | H59: =IF(LP_Present="No",H$38,H$58+H$51) | I59: =IF(LP_Present="No",I$38,I$58+I$51) | J59: =IF(LP_Present="No",J$38,J$58+J$51) | K59: =IF(LP_Present="No",K$38,K$58+K$51) | L59: =IF(LP_Present="No",L$38,L$58+L$51) | ... DT59: =IF(LP_Present="No",DT$38,DT$58+DT$51)
A60: LP cash flow (contrib + dist) | E60: =IF(LP_Present="No",0,-E$37*(LP_Split+GP_Split*(1-GP_CoInvest))+E$57) | F60: =IF(LP_Present="No",0,-F$37*(LP_Split+GP_Split*(1-GP_CoInvest))+F$57) | G60: =IF(LP_Present="No",0,-G$37*(LP_Split+GP_Split*(1-GP_CoInvest))+G$57) | H60: =IF(LP_Present="No",0,-H$37*(LP_Split+GP_Split*(1-GP_CoInvest))+H$57) | I60: =IF(LP_Present="No",0,-I$37*(LP_Split+GP_Split*(1-GP_CoInvest))+I$57) | J60: =IF(LP_Present="No",0,-J$37*(LP_Split+GP_Split*(1-GP_CoInvest))+J$57) | K60: =IF(LP_Present="No",0,-K$37*(LP_Split+GP_Split*(1-GP_CoInvest))+K$57) | L60: =IF(LP_Present="No",0,-L$37*(LP_Split+GP_Split*(1-GP_CoInvest))+L$57) | ... DT60: =IF(LP_Present="No",0,-DT$37*(LP_Split+GP_Split*(1-GP_CoInvest))+DT$57)
A61: GP cash flow (contrib + dist) | E61: =IF(LP_Present="No",E$36,-E$37*(GP_Split*GP_CoInvest)+E$59) | F61: =IF(LP_Present="No",F$36,-F$37*(GP_Split*GP_CoInvest)+F$59) | G61: =IF(LP_Present="No",G$36,-G$37*(GP_Split*GP_CoInvest)+G$59) | H61: =IF(LP_Present="No",H$36,-H$37*(GP_Split*GP_CoInvest)+H$59) | I61: =IF(LP_Present="No",I$36,-I$37*(GP_Split*GP_CoInvest)+I$59) | J61: =IF(LP_Present="No",J$36,-J$37*(GP_Split*GP_CoInvest)+J$59) | K61: =IF(LP_Present="No",K$36,-K$37*(GP_Split*GP_CoInvest)+K$59) | L61: =IF(LP_Present="No",L$36,-L$37*(GP_Split*GP_CoInvest)+L$59) | ... DT61: =IF(LP_Present="No",DT$36,-DT$37*(GP_Split*GP_CoInvest)+DT$59)
A63: Distribution results & partner returns
A64: LP distributions ($) | B64: =SUM(E$57:DT$57)
A65: GP distributions ($) | B65: =SUM(E$59:DT$59)
A66: GP promote ($) | B66: =SUM(E$51:DT$51)
A67: LP IRR (%) | B67: =IFERROR(XIRR(E$60:DT$60,'Monthly CF'!E$6:DT$6),0)
A68: GP IRR (%) | B68: =IFERROR(XIRR(E$61:DT$61,'Monthly CF'!E$6:DT$6),0)
A69: LP equity multiple (x) | B69: =SUMIF(E$60:DT$60,">0")/MAX(1,-SUMIF(E$60:DT$60,"<0"))
A70: Sponsor / single-sponsor levered return (%) | B70: =IF(LP_Present="No",LeveredIRR,GP_IRR)
A71: Check: SUM(LP CF)+SUM(GP CF) = project levered CF | B71: =SUM(E$60:DT$60)+SUM(E$61:DT$61)

Sheet Sensitivities
A1: SENSITIVITIES — Phase 1 stub (live data tables built in Phase 2)
A2: Asset: | B2: =AssetName | D2: Run date: | E2: =RunDate | G2: Business plan: | H2: =BusinessPlanMode | J2: Hold (mo): | K2: =HoldMonths
A3: Model status: | B3: =ModelStatus
A4: Output anchors (Phase 2 sets row/col input cells via Data Table):
A5: Levered IRR anchor | B5: =LeveredIRR
A6: Equity multiple anchor | B6: =EquityMultiple
A7: Unlevered IRR anchor | B7: =UnleveredIRR
A9: Grid 1: Exit cap (rows) x MF rent growth Y1 (cols) -> Levered IRR
A10: =Sens_LIRR | B10: 0.02 | C10: 0.03 | D10: 0.04 | E10: 0.05 | F10: 0.06
A11: 0.045
A12: 0.05
A13: 0.055
A14: 0.06
A15: 0.065
A17: DATA TABLE inputs: Row input cell = Assumptions!$E$56 (MF rent growth Y1) ; Column input cell = ExitCapBlended (Assumptions!$B$13)
A19: Grid 2: Purchase price (rows) x exit cap (cols) -> Levered IRR
A20: =Sens_LIRR | B20: 0.045 | C20: 0.05 | D20: 0.055 | E20: 0.06 | F20: 0.065
A21: 40000000
A22: 44000000
A23: 48000000
A24: 52000000
A25: 56000000
A27: DATA TABLE inputs: Row input cell = ExitCapBlended (Assumptions!$B$13) ; Column input cell = InputPrice (Assumptions!$B$6)
A29: Grid 3 (one-way): Disposition date -> Levered IRR & EM
A30: Disp date | B30: =Sens_LIRR | C30: =Sens_EM
A31: =EDATE(DispositionDate,-24)
A32: =EDATE(DispositionDate,-12)
A33: =EDATE(DispositionDate,0)
A34: =EDATE(DispositionDate,12)
A35: =EDATE(DispositionDate,24)
A37: DATA TABLE input (one-variable, dates run down the column): Column input cell = DispositionDate (Control Panel!$B$9)

Sheet IC One-Pager
A1: INVESTMENT COMMITTEE — One-Pager
A2: Asset: | B2: =AssetName | D2: Run date: | E2: =RunDate | G2: Business plan: | H2: =BusinessPlanMode | J2: Hold (mo): | K2: =HoldMonths
A3: Model status: | B3: =ModelStatus
A5: Deal snapshot
A6: Asset | B6: =AssetName | C6: Business plan | D6: =BusinessPlanMode
A7: Units | B7: =MF_UnitCount | C7: Retail GLA | D7: =Retail_GLA
A8: Purchase price | B8: =PurchasePrice | C8: $/unit | D8: =PurchasePrice/MF_UnitCount
A9: Going-in cap | B9: =GoingInCap | C9: Stabilized cap | D9: =StabCap
A11: Sources & Uses
A12: Loan | B12: =LoanAmount | C12: Equity | D12: =InitialEquity
A13: Total cost | B13: =TotalCost | C13: Binding constraint | D13: =BindingConstraint
A15: Returns
A16: Unlevered IRR | B16: =UnleveredIRR | C16: Levered IRR | D16: =LeveredIRR
A17: Equity multiple | B17: =EquityMultiple | C17: Yield-on-cost | D17: =YieldOnCost
A18: Exit cap | B18: =ExitCapBlended | C18: Development spread (bps) | D18: =DevSpread
A19: LP IRR | B19: =LP_IRR | C19: GP IRR | D19: =GP_IRR
A21: Debt terms
A22: Loan rate | B22: =LoanRate | C22: Amort (yrs) | D22: =AmortYears
A23: IO (mo) | B23: =IOMonths | C23: Refi | D23: =RefiOn
A25: Key assumptions / risks
A26: Exit NOI basis | B26: =ExitNOIBasis
A27: Tax method | B27: =TaxMethod
A28: LP present | B28: =LP_Present
